Workbook

Sheet Drivers
B2: X | C2: ="Financial Statement Model for "&D5 -> Financial Statement Model for StandardAero
C3: $ in thousands except per share | N3: Comments
C5: Company name | D5: StandardAero
C6: Ticker | D6: SARO
C7: Latest closing share price | D7: 25.59
C8: Latest closing share price date | D8: 46119
C9: Latest fiscal year end date | D9: 46022
C10: Shares outstanding (millions) | D10: 334294 | N10: Outstanding at Dec 31, 2025 per 10-K BS. Jan 2026 repurchase of 1,637k shares (subsequent event) reduces to 332,657k.
C11: Case | D11: Description | F11: Source
C12: 2 | D12: =OFFSET(D12,$C$12,) -> [Case 2] | F12: =OFFSET(F12,$C$12,) -> Investment Case
C13: 1 | D13: [Case 1] | F13: Management Case
C14: 2 | D14: [Case 2] | F14: Investment Case
C15: 3 | D15: [Case 3] | F15: Downside Projection
C17: Growth rates & margins
C18: Fiscal year | E18: 2023 | F18: 2024 | G18: 2025 | H18: 2026 | I18: 2027 | J18: 2028 | K18: 2029 | L18: 2030
C19: Fiscal year end date | E19: 45291 | F19: 45657 | G19: 46022 | H19: 46387 | I19: 46752 | J19: 47118 | K19: 47483 | L19: 47848
C21: Revenue growth | F21: =(Model!F9-Model!E9)/Model!E9 -> 0.14767369 | G21: =(Model!H9-Model!F9)/Model!F9 -> 0.15759512 | H21: =(Model!I9-Model!H9)/Model!H9 -> 0.12467503 | I21: =(Model!J9-Model!I9)/Model!I9 -> 0.13607751 | J21: =(Model!K9-Model!J9)/Model!J9 -> 0.12136802 | K21: =(Model!L9-Model!K9)/Model!K9 -> 0.1120143 | L21: =(Model!M9-Model!L9)/Model!L9 -> 0.094108201 | N21: LEAP/CFM56 shop visits ramping; ~80% of revenue under long-term agreements; aging installed base drives MRO demand through 2030; military spending elevated due to geopolitical tensions; business aviation fleet growth
C23: Engine Service growth rate | F23: =OFFSET(F23,Drivers!$C$12,) -> 0.14688652 | G23: =OFFSET(G23,Drivers!$C$12,) -> 0.15269168 | H23: =OFFSET(H23,Drivers!$C$12,) -> 0.12 | I23: =OFFSET(I23,Drivers!$C$12,) -> 0.13 | J23: =OFFSET(J23,Drivers!$C$12,) -> 0.11 | K23: =OFFSET(K23,Drivers!$C$12,) -> 0.1 | L23: =OFFSET(L23,Drivers!$C$12,) -> 0.08
C24: =Drivers!$C$13 -> 1 | D24: =Drivers!$D$13 -> [Case 1] | F24: =(Model!F$6-Model!E$6)/Model!E$6 -> 0.14688652 | G24: =(Model!H$6-Model!F$6)/Model!F$6 -> 0.15269168 | H24: 0.145 | I24: 0.125 | J24: 0.115 | K24: 0.105 | L24: 0.1
C25: =Drivers!$C$14 -> 2 | D25: =Drivers!$D$14 -> [Case 2] | F25: =(Model!F$6-Model!E$6)/Model!E$6 -> 0.14688652 | G25: =(Model!H$6-Model!F$6)/Model!F$6 -> 0.15269168 | H25: 0.12 | I25: 0.13 | J25: 0.11 | K25: 0.1 | L25: 0.08 | N25: Haircut by 2–3pts Because supply chain parts availability risk and LEAP ramp execution uncertainty are flagged as key risks in the 10-K Item 1A.
C26: =Drivers!$C$15 -> 3 | D26: =Drivers!$D$15 -> [Case 3] | F26: =(Model!F$6-Model!E$6)/Model!E$6 -> 0.14688652 | G26: =(Model!H$6-Model!F$6)/Model!F$6 -> 0.15269168 | H26: 0.09 | I26: 0.09 | J26: 0.08 | K26: 0.08 | L26: 0.07 | N26: LEAP ramp delay costs 3pts in Year 1–2. By Year 4 gap narrows as backlog eventually clears.
C28: Component Repair Service growth rate | F28: =OFFSET(F28,Drivers!$C$12,) -> 0.15388301 | G28: =OFFSET(G28,Drivers!$C$12,) -> 0.19603931 | H28: =OFFSET(H28,Drivers!$C$12,) -> 0.16 | I28: =OFFSET(I28,Drivers!$C$12,) -> 0.15 | J28: =OFFSET(J28,Drivers!$C$12,) -> 0.15 | K28: =OFFSET(K28,Drivers!$C$12,) -> 0.14 | L28: =OFFSET(L28,Drivers!$C$12,) -> 0.13
C29: =Drivers!$C$13 -> 1 | D29: =Drivers!$D$13 -> [Case 1] | F29: =(Model!F$7-Model!E$7)/Model!E$7 -> 0.15388301 | G29: =(Model!H$7-Model!F$7)/Model!F$7 -> 0.19603931 | H29: 0.17 | I29: 0.16 | J29: 0.155 | K29: 0.155 | L29: 0.15
C30: =Drivers!$C$14 -> 2 | D30: =Drivers!$D$14 -> [Case 2] | F30: =(Model!F$7-Model!E$7)/Model!E$7 -> 0.15388301 | G30: =(Model!H$7-Model!F$7)/Model!F$7 -> 0.19603931 | H30: 0.16 | I30: 0.15 | J30: 0.15 | K30: 0.14 | L30: 0.13 | N30: Component Repair has been the faster-growing segment (19.6% growth in 2025) driven by Aero Turbine and military demand. But 28.6% Adj EBITDA margins can't expand forever, and the military helicopter market is cyclical.
C31: =Drivers!$C$15 -> 3 | D31: =Drivers!$D$15 -> [Case 3] | F31: =(Model!F$7-Model!E$7)/Model!E$7 -> 0.15388301 | G31: =(Model!H$7-Model!F$7)/Model!F$7 -> 0.19603931 | H31: 0.15 | I31: 0.15 | J31: 0.14 | K31: 0.14 | L31: 0.13 | N31: Phoenix fire + gov shutdown persists through H2 2026. Military budget pressure from potential defense cuts limits recovery.
C33: Gross profit margin | E33: =OFFSET(E33,Drivers!$C$12,) -> 0.13922408 | F33: =OFFSET(F33,Drivers!$C$12,) -> 0.14399825 | G33: =OFFSET(G33,Drivers!$C$12,) -> 0.14803303 | H33: =OFFSET(H33,Drivers!$C$12,) -> 0.148 | I33: =OFFSET(I33,Drivers!$C$12,) -> 0.15 | J33: =OFFSET(J33,Drivers!$C$12,) -> 0.152 | K33: =OFFSET(K33,Drivers!$C$12,) -> 0.153 | L33: =OFFSET(L33,Drivers!$C$12,) -> 0.154
C34: =Drivers!$C$13 -> 1 | D34: =Drivers!$D$13 -> [Case 1] | E34: =Model!E$11/Model!E$9 -> 0.13922408 | F34: =Model!F$11/Model!F$9 -> 0.14399825 | G34: =Model!H$11/Model!H$9 -> 0.14803303 | H34: 0.152 | I34: 0.155 | J34: 0.16 | K34: 0.163 | L34: 0.165 | N34: LEAP learning curve progressively reduces industrialization costs; mix shift toward higher-margin Component Repair Services; operating leverage on fixed overhead as volumes scale; partially offset by material cost inflation pass-through
C35: =Drivers!$C$14 -> 2 | D35: =Drivers!$D$14 -> [Case 2] | E35: =Model!E$11/Model!E$9 -> 0.13922408 | F35: =Model!F$11/Model!F$9 -> 0.14399825 | G35: =Model!H$11/Model!H$9 -> 0.14803303 | H35: 0.148 | I35: 0.15 | J35: 0.152 | K35: 0.153 | L35: 0.154 | N35: Materials are 71.5% of COGS, and tariff risk remains live even after the IEEPA ruling was struck down. LEAP industrialization savings are real but partially offset by inflationary labor pressures. The 10-K explicitly says "timing delays may impact margins" on tariff pass-throughs.
C36: =Drivers!$C$15 -> 3 | D36: =Drivers!$D$15 -> [Case 3] | E36: =Model!E$11/Model!E$9 -> 0.13922408 | F36: =Model!F$11/Model!F$9 -> 0.14399825 | G36: =Model!H$11/Model!H$9 -> 0.14803303 | H36: 0.143 | I36: 0.145 | J36: 0.146 | K36: 0.148 | L36: 0.15 | N36: 50bps GP compression from OEM inflation.
C38: SG&A % of sales | E38: =OFFSET(E38,Drivers!$C$12,) -> 0.044434228 | F38: =OFFSET(F38,Drivers!$C$12,) -> 0.048517126 | G38: =OFFSET(G38,Drivers!$C$12,) -> 0.040858146 | H38: =OFFSET(H38,Drivers!$C$12,) -> 0.041 | I38: =OFFSET(I38,Drivers!$C$12,) -> 0.04 | J38: =OFFSET(J38,Drivers!$C$12,) -> 0.04 | K38: =OFFSET(K38,Drivers!$C$12,) -> 0.039 | L38: =OFFSET(L38,Drivers!$C$12,) -> 0.039
C39: =Drivers!$C$13 -> 1 | D39: =Drivers!$D$13 -> [Case 1] | E39: =-Model!E$13/Model!E$9 -> 0.044434228 | F39: =-Model!F$13/Model!F$9 -> 0.048517126 | G39: =-Model!H$13/Model!H$9 -> 0.040858146 | H39: 0.041 | I39: 0.04 | J39: 0.039 | K39: 0.038 | L39: 0.037 | N39: SG&A already declined to 4.1% in 2025 (from 4.9% in 2024). Post-IPO one-time costs are behind the company. Further leverage expected as revenue scales against relatively fixed corporate overhead and sales force
C40: =Drivers!$C$14 -> 2 | D40: =Drivers!$D$14 -> [Case 2] | E40: =-Model!E$13/Model!E$9 -> 0.044434228 | F40: =-Model!F$13/Model!F$9 -> 0.048517126 | G40: =-Model!H$13/Model!H$9 -> 0.040858146 | H40: 0.041 | I40: 0.04 | J40: 0.04 | K40: 0.039 | L40: 0.039 | N40: The 10-K notes material weaknesses in internal controls requiring additional personnel and compliance investment. Remediation costs will partially offset the operating leverage from revenue growth.
C41: =Drivers!$C$15 -> 3 | D41: =Drivers!$D$15 -> [Case 3] | E41: =-Model!E$13/Model!E$9 -> 0.044434228 | F41: =-Model!F$13/Model!F$9 -> 0.048517126 | G41: =-Model!H$13/Model!H$9 -> 0.040858146 | H41: 0.043 | I41: 0.041 | J41: 0.041 | K41: 0.04 | L41: 0.04 | N41: 20bps SG&A increase from material weakness remediation costs (10-K disclosed).
C43: Tax rate | E43: =OFFSET(E43,Drivers!$C$12,) -> 7.8491893 | F43: =OFFSET(F43,Drivers!$C$12,) -> 0.86577296 | G43: =OFFSET(G43,Drivers!$C$12,) -> 0.2638576 | H43: =OFFSET(H43,Drivers!$C$12,) -> 0.3 | I43: =OFFSET(I43,Drivers!$C$12,) -> 0.3 | J43: =OFFSET(J43,Drivers!$C$12,) -> 0.3 | K43: =OFFSET(K43,Drivers!$C$12,) -> 0.3 | L43: =OFFSET(L43,Drivers!$C$12,) -> 0.3
C44: =Drivers!$C$13 -> 1 | D44: =Drivers!$D$13 -> [Case 1] | E44: =-Model!E$23/Model!E$22 -> 7.8491893 | F44: =-Model!F$23/Model!F$22 -> 0.86577296 | G44: =-Model!H$23/Model!H$22 -> 0.2638576 | H44: 0.3 | I44: 0.3 | J44: 0.3 | K44: 0.3 | L44: 0.3 | N44: 2025 effective rate of 26.4% includes GILTI, state taxes (California heavy), and changes in uncertain tax benefits. OBBBA provisions (signed Jul 4, 2025) restore favorable business tax treatment in 2026–2027 rate likely drifts toward 24–26% as Canada/foreign mix optimizes and interest carryforwards begin to release
C45: =Drivers!$C$14 -> 2 | D45: =Drivers!$D$14 -> [Case 2] | E45: =-Model!E$23/Model!E$22 -> 7.8491893 | F45: =-Model!F$23/Model!F$22 -> 0.86577296 | G45: =-Model!H$23/Model!H$22 -> 0.2638576 | H45: 0.3 | I45: 0.3 | J45: 0.3 | K45: 0.3 | L45: 0.3 | N45: The OBBBA provisions are recent and their permanence is uncertain
C46: =Drivers!$C$15 -> 3 | D46: =Drivers!$D$15 -> [Case 3] | E46: =-Model!E$23/Model!E$22 -> 7.8491893 | F46: =-Model!F$23/Model!F$22 -> 0.86577296 | G46: =-Model!H$23/Model!H$22 -> 0.2638576 | H46: 0.3 | I46: 0.3 | J46: 0.3 | K46: 0.3 | L46: 0.3
C48: Adjusted EBITDA Margin | E48: =OFFSET(E48,Drivers!$C$12,) -> 0.12295969 | F48: =OFFSET(F48,Drivers!$C$12,) -> 0.13185257 | G48: =OFFSET(G48,Drivers!$C$12,) -> 0.13330648 | H48: =OFFSET(H48,Drivers!$C$12,) -> 0.13 | I48: =OFFSET(I48,Drivers!$C$12,) -> 0.135 | J48: =OFFSET(J48,Drivers!$C$12,) -> 0.14 | K48: =OFFSET(K48,Drivers!$C$12,) -> 0.143 | L48: =OFFSET(L48,Drivers!$C$12,) -> 0.146
C49: =Drivers!$C$13 -> 1 | D49: =Drivers!$D$13 -> [Case 1] | E49: =Model!E$37/Model!E$9 -> 0.12295969 | F49: =Model!F$37/Model!F$9 -> 0.13185257 | G49: =Model!H$37/Model!H$9 -> 0.13330648 | H49: 0.139 | I49: 0.143 | J49: 0.147 | K49: 0.15 | L49: 0.153
C50: =Drivers!$C$14 -> 2 | D50: =Drivers!$D$14 -> [Case 2] | E50: =Model!E$37/Model!E$9 -> 0.12295969 | F50: =Model!F$37/Model!F$9 -> 0.13185257 | G50: =Model!H$37/Model!H$9 -> 0.13330648 | H50: 0.13 | I50: 0.135 | J50: 0.14 | K50: 0.143 | L50: 0.146 | N50: Business transformation costs ($26M in 2025) won't go to zero as the company is still ramping LEAP and may need ongoing industrialization investment.
C51: =Drivers!$C$15 -> 3 | D51: =Drivers!$D$15 -> [Case 3] | E51: =Model!E$37/Model!E$9 -> 0.12295969 | F51: =Model!F$37/Model!F$9 -> 0.13185257 | G51: =Model!H$37/Model!H$9 -> 0.13330648 | H51: 0.118 | I51: 0.125 | J51: 0.128 | K51: 0.13 | L51: 0.13 | N51: Combination of GP compression, SG&A stickiness, and LEAP dilution. Note Case 3 margin is below 2025A (13.3%) in Year 1 — that is the LEAP ramp cost made explicit.
C53: Acquisitions net of Cash | E53: =OFFSET(E53,Drivers!$C$12,) -> 0 | F53: =OFFSET(F53,Drivers!$C$12,) -> 0 | G53: =OFFSET(G53,Drivers!$C$12,) -> 0 | H53: =OFFSET(H53,Drivers!$C$12,) -> 0 | I53: =OFFSET(I53,Drivers!$C$12,) -> 50000 | J53: =OFFSET(J53,Drivers!$C$12,) -> 50000 | K53: =OFFSET(K53,Drivers!$C$12,) -> 75000 | L53: =OFFSET(L53,Drivers!$C$12,) -> 75000
C54: =Drivers!$C$13 -> 1 | D54: =Drivers!$D$13 -> [Case 1] | H54: 0 | I54: 75000 | J54: 75000 | K54: 100000 | L54: 100000
C55: =Drivers!$C$14 -> 2 | D55: =Drivers!$D$14 -> [Case 2] | H55: 0 | I55: 50000 | J55: 50000 | K55: 75000 | L55: 75000 | N55: We assume the company acquires but at a lower cadence since integration capacity is constrained (the 10-K discloses $5.6M of integration costs still flowing through in 2025)
C56: =Drivers!$C$15 -> 3 | D56: =Drivers!$D$15 -> [Case 3] | H56: 0 | I56: 0 | J56: 0 | K56: 0 | L56: 0 | N56: Lower FCF means no M&A capacity.
C58: Share Repurchases | E58: =OFFSET(E58,Drivers!$C$12,) -> 0 | F58: =OFFSET(F58,Drivers!$C$12,) -> 0 | G58: =OFFSET(G58,Drivers!$C$12,) -> 0 | H58: =OFFSET(H58,Drivers!$C$12,) -> 0 | I58: =OFFSET(I58,Drivers!$C$12,) -> 0 | J58: =OFFSET(J58,Drivers!$C$12,) -> 0 | K58: =OFFSET(K58,Drivers!$C$12,) -> 0 | L58: =OFFSET(L58,Drivers!$C$12,) -> 0
C59: =Drivers!$C$13 -> 1 | D59: =Drivers!$D$13 -> [Case 1] | H59: 0 | I59: 0 | J59: 0 | K59: 0 | L59: 0
C60: =Drivers!$C$14 -> 2 | D60: =Drivers!$D$14 -> [Case 2] | H60: 0 | I60: 0 | J60: 0 | K60: 0 | L60: 0 | N60: The New Credit Agreement also has restricted payment covenants that may limit buyback pace at higher leverage.
C61: =Drivers!$C$15 -> 3 | D61: =Drivers!$D$15 -> [Case 3] | H61: 0 | I61: 0 | J61: 0 | K61: 0 | L61: 0 | N61: y
C63: Voluntary Debt Prepayment | E63: =OFFSET(E63,Drivers!$C$12,) -> 0 | F63: =OFFSET(F63,Drivers!$C$12,) -> 0 | G63: =OFFSET(G63,Drivers!$C$12,) -> 0 | H63: =OFFSET(H63,Drivers!$C$12,) -> 45000 | I63: =OFFSET(I63,Drivers!$C$12,) -> 45000 | J63: =OFFSET(J63,Drivers!$C$12,) -> 100000 | K63: =OFFSET(K63,Drivers!$C$12,) -> 140000 | L63: =OFFSET(L63,Drivers!$C$12,) -> 185000
C64: =Drivers!$C$13 -> 1 | D64: =Drivers!$D$13 -> [Case 1] | H64: 47000 | I64: 50000 | J64: 110000 | K64: 200000 | L64: 350000
C65: =Drivers!$C$14 -> 2 | D65: =Drivers!$D$14 -> [Case 2] | H65: 45000 | I65: 45000 | J65: 100000 | K65: 140000 | L65: 185000 | N65: We assume slightly less prepayment since lower revenue growth means lower FCF. But deleveraging is still a priority
C66: =Drivers!$C$15 -> 3 | D66: =Drivers!$D$15 -> [Case 3] | H66: 0 | I66: 0 | J66: 25000 | K66: 50000 | L66: 75000
C69: M&A Per Year | H69: =H53 -> 0 | I69: =I53 -> 50000 | J69: =J53 -> 50000 | K69: =K53 -> 75000 | L69: =L53 -> 75000
C71: Multiple x Revenue | H71: 1 | I71: 1 | J71: 1 | K71: 1 | L71: 1
C72: Revenue Acquired | H72: =H69*H71 -> 0 | I72: =I69*I71 -> 50000 | J72: =J69*J71 -> 50000 | K72: =K69*K71 -> 75000 | L72: =L69*L71 -> 75000
C74: EBITDA Multiple | H74: 10 | I74: 10 | J74: 10 | K74: 10 | L74: 10
C75: EBITDA Acquired | H75: =H72/H74 -> 0 | I75: =I72/I74 -> 5000 | J75: =J72/J74 -> 5000 | K75: =K72/K74 -> 7500 | L75: =L72/L74 -> 7500
C77: Synergized Multiple | H77: 0 | I77: =IFERROR(I69/I78,0) -> 6.6666667 | J77: =IFERROR(J69/J78,0) -> 6.6666667 | K77: =IFERROR(K69/K78,0) -> 6.6666667 | L77: =IFERROR(L69/L78,0) -> 6.6666667
C78: Synergized EBITDA | H78: =H75*1.5 -> 0 | I78: =I75*1.5 -> 7500 | J78: =J75*1.5 -> 7500 | K78: =K75*1.5 -> 11250 | L78: =L75*1.5 -> 11250

Sheet Model
B2: X | C2: INCOME STATEMENT
C3: Fiscal year | E3: =F3-1 -> 2023 | F3: =H3-1 -> 2024 | H3: =YEAR(Drivers!D9) -> 2025 | I3: =H3+1 -> 2026 | J3: =I3+1 -> 2027 | K3: =J3+1 -> 2028 | L3: =K3+1 -> 2029 | M3: =L3+1 -> 2030
C4: Fiscal year end date | E4: =EOMONTH(F4,-12) -> 45291 | F4: =EOMONTH(H4,-12) -> 45657 | H4: =Drivers!D9 -> 46022 | I4: =EOMONTH(H4,12) -> 46387 | J4: =EOMONTH(I4,12) -> 46752 | K4: =EOMONTH(J4,12) -> 47118 | L4: =EOMONTH(K4,12) -> 47483 | M4: =EOMONTH(L4,12) -> 47848 | O4: Comments
C6: Revenue from Engine Repair | E6: 4049868 | F6: 4644739 | H6: 5353952 | I6: =H6*(1+Drivers!H23) -> 5996426.2 | J6: =I6*(1+Drivers!I23) -> 6775961.7 | K6: =J6*(1+Drivers!J23) -> 7521317.4 | L6: =K6*(1+Drivers!K23) -> 8273449.2 | M6: =L6*(1+Drivers!L23) -> 8935325.1
C7: Revenue from Component Repair | E7: 513416 | F7: 592422 | H7: 708560 | I7: =H7*(1+Drivers!H28) -> 821929.6 | J7: =I7*(1+Drivers!I28) -> 945219.04 | K7: =J7*(1+Drivers!J28) -> 1087001.9 | L7: =K7*(1+Drivers!K28) -> 1239182.2 | M7: =L7*(1+Drivers!L28) -> 1400275.8
C8: Revenue from M&A | E8: 0 | F8: 0 | H8: 0 | I8: =I260 -> 0 | J8: =J260 -> 25000 | K8: =K260 -> 78000 | L8: =L260 -> 146680 | M8: =M260 -> 232730.8
C9: Total Revenue | E9: =SUM(E6:E8) -> 4563284 | F9: =SUM(F6:F8) -> 5237161 | G9: =SUM(G6:G8) -> 0 | H9: =SUM(H6:H8) -> 6062512 | I9: =SUM(I6:I8) -> 6818355.8 | J9: =SUM(J6:J8) -> 7746180.7 | K9: =SUM(K6:K8) -> 8686319.3 | L9: =SUM(L6:L8) -> 9659311.3 | M9: =SUM(M6:M8) -> 10568332
C10: Cost of sales | E10: -3927965 | F10: -4483019 | H10: -5165060 | I10: =I11-I9 -> -5809239.2 | J10: =J11-J9 -> -6584253.6 | K10: =K11-K9 -> -7365998.8 | L10: =L11-L9 -> -8181436.7 | M10: =M11-M9 -> -8940808.7
C11: Gross Profit | E11: =SUM(E9:E10) -> 635319 | F11: =SUM(F9:F10) -> 754142 | H11: =SUM(H9:H10) -> 897452 | I11: =I9*Drivers!H33 -> 1009116.7 | J11: =J9*Drivers!I33 -> 1161927.1 | K11: =K9*Drivers!J33 -> 1320320.5 | L11: =L9*Drivers!K33 -> 1477874.6 | M11: =M9*Drivers!L33 -> 1627523.1
C12: Amortisation of intangible assets | E12: -93681 | F12: -95457 | H12: -98681 | I12: =-I127*0.7516 -> -91261.527 | J12: =-J127*0.7516 -> -83538.837 | K12: =-K127*0.7516 -> -82367.092 | L12: =-L127*0.7516 -> -79979.259 | M12: =-M127*0.7516 -> -79200.602 | O12: Formula: Total Amortization from intangible Assets acc to note 9× 75% to excludes OEM auth amort which goes through COGS per Note 9.
C13: Selling, general & administrative | E13: -202766 | F13: -254092 | H13: -247703 | I13: =-I9*Drivers!H38 -> -279552.59 | J13: =-J9*Drivers!I38 -> -309847.23 | K13: =-K9*Drivers!J38 -> -347452.77 | L13: =-L9*Drivers!K38 -> -376713.14 | M13: =-M9*Drivers!L38 -> -412164.94
C14: Acquisition Cost | E14: -1514 | F14: -1374 | H14: 0 | I14: =H14 -> 0 | J14: =I14 -> 0 | K14: =J14 -> 0 | L14: =K14 -> 0 | M14: =L14 -> 0
C15: Operating profit (EBIT) | E15: =SUM(E11:E14) -> 337358 | F15: =SUM(F11:F14) -> 403219 | H15: =SUM(H11:H14) -> 551068 | I15: =SUM(I11:I14) -> 638302.55 | J15: =SUM(J11:J14) -> 768541.04 | K15: =SUM(K11:K14) -> 890500.67 | L15: =SUM(L11:L14) -> 1021182.2 | M15: =SUM(M11:M14) -> 1136157.5
C16: Interest income | E16: 0 | F16: 0 | H16: 0 | I16: =I172 -> 0 | J16: =J172 -> 0 | K16: =K172 -> 0 | L16: =L172 -> 0 | M16: =M172 -> 0
C17: Interest expense | E17: -309645 | F17: -282507 | H17: -174217 | I17: =I159 -> -427448.47 | J17: =J159 -> -421783.23 | K17: =K159 -> -413288.21 | L17: =L159 -> -400676.56 | M17: =M159 -> -385353.39
C18: Amotisation of Financing fees | E18: 0 | F18: 0 | H18: 0 | I18: =-I231 -> -17340.423 | J18: =-J231 -> -17340.423 | K18: =-K231 -> -17340.423 | L18: =-L231 -> -17340.423 | M18: =-M231 -> -17340.423
C19: Refinancing costs | E19: -19921 | F19: -23700 | H19: 0 | I19: =H19 -> 0 | J19: =I19 -> 0 | K19: =J19 -> 0 | L19: =K19 -> 0 | M19: =L19 -> 0
C20: Loss on debt extinguishment | E20: -6182 | F20: -15255 | H20: 0 | I20: =H20 -> 0 | J20: =I20 -> 0 | K20: =J20 -> 0 | L20: =K20 -> 0 | M20: =L20 -> 0
C21: Other expense, net | E21: 3509 | F21: 0 | H21: 0 | I21: 0 | J21: 0 | K21: 0 | L21: 0 | M21: 0
C22: Pretax profit | E22: =SUM(E15:E21) -> 5119 | F22: =SUM(F15:F21) -> 81757 | H22: =SUM(H15:H21) -> 376851 | I22: =SUM(I15:I21) -> 193513.65 | J22: =SUM(J15:J21) -> 329417.39 | K22: =SUM(K15:K21) -> 459872.04 | L22: =SUM(L15:L21) -> 603165.25 | M22: =SUM(M15:M21) -> 733463.73
C23: Taxes | E23: -40180 | F23: -70783 | H23: -99435 | I23: =-I22*Drivers!H43 -> -58054.096 | J23: =-J22*Drivers!I43 -> -98825.217 | K23: =-K22*Drivers!J43 -> -137961.61 | L23: =-L22*Drivers!K43 -> -180949.57 | M23: =-M22*Drivers!L43 -> -220039.12
C24: Net income | E24: =SUM(E22:E23) -> -35061 | F24: =SUM(F22:F23) -> 10974 | H24: =SUM(H22:H23) -> 277416 | I24: =SUM(I22:I23) -> 135459.56 | J24: =SUM(J22:J23) -> 230592.17 | K24: =SUM(K22:K23) -> 321910.43 | L24: =SUM(L22:L23) -> 422215.67 | M24: =SUM(M22:M23) -> 513424.61
C25: Depreciation & amortization | E25: 197104 | F25: 188164 | H25: 193664 | I25: =I129 -> 191602.72 | J25: =J129 -> 190877.6 | K25: =K129 -> 198995.23 | L25: =L129 -> 205833 | M25: =M129 -> 214153.34
C26: EBITDA | E26: =E15+E25 -> 534462 | F26: =F15+F25 -> 591383 | H26: =H15+H25 -> 744732 | I26: =I15+I25 -> 829905.27 | J26: =J15+J25 -> 959418.64 | K26: =K15+K25 -> 1089495.9 | L26: =L15+L25 -> 1227015.2 | M26: =M15+M25 -> 1350310.9
C27: % of Revenue | E27: =E26/E9 -> 0.11712223 | F27: =F26/F9 -> 0.11292053 | G27: =IFERROR(G26/G9,"") | H27: =H26/H9 -> 0.12284215 | I27: =I26/I9 -> 0.12171633 | J27: =J26/J9 -> 0.12385699 | K27: =K26/K9 -> 0.12542665 | L27: =L26/L9 -> 0.12702927 | M27: =M26/M9 -> 0.12776954
C28: Stock based compensation | E28: - | F28: 17376 | H28: 13237 | I28: =0.2%*I9 -> 13636.712 | J28: =0.2%*J9 -> 15492.361 | K28: =0.2%*K9 -> 17372.639 | L28: =0.2%*L9 -> 19318.623 | M28: =0.2%*M9 -> 21136.664
C29: Business transformation costs | E29: - | F29: 43239 | H29: 26028 | I29: - | J29: - | K29: - | L29: - | M29: -
C30: IPO related cost | E30: - | F30: 26909 | H30: 0 | I30: - | J30: - | K30: - | L30: - | M30: -
C31: Integration costs and severance | E31: - | F31: 2782 | H31: 5601 | I31: - | J31: - | K31: - | L31: - | M31: -
C32: Acquisition costs | E32: - | F32: 1374 | H32: 0 | I32: - | J32: - | K32: - | L32: - | M32: -
C33: Insurance recovery | E33: - | F33: 0 | H33: -3000 | I33: - | J33: - | K33: - | L33: - | M33: -
C34: Loss on disposals | E34: - | F34: 0 | H34: 2764 | I34: - | J34: - | K34: - | L34: - | M34: -
C35: Secondary offering costs | E35: - | F35: 0 | H35: 4990 | I35: - | J35: - | K35: - | L35: - | M35: -
C36: Other | E36: - | F36: 7470 | H36: 13820 | I36: - | J36: - | K36: - | L36: - | M36: -
C37: Adj EBITDA | E37: 561100 | F37: =SUM(F26:F36) -> 690533.11 | H37: =SUM(H26:H36) -> 808172.12 | I37: =(I6+I7)*Drivers!H48+I268-I271 -> 886386.26 | J37: =(J6+J7)*Drivers!I48+J268-J271 -> 1042776.1 | K37: =(K6+K7)*Drivers!J48+K268-K271 -> 1212648 | L37: =(L6+L7)*Drivers!K48+L268-L271 -> 1376424.9 | M37: =(M6+M7)*Drivers!L48+M268-M271 -> 1537582.4 | O37: Formula: EBITDA*Adj. EBITDA margin + M&A acquired EBITDA - synergy cost/year
B39: X | C39: BALANCE SHEET
C40: =C3 -> Fiscal year | E40: =E3 -> 2023 | F40: =F3 -> 2024 | G40: =H3 -> 2025 | H40: Pro forma 2025A | I40: =I3 -> 2026 | J40: =J3 -> 2027 | K40: =K3 -> 2028 | L40: =L3 -> 2029 | M40: =M3 -> 2030
C41: =C4 -> Fiscal year end date | E41: =E4 -> 45291 | F41: =F4 -> 45657 | G41: =H4 -> 46022 | H41: =Drivers!D9 -> 46022 | I41: =I4 -> 46387 | J41: =J4 -> 46752 | K41: =K4 -> 47118 | L41: =L4 -> 47483 | M41: =M4 -> 47848
C42: ASSETS
C43: Current Assets
C44: Cash & equivalents, ST and LT marketable securities | F44: 102581 | G44: 289717 | H44: ='Sources & Uses'!F23 -> 100000 | I44: =H44+I113 -> 100000 | J44: =I44+J113 -> 100000 | K44: =J44+K113 -> 100000 | L44: =K44+L113 -> 137290.58 | M44: =L44+M113 -> 239296.32
C45: Accounts receivable | F45: 580668 | G45: 654390 | H45: =G45 -> 654390 | I45: =H45*(1+Drivers!H21) -> 735976.09 | J45: =I45*(1+Drivers!I21) -> 836125.88 | K45: =J45*(1+Drivers!J21) -> 937604.83 | L45: =K45*(1+Drivers!K21) -> 1042630 | M45: =L45*(1+Drivers!L21) -> 1140750
C46: Contract Assets | F46: 915200 | G46: 1071703 | H46: =G46 -> 1071703 | I46: =H46*(1+Drivers!H21) -> 1205317.6 | J46: =I46*(1+Drivers!I21) -> 1369334.2 | K46: =J46*(1+Drivers!J21) -> 1535527.6 | L46: =K46*(1+Drivers!K21) -> 1707528.7 | M46: =L46*(1+Drivers!L21) -> 1868221.1
C47: Inventories | F47: 847018 | G47: 827691 | H47: =G47 -> 827691 | I47: =H47*(1+((I10-H10)/H10)) -> 930919.48 | J47: =I47*(1+((J10-I10)/I10)) -> 1055114.1 | K47: =J47*(1+((K10-J10)/J10)) -> 1180387.2 | L47: =K47*(1+((L10-K10)/K10)) -> 1311059.6 | M47: =L47*(1+((M10-L10)/L10)) -> 1432747.5
C48: Other current assets | F48: 29707 | G48: 42776 | H48: =G48 -> 42776 | I48: =H48*(1+Drivers!H21) -> 48109.099 | J48: =I48*(1+Drivers!I21) -> 54655.665 | K48: =J48*(1+Drivers!J21) -> 61289.115 | L48: =K48*(1+Drivers!K21) -> 68154.373 | M48: =L48*(1+Drivers!L21) -> 74568.258
C49: Income tax receivable | F49: 9960 | G49: 10182 | H49: =G49 -> 10182 | I49: =H49 -> 10182 | J49: =I49 -> 10182 | K49: =J49 -> 10182 | L49: =K49 -> 10182 | M49: =L49 -> 10182
C50: Total current assets | F50: =SUM(F44:F49) -> 2485134 | G50: =SUM(G44:G49) -> 2896459 | H50: =SUM(H44:H49) -> 2706742 | I50: =SUM(I44:I49) -> 3030504.3 | J50: =SUM(J44:J49) -> 3425411.8 | K50: =SUM(K44:K49) -> 3824990.8 | L50: =SUM(L44:L49) -> 4276845.2 | M50: =SUM(M44:M49) -> 4765765.2
C51: Property, plant & equipment | F51: 568607 | G51: 579971 | H51: =G51 -> 579971 | I51: =I122 -> 602464.5 | J51: =J122 -> 628018.86 | K51: =K122 -> 656674.7 | L51: =L122 -> 688540.41 | M51: =M122 -> 723404.94
C52: Operating lease right of use asset | F52: 172206 | G52: 222151 | H52: =G52 -> 222151 | I52: =H52 -> 222151 | J52: =I52 -> 222151 | K52: =J52 -> 222151 | L52: =K52 -> 222151 | M52: =L52 -> 222151
C53: Customer relationships | F53: 1004701 | G53: 920432 | H53: =G53 -> 920432 | I53: =H53 - I127*0.6425 + (-I103)*0.4 -> 842417.72 | J53: =I53 - J127*0.6425 + (-J103)*0.4 -> 791005.13 | K53: =J53 - K127*0.6425 + (-K103)*0.4 -> 740594.2 | L53: =K53 - L127*0.6425 + (-L103)*0.4 -> 702224.49 | M53: =L53 - M127*0.6425 + (-M103)*0.4 -> 664520.41 | O53: Formula: Prior year − amort (Note 9 × 64.2% CR share) + new CRs from M&A (Row 110 × 40% allocation).
C54: Other intangible assets | F54: 291487 | G54: 244877 | H54: =G54 -> 244877 | I54: =H54 - I127*0.3575 + (-I106) -> 228468.28 | J54: =I54 - J127*0.3575 + (-J106) -> 215732.87 | K54: =J54 - K127*0.3575 + (-K106) -> 203554.8 | L54: =K54 - L127*0.3575 + (-L106) -> 192512.51 | M54: =L54 - M127*0.3575 + (-M106) -> 181840.59 | O54: Formula: Prior year − amort (Note 9 × 35.8% Other share) + OEM license purchases (Row 113)
C55: Goodwill | F55: 1685970 | G55: 1684255 | H55: =G55+'Sources & Uses'!F20-G85 -> 8810551.8 | I55: =H55 + (-I103)*0.6 -> 8810551.8 | J55: =I55 + (-J103)*0.6 -> 8840551.8 | K55: =J55 + (-K103)*0.6 -> 8870551.8 | L55: =K55 + (-L103)*0.6 -> 8915551.8 | M55: =L55 + (-M103)*0.6 -> 8960551.8 | O55: Formula: Prior year + M&A goodwill (Row 110 × 60% allocation) + transaction fees. Per Aero Turbine: ~60% of purchase price allocated to goodwill, ~40% to customer relationships.
C56: Deferred income tax assets | F56: 1079 | G56: 2832 | H56: =G56 -> 2832 | I56: =H56 -> 2832 | J56: =I56 -> 2832 | K56: =J56 -> 2832 | L56: =K56 -> 2832 | M56: =L56 -> 2832
C57: Other non current assets | F57: 4417 | G57: 6434 | H57: =G57 -> 6434 | I57: =H57*(1+Drivers!H21) -> 7236.1591 | J57: =I57*(1+Drivers!I21) -> 8220.8376 | K57: =J57*(1+Drivers!J21) -> 9218.5844 | L57: =K57*(1+Drivers!K21) -> 10251.198 | M57: =L57*(1+Drivers!L21) -> 11215.919
C58: Total assets | F58: =SUM(F50:F57) -> 6213601 | G58: =SUM(G50:G57) -> 6557411 | H58: =SUM(H50:H57) -> 13493991 | I58: =SUM(I50:I57) -> 13746626 | J58: =SUM(J50:J57) -> 14133924 | K58: =SUM(K50:K57) -> 14530568 | L58: =SUM(L50:L57) -> 15010909 | M58: =SUM(M50:M57) -> 15532282
C59: LIABILITIES AND STOCKHOLDERS' EQUITY
C60: Current Liabilities
C61: Accounts payable | F61: 645701 | G61: 679772 | H61: =G61 -> 679772 | I61: =H61*(1+(I10-H10)/H10) -> 764552.23 | J61: =I61*(1+(J10-I10)/I10) -> 866551.64 | K61: =J61*(1+(K10-J10)/J10) -> 969436.9 | L61: =K61*(1+(L10-K10)/K10) -> 1076756.4 | M61: =L61*(1+(M10-L10)/L10) -> 1176697.2
C62: Accrued expenses and other current liabilities | F62: 99572 | G62: 91499 | H62: =G62 -> 91499 | I62: =H62*(1+Drivers!H21) -> 102906.64 | J62: =I62*(1+Drivers!I21) -> 116909.92 | K62: =J62*(1+Drivers!J21) -> 131099.04 | L62: =K62*(1+Drivers!K21) -> 145784.01 | M62: =L62*(1+Drivers!L21) -> 159503.48
C63: Accrued employ costs | F63: 79134 | G63: 74008 | H63: =G63 -> 74008 | I63: =H63*(1+Drivers!H21) -> 83234.949 | J63: =I63*(1+Drivers!I21) -> 94561.354 | K63: =J63*(1+Drivers!J21) -> 106038.08 | L63: =K63*(1+Drivers!K21) -> 117915.86 | M63: =L63*(1+Drivers!L21) -> 129012.71
C64: Operating lease liabilities, current | F64: 17663 | G64: 22308 | H64: =G64 -> 22308 | I64: =H64 -> 22308 | J64: =I64 -> 22308 | K64: =J64 -> 22308 | L64: =K64 -> 22308 | M64: =L64 -> 22308
C65: Due to related parties | F65: 1345 | G65: 438 | H65: =G65 -> 438 | I65: =H65 -> 438 | J65: =I65 -> 438 | K65: =J65 -> 438 | L65: =K65 -> 438 | M65: =L65 -> 438
C66: Contract liabilities | F66: 400025 | G66: 411321 | H66: =G66 -> 411321 | I66: =H66*(1+Drivers!H21) -> 462602.46 | J66: =I66*(1+Drivers!I21) -> 525552.24 | K66: =J66*(1+Drivers!J21) -> 589337.48 | L66: =K66*(1+Drivers!K21) -> 655351.71 | M66: =L66*(1+Drivers!L21) -> 717025.68
C67: Income taxes payable, current | F67: 6655 | G67: 13547 | H67: =G67 -> 13547 | I67: =H67 -> 13547 | J67: =I67 -> 13547 | K67: =J67 -> 13547 | L67: =K67 -> 13547 | M67: =L67 -> 13547
C68: Long-term debt, current portion | F68: 23449 | G68: 23444 | H68: =H206*0.01 -> 36367.746 | I68: =H209*0.01 -> 36004.068 | J68: =I209*0.01 -> 35194.027 | K68: =J209*0.01 -> 34392.087 | L68: =K209*0.01 -> 33048.166 | M68: =L209*0.01 -> 31317.685 | O68: r
C69: Total current liabilities | F69: =SUM(F61:F68) -> 1273544 | G69: =SUM(G61:G68) -> 1316337 | H69: =SUM(H61:H68) -> 1329260.7 | I69: =SUM(I61:I68) -> 1485593.3 | J69: =SUM(J61:J68) -> 1675062.2 | K69: =SUM(K61:K68) -> 1866596.6 | L69: =SUM(L61:L68) -> 2065149.2 | M69: =SUM(M61:M68) -> 2249849.7
C70: Long term debt | F70: 2207977 | G70: 2191161 | H70: ='Sources & Uses'!F10-H68 -> 5216751.1 | I70: =H70-I68+I112 -> 5135747 | J70: =I70-J68+J112 -> 5055553 | K70: =J70-K68+K112 -> 4921160.9 | L70: =K70-L68+L112 -> 4748112.7 | M70: =L70-M68+M112 -> 4531795
C71: Financing fees | F71: 0 | G71: 0 | H71: =-H233 -> -124256.46 | I71: =-I233 -> -106916.04 | J71: =-J233 -> -89575.617 | K71: =-K233 -> -72235.194 | L71: =-L233 -> -54894.771 | M71: =-M233 -> -37554.347
C72: Operating Lease Liabilities Non Current | F72: 164224 | G72: 212365 | H72: =G72 -> 212365 | I72: =H72 -> 212365 | J72: =I72 -> 212365 | K72: =J72 -> 212365 | L72: =K72 -> 212365 | M72: =L72 -> 212365
C73: Deferred income tax liabilities | F73: 169824 | G73: 157206 | H73: =G73 -> 157206 | I73: =H73 -> 157206 | J73: =I73 -> 157206 | K73: =J73 -> 157206 | L73: =K73 -> 157206 | M73: =L73 -> 157206
C74: Income tax payable, non-current | F74: 0 | G74: 5770 | H74: =G74 -> 5770 | I74: =H74 -> 5770 | J74: =I74 -> 5770 | K74: =J74 -> 5770 | L74: =K74 -> 5770 | M74: =L74 -> 5770
C75: Other non current liabilities | F75: 24628 | G75: 7261 | H75: =G75 -> 7261 | I75: =H75*(1+Drivers!H21) -> 8166.2654 | J75: =I75*(1+Drivers!I21) -> 9277.5104 | K75: =J75*(1+Drivers!J21) -> 10403.503 | L75: =K75*(1+Drivers!K21) -> 11568.845 | M75: =L75*(1+Drivers!L21) -> 12657.568
C76: Total liabilities | F76: =SUM(F69:F75) -> 3840197 | G76: =SUM(G69:G75)+G77 -> 3890100 | H76: =SUM(H69:H75)+H77 -> 6804357.3 | I76: =SUM(I69:I75)+I77 -> 6907896 | J76: =SUM(J69:J75)+J77 -> 7049110 | K76: =SUM(K69:K75)+K77 -> 7106470.5 | L76: =SUM(L69:L75)+L77 -> 7145277 | M76: =SUM(M69:M75)+M77 -> 7132088.9
C77: Revolver | F77: 0 | G77: 0 | H77: 0 | I77: =I225 -> 9964.445 | J77: =J225 -> 23452.01 | K77: =K225 -> 5203.7606 | L77: =L225 -> 0 | M77: =M225 -> 0
C78: Stockholders Equity:
C79: Common stock | F79: 3345 | G79: 3345 | H79: 3300 | I79: =H79 -> 3300 | J79: =I79 -> 3300 | K79: =J79 -> 3300 | L79: =K79 -> 3300 | M79: =L79 -> 3300
C80: Preferred stock | F80: 0 | G80: 0 | H80: 0 | I80: 0 | J80: 0 | K80: 0 | L80: 0 | M80: 0
C81: Additional paid-in capital | F81: 3944802 | G81: 3958039 | H81: ='Sources & Uses'!F14-H79 -> 6803518.4 | I81: =H81+I28 -> 6817155.1 | J81: =I81+J28 -> 6832647.5 | K81: =J81+K28 -> 6850020.1 | L81: =K81+L28 -> 6869338.7 | M81: =L81+M28 -> 6890475.4
C82: Accumulated deficit | F82: -1563321 | G82: -1285904 | H82: =-'Sources & Uses'!E34 -> -117184.96 | I82: =H82+I24 -> 18274.599 | J82: =I82+J24 -> 248866.77 | K82: =J82+K24 -> 570777.2 | L82: =K82+L24 -> 992992.87 | M82: =L82+M24 -> 1506417.5
C83: Accumulated other comprehensive loss | F83: -11422 | G83: -8169 | H83: 0 | I83: =H83 -> 0 | J83: =I83 -> 0 | K83: =J83 -> 0 | L83: =K83 -> 0 | M83: =L83 -> 0
C84: Treasury stock | F84: 0 | G84: 0 | H84: 0 | I84: =H84+I109 -> 0 | J84: =I84+J109 -> 0 | K84: =J84+K109 -> 0 | L84: =K84+L109 -> 0 | M84: =L84+M109 -> 0
C85: Total equity | F85: =SUM(F79:F84) -> 2373404 | G85: =SUM(G79:G84) -> 2667311 | H85: =SUM(H79:H84) -> 6689633.4 | I85: =SUM(I79:I84) -> 6838729.7 | J85: =SUM(J79:J84) -> 7084814.2 | K85: =SUM(K79:K84) -> 7424097.3 | L85: =SUM(L79:L84) -> 7865631.6 | M85: =SUM(M79:M84) -> 8400192.9
C86: Total liabilities and stockholders' equity | F86: =SUM(F85,F76) -> 6213601 | G86: =SUM(G85,G76) -> 6557411 | H86: =SUM(H85,H76) -> 13493991 | I86: =SUM(I85,I76) -> 13746626 | J86: =SUM(J85,J76) -> 14133924 | K86: =SUM(K85,K76) -> 14530568 | L86: =SUM(L85,L76) -> 15010909 | M86: =SUM(M85,M76) -> 15532282
C88: Balance check | F88: =F58-F86 -> 0 | G88: =G58-G86 -> 0 | H88: =H58-H86 -> 0 | I88: =I58-I86 -> 0 | J88: =J58-J86 -> 0 | K88: =K58-K86 -> 0 | L88: =L58-L86 -> 0 | M88: =M58-M86 -> 0
B90: X | C90: CASH FLOW STATEMENT
C91: =C3 -> Fiscal year | I91: =I3 -> 2026 | J91: =J3 -> 2027 | K91: =K3 -> 2028 | L91: =L3 -> 2029 | M91: =M3 -> 2030
C92: =C4 -> Fiscal year end date | I92: =I4 -> 46387 | J92: =J4 -> 46752 | K92: =K4 -> 47118 | L92: =L4 -> 47483 | M92: =M4 -> 47848
C94: Net income | I94: =I24 -> 135459.56 | J94: =J24 -> 230592.17 | K94: =K24 -> 321910.43 | L94: =L24 -> 422215.67 | M94: =M24 -> 513424.61
C95: Depreciation and amortization | I95: =I25 -> 191602.72 | J95: =J25 -> 190877.6 | K95: =K25 -> 198995.23 | L95: =L25 -> 205833 | M95: =M25 -> 214153.34
C96: Amortization of financing fees | I96: =I231 -> 17340.423 | J96: =J231 -> 17340.423 | K96: =K231 -> 17340.423 | L96: =L231 -> 17340.423 | M96: =M231 -> 17340.423
C97: Stock based compensation | I97: =I28 -> 13636.712 | J97: =J28 -> 15492.361 | K97: =K28 -> 17372.639 | L97: =L28 -> 19318.623 | M97: =M28 -> 21136.664
C98: Decreases / (Increases) in working capital assets | I98: =G45+G46+G47+G48-I45-I46-I47-I48 -> -323762.27 | J98: =I45+I46+I47+I48-J45-J46-J47-J48 -> -394907.55 | K98: =J45+J46+J47+J48-K45-K46-K47-K48 -> -399578.96 | L98: =K45+K46+K47+K48-L45-L46-L47-L48 -> -414563.83 | M98: =L45+L46+L47+L48-M45-M46-M47-M48 -> -386914.27
C99: Increases / (Decreases) in working capital liabilities | I99: =I61+I62+I63+I66-G61-G62-G63-G66 -> 156696.27 | J99: =J61+J62+J63+J66-I61-I62-I63-I66 -> 190278.89 | K99: =K61+K62+K63+K66-J61-J62-J63-J66 -> 192336.34 | L99: =L61+L62+L63+L66-K61-K62-K63-K66 -> 199896.52 | M99: =M61+M62+M63+M66-L61-L62-L63-L66 -> 186431.01
C100: Other non current assets | I100: =-I57+G57 -> -802.15912 | J100: =-J57+I57 -> -984.67848 | K100: =-K57+J57 -> -997.74681 | L100: =-L57+K57 -> -1032.6133 | M100: =-M57+L57 -> -964.72178
C101: Other non current liabilities | I101: =I75-G75 -> 905.26536 | J101: =J75-I75 -> 1111.245 | K101: =K75-J75 -> 1125.9931 | L101: =L75-K75 -> 1165.3412 | M101: =M75-L75 -> 1088.7232
C102: Cash from operating activities | I102: =SUM(I94:I101) -> 191076.52 | J102: =SUM(J94:J101) -> 249800.47 | K102: =SUM(K94:K101) -> 348504.35 | L102: =SUM(L94:L101) -> 450173.14 | M102: =SUM(M94:M101) -> 565695.77
C103: Acquisitions, net of cash | I103: =-Drivers!H53 -> 0 | J103: =-Drivers!I53 -> -50000 | K103: =-Drivers!J53 -> -50000 | L103: =-Drivers!K53 -> -75000 | M103: =-Drivers!L53 -> -75000 | O103: Normalized bolt-on M&A based on Western Jet ($33M) and Aero Turbine ($132M) historical cadence; 10-K states company "continually acquiring and investing"
C104: Capital expenditures | I104: =-I120 -> -92673.222 | J104: =-J120 -> -105283.96 | K104: =-K120 -> -118062.07 | L104: =-L120 -> -131286.71 | M104: =-M120 -> -143641.87
C105: Cash from investing activities | I105: =I104+I103+I106 -> -119673.22 | J105: =J104+J103+J106 -> -182283.96 | K105: =K104+K103+K106 -> -195062.07 | L105: =L104+L103+L106 -> -233286.71 | M105: =M104+M103+M106 -> -245641.87
C106: Intangible asset purchases | I106: -27000 | J106: -27000 | K106: -27000 | L106: -27000 | M106: -27000 | O106: OEM authorizations & licenses: 3-yr avg of $27M (2023: $30.2M, 2024: $20.3M, 2025: $30.4M)
...

Sheet Sources & Uses
B2: X | C2: Sources and Uses | J2: Purchase price
C3: Minimum Equity | E3: 0.4 | J3: Adjusted 2025 Cash EBITDA | L3: =Model!H37 -> 808172.12
C4: Available debt package at closing | E4: =SUM(F7:F9) -> 5253118.8 | J4: Purchase Multiple | L4: 14.5
C6: Sources | E6: EBITDA turns | F6: Amount | J6: TEV | L6: =L4*L3 -> 11718496
C7: Revolver | F7: 0
C8: Bank Debt (Term Loan B) | E8: =D74 -> 4.5 | F8: =E8*L3 -> 3636774.6 | J8: Total Debt to be refi | L8: =Model!G70+Model!G68 -> 2214605
C9: Subordinated Debt | E9: =MIN(D75,D76-E8) -> 2 | F9: =E9*L3 -> 1616344.2
C10: Total Debt | E10: =F10/L3 -> 6.5 | F10: =SUM(F7:F9) -> 5253118.8 | J10: Unrestricted cash | L10: =L11 -> 289717
C11: % Total Sources | F11: =F10/F17 -> 0.42536566 | J11: Cash | L11: =Model!G44 -> 289717
C12: Cash on balance sheet | F12: =L10 -> 289717 | J12: Equity | L12: =L6-L8+L10 -> 9793607.8
C14: Sponsor Equity | E14: =F14/L3 -> 8.422486 | F14: =F17-F10-F12-F13 -> 6806818.4 | G14: =F14/SUM(F13:F14) -> 1
C15: % Total Sources | F15: =F14/F17 -> 0.55117482
C17: Total sources | E17: =F17/L3 -> 15.28097 | F17: =SUM(F24) -> 12349654
C19: Uses | F19: Amount
C20: Purchase of Equity | F20: =L12 -> 9793607.8
C21: Repayment of existing debt | F21: =L8 -> 2214605
C22: Fees (Financing and transaction) | F22: =G31+E34 -> 241441.42
C23: Cash on balance sheet | F23: =-Model!I144 -> 100000
C24: Total uses | F24: =SUM(F20:F23) -> 12349654
B26: X | C26: Fees
C27: Financing | D27: Funded | E27: EBITDA turns | F27: Fees rate | G27: Fees | H27: Term | I27: Fee amount/year
C28: Revolver | D28: =F7 -> 0 | E28: 0 | F28: 0.02 | G28: =D73*L3*0.005 -> 4040.8606 | H28: =G73 -> 5 | I28: =G28/H28 -> 808.17212
C29: Bank Debt (Term Loan B) | D29: =F8 -> 3636774.6 | E29: =E8 -> 4.5 | F29: =1-F74+0.0225 -> 0.0275 | G29: =D29*F29 -> 100011.3 | H29: =G74 -> 7 | I29: =G29/H29 -> 14287.329
C30: Subordinated Debt | D30: =F9 -> 1616344.2 | E30: =E9 -> 2 | F30: 0.0125 | G30: =D30*F30 -> 20204.303 | H30: =G75 -> 9 | I30: =G30/H30 -> 2244.9226
C31: Financing fees | G31: =SUM(G28:G30) -> 124256.46 | I31: =SUM(I28:I30) -> 17340.423
D33: % of offer value | E33: Fee
C34: Trans. fees | D34: 0.01 | E34: =D34*L6 -> 117184.96
C35: Equity % check | D35: =F15 -> 0.55117482
B36: X | C36: IRR Calculation
C37: =Model!C91 -> Fiscal year | H37: =Model!H3 -> 2025 | I37: =Model!I3 -> 2026 | J37: =Model!J3 -> 2027 | K37: =Model!K3 -> 2028 | L37: =Model!L3 -> 2029 | M37: =Model!M3 -> 2030
C38: =Model!C92 -> Fiscal year end date | H38: =Drivers!D9 -> 46022 | I38: =Model!I4 -> 46387 | J38: =Model!J4 -> 46752 | K38: =Model!K4 -> 47118 | L38: =Model!L4 -> 47483 | M38: =Model!M4 -> 47848
C40: Sponsor Equity Invested | H40: =-'Sources & Uses'!F14 -> -6806818.4 | I40: 0 | J40: 0 | K40: 0 | L40: 0 | M40: 0
C41: Dividends Pay | H41: 0 | I41: 0 | J41: 0 | K41: 0 | L41: 0 | M41: 0
C42: Sponsor Equity Value at exit | H42: 0 | I42: 0 | J42: 0 | K42: 0 | L42: 0 | M42: =M50 -> 16533438
C43: Total equity Flows | H43: =SUM(H40:H42) -> -6806818.4 | I43: =SUM(I40:I42) -> 0 | J43: =SUM(J40:J42) -> 0 | K43: =SUM(K40:K42) -> 0 | L43: =SUM(L40:L42) -> 0 | M43: =SUM(M40:M42) -> 16533438
C45: Management Option Pool | D45: 0.08 | M45: =D45*M49 -> 1437690.2
C47: Exit Value | D47: =Model!F191 -> 14.5 | M47: =D47*Model!M185 -> 22294944
C48: Net debt at exit | M48: =-(Model!M70+Model!M68)+Model!M44 -> -4323816.4
C49: Equity value | M49: =SUM(M47,M48) -> 17971128
C50: Sponsor Equity | D50: =1-D45 -> 0.92 | M50: =D50*M49 -> 16533438
C52: Sponsor IRR | D52: =IRR(H43:M43) -> 0.19421851
C53: Sponsor MOIC | D53: =M43/-H40 -> 2.4289524
C55: IRR SENSITIVITY: Entry Multiple vs Exit Multiple | F55: Exit Multiple
E56: =D52 -> 0.19421851 | F56: =G56-1 -> 12.5 | G56: =H56-1 -> 13.5 | H56: 14.5 | I56: =H56+1 -> 15.5
D57: Entry | E57: =E58-1 -> 12.5 | F57: 0.21506856 | G57: 0.23917693 | H57: 0.26154321 | I57: 0.28242736
D58: Mult. | E58: =E59-1 -> 13.5 | F58: 0.17998839 | G58: 0.20340073 | H58: 0.22512127 | I58: 0.24540248
E59: 14.5 | F59: 0.15022407 | G59: 0.17304585 | H59: 0.19421851 | I59: 0.21398814
E60: =E59+1 -> 15.5 | F60: 0.12446327 | G60: 0.14677393 | H60: 0.16747241 | I60: 0.18679927
E61: =E60+1 -> 16.5 | F61: 0.10181766 | G61: 0.123679 | H61: 0.14396063 | I61: 0.16289827
C63: MOIC SENSITIVITY: Entry Multiple vs Exit Multiple | F63: Exit Multiple
E64: =D53 -> 2.4289524 | F64: =G64-1 -> 12.5 | G64: =H64-1 -> 13.5 | H64: 14.5 | I64: =H64+1 -> 15.5
D65: Entry | E65: =E66-1 -> 12.5 | F65: 2.648524 | G65: 2.9219084 | H65: 3.1952928 | I65: 3.4686772
D66: Mult. | E66: =E67-1 -> 13.5 | F66: 2.2876452 | G66: 2.5237791 | H66: 2.7599131 | I66: 2.9960471
E67: 14.5 | F67: 2.0133174 | G67: 2.2211349 | H67: 2.4289524 | I67: 2.6367698
E68: =E67+1 -> 15.5 | F68: 1.7977379 | G68: 1.983303 | H68: 2.168868 | I68: 2.3544331
E69: =E68+1 -> 16.5 | F69: 1.6238602 | G69: 1.7914774 | H69: 1.9590945 | I69: 2.1267117
B71: X | C71: DEBT TERM SHEET CONSTRAINTS (from PJT Term Sheets, Day 22)
C72: Facility | D72: Max Turns | E72: Interest Rate | F72: OID | G72: Tenor (yrs) | H72: Amortization
C73: Revolving Credit Facility | D73: 1 | E73: 0.063 | F73: 1 | G73: 5 | H73: 0 | I73: S+175-225 bps; unfunded at close
C74: Term Loan B | D74: 4.5 | E74: 0.078 | F74: 0.995 | G74: 7 | H74: 0.01 | I74: S+350 bps; 99.50 OID; 101 soft call 6mo
C75: Senior Notes / HY Bond | D75: 2 | E75: 0.0875 | F75: 1 | G75: 9 | H75: 0 | I75: 8.75% fixed; non-callable 3yrs
C76: Maximum Total Leverage | D76: 6.5

Sheet vF
B2: X | C2: ="Financial Statement Model for "&D5 -> Financial Statement Model for StandardAero
C3: $ in thousands except per share
C5: Company name | D5: StandardAero
C6: Ticker | D6: SARO
C7: Latest closing share price | D7: 25.59
C8: Latest closing share price date | D8: 46119
C9: Latest fiscal year end date | D9: 46022
C10: Shares outstanding (millions) | D10: 334294 | N10: Outstanding at Dec 31, 2025 per 10-K BS. Jan 2026 repurchase of 1,637k shares (subsequent event) reduces to 332,657k.
C11: Case | D11: Description | F11: Source
C12: 1 | D12: =OFFSET(D12,$C$12,) -> [Case 1] | F12: =OFFSET(F12,$C$12,) -> Management Case
C13: 1 | D13: [Case 1] | F13: Management Case
C14: 2 | D14: [Case 2] | F14: Investment Case
C15: 3 | D15: [Case 3] | F15: Downside Projection
B17: X | C17: INCOME STATEMENT
C18: Fiscal year | E18: =F18-1 -> 2023 | F18: =G18-1 -> 2024 | G18: =YEAR(D9) -> 2025 | H18: =G18+1 -> 2026 | I18: =H18+1 -> 2027 | J18: =I18+1 -> 2028 | K18: =J18+1 -> 2029 | L18: =K18+1 -> 2030
C19: Fiscal year end date | E19: =EOMONTH(F19,-12) -> 45291 | F19: =EOMONTH(G19,-12) -> 45657 | G19: =D9 -> 46022 | H19: =EOMONTH(G19,12) -> 46387 | I19: =EOMONTH(H19,12) -> 46752 | J19: =EOMONTH(I19,12) -> 47118 | K19: =EOMONTH(J19,12) -> 47483 | L19: =EOMONTH(K19,12) -> 47848 | N19: Comments
C21: Revenue from Engine Repair | E21: 4049868 | F21: 4644739 | G21: 5353952 | H21: =G21*(1+H55) -> 6130275 | I21: =H21*(1+I55) -> 6896559.4 | J21: =I21*(1+J55) -> 7689663.8 | K21: =J21*(1+K55) -> 8497078.4 | L21: =K21*(1+L55) -> 9346786.3
C22: Revenue from Component Repair | E22: 513416 | F22: 592422 | G22: 708560 | H22: =G22*(1+H60) -> 829015.2 | I22: =H22*(1+I60) -> 961657.63 | J22: =I22*(1+J60) -> 1110714.6 | K22: =J22*(1+K60) -> 1282875.3 | L22: =K22*(1+L60) -> 1475306.6
C23: Total Revenue | E23: =E22+E21 -> 4563284 | F23: =F22+F21 -> 5237161 | G23: =G22+G21 -> 6062512 | H23: =H22+H21 -> 6959290.2 | I23: =I22+I21 -> 7858217.1 | J23: =J22+J21 -> 8800378.3 | K23: =K22+K21 -> 9779953.8 | L23: =L22+L21 -> 10822093
C24: Cost of sales | E24: -3927965 | F24: -4483019 | G24: -5165060 | H24: =H25-H23 -> -5901478.1 | I24: =I25-I23 -> -6640193.4 | J24: =J25-J23 -> -7392317.8 | K24: =K25-K23 -> -8185821.3 | L24: =L25-L23 -> -9036447.6
C25: Gross Profit | E25: =SUM(E23:E24) -> 635319 | F25: =SUM(F23:F24) -> 754142 | G25: =SUM(G23:G24) -> 897452 | H25: =H23*H66 -> 1057812.1 | I25: =I23*I66 -> 1218023.6 | J25: =J23*J66 -> 1408060.5 | K25: =K23*K66 -> 1594132.5 | L25: =L23*L66 -> 1785645.3
C26: Amortisation of intangible assets | E26: -93681 | F26: -95457 | G26: -98681 | H26: =-H187*0.7516 -> -91261.527 | I26: =-I187*0.7516 -> -83538.837 | J26: =-J187*0.7516 -> -82367.092 | K26: =-K187*0.7516 -> -79979.259 | L26: =-L187*0.7516 -> -79200.602 | N26: Formula: Total Amortization from intangible Assets acc to note 9× 75% to excludes OEM auth amort which goes through COGS per Note 9.
C27: Selling, general & administrative | E27: -202766 | F27: -254092 | G27: -247703 | H27: =-H23*H71 -> -285330.9 | I27: =-I23*I71 -> -314328.68 | J27: =-J23*J71 -> -343214.75 | K27: =-K23*K71 -> -371638.24 | L27: =-L23*L71 -> -400417.44
C28: Acquisition Cost | E28: -1514 | F28: -1374 | G28: 0 | H28: =G28 -> 0 | I28: =H28 -> 0 | J28: =I28 -> 0 | K28: =J28 -> 0 | L28: =K28 -> 0
C29: Operating profit (EBIT) | E29: =SUM(E25:E28) -> 337358 | F29: =SUM(F25:F28) -> 403219 | G29: =SUM(G25:G28) -> 551068 | H29: =SUM(H25:H28) -> 681219.69 | I29: =SUM(I25:I28) -> 820156.12 | J29: =SUM(J25:J28) -> 982478.68 | K29: =SUM(K25:K28) -> 1142515 | L29: =SUM(L25:L28) -> 1306027.3
C30: Interest income | E30: 0 | F30: 0 | G30: 0 | H30: =H233 -> 0 | I30: =I233 -> 0 | J30: =J233 -> 0 | K30: =K233 -> 0 | L30: =L233 -> 0
C31: Interest expense | E31: -309645 | F31: -282507 | G31: -174217 | H31: =H219 -> -138781.63 | I31: =I219 -> -134154.66 | J31: =J219 -> -126377.68 | K31: =K219 -> -117025.71 | L31: =L219 -> -106098.74
C32: Refinancing costs | E32: -19921 | F32: -23700 | G32: 0 | H32: =G32 -> 0 | I32: =H32 -> 0 | J32: =I32 -> 0 | K32: =J32 -> 0 | L32: =K32 -> 0
C33: Loss on debt extinguishment | E33: -6182 | F33: -15255 | G33: 0 | H33: =G33 -> 0 | I33: =H33 -> 0 | J33: =I33 -> 0 | K33: =J33 -> 0 | L33: =K33 -> 0
C34: Other expense, net | E34: 3509 | F34: 0 | G34: 0 | H34: 0 | I34: 0 | J34: 0 | K34: 0 | L34: 0
C35: Pretax profit | E35: =SUM(E29:E34) -> 5119 | F35: =SUM(F29:F34) -> 81757 | G35: =SUM(G29:G34) -> 376851 | H35: =SUM(H29:H34) -> 542438.06 | I35: =SUM(I29:I34) -> 686001.47 | J35: =SUM(J29:J34) -> 856101 | K35: =SUM(K29:K34) -> 1025489.2 | L35: =SUM(L29:L34) -> 1199928.6
C36: Taxes | E36: -40180 | F36: -70783 | G36: -99435 | H36: =-H35*H76 -> -135609.52 | I36: =-I35*I76 -> -171500.37 | J36: =-J35*J76 -> -214025.25 | K36: =-K35*K76 -> -256372.31 | L36: =-L35*L76 -> -299982.14
C37: Net income | E37: =SUM(E35:E36) -> -35061 | F37: =SUM(F35:F36) -> 10974 | G37: =SUM(G35:G36) -> 277416 | H37: =SUM(H35:H36) -> 406828.55 | I37: =SUM(I35:I36) -> 514501.1 | J37: =SUM(J35:J36) -> 642075.75 | K37: =SUM(K35:K36) -> 769116.94 | L37: =SUM(L35:L36) -> 899946.41
C39: Depreciation & amortization | E39: 197104 | F39: 188164 | G39: 193664 | H39: =H189 -> 193053.33 | I39: =I189 -> 192030.77 | J39: =J189 -> 200169.21 | K39: =K189 -> 207074.75 | L39: =L189 -> 216765.24
C40: EBITDA | E40: =E29+E39 -> 534462 | F40: =F29+F39 -> 591383 | G40: =G29+G39 -> 744732 | H40: =H29+H39 -> 874273.02 | I40: =I29+I39 -> 1012186.9 | J40: =J29+J39 -> 1182647.9 | K40: =K29+K39 -> 1349589.7 | L40: =L29+L39 -> 1522792.5
C41: Stock based compensation | E41: - | F41: 17376 | G41: 13237 | H41: 13500 | I41: 14000 | J41: 14500 | K41: 15000 | L41: 15500
C42: Business transformation costs | E42: - | F42: 43239 | G42: 26028 | H42: - | I42: - | J42: - | K42: - | L42: -
C43: IPO related cost | E43: - | F43: 26909 | G43: 0 | H43: - | I43: - | J43: - | K43: - | L43: -
C44: Integration costs and severance | E44: - | F44: 2782 | G44: 5601 | H44: - | I44: - | J44: - | K44: - | L44: -
C45: Acquisition costs | E45: - | F45: 1374 | G45: 0 | H45: - | I45: - | J45: - | K45: - | L45: -
C46: Insurance recovery | E46: - | F46: 0 | G46: -3000 | H46: - | I46: - | J46: - | K46: - | L46: -
C47: Loss on disposals | E47: - | F47: 0 | G47: 2764 | H47: - | I47: - | J47: - | K47: - | L47: -
C48: Secondary offering costs | E48: - | F48: 0 | G48: 4990 | H48: - | I48: - | J48: - | K48: - | L48: -
C49: Other | E49: - | F49: 7470 | G49: 13820 | H49: - | I49: - | J49: - | K49: - | L49: -
C50: Adj EBITDA | E50: 561100 | F50: =SUM(F40:F49) -> 690533 | G50: =SUM(G40:G49) -> 808172 | H50: =H23*H81 -> 904707.73 | I50: =I23*I81 -> 1021568.2 | J50: =J23*J81 -> 1144049.2 | K50: =K23*K81 -> 1271394 | L50: =L23*L81 -> 1406872.1
C52: Growth rates & margins
C53: Revenue growth | F53: =(F23-E23)/E23 -> 0.14767369 | G53: =(G23-F23)/F23 -> 0.15759512 | H53: =(H23-G23)/G23 -> 0.14792189 | I53: =(I23-H23)/H23 -> 0.12916932 | J53: =(J23-I23)/I23 -> 0.11989504 | K53: =(K23-J23)/J23 -> 0.11131061 | L53: =(L23-K23)/K23 -> 0.1065587 | N53: LEAP/CFM56 shop visits ramping; ~80% of revenue under long-term agreements; aging installed base drives MRO demand through 2030; military spending elevated due to geopolitical tensions; business aviation fleet growth
C55: Engine Service growth rate | F55: =OFFSET(F55,$C$12,) -> 0.14688652 | G55: =OFFSET(G55,$C$12,) -> 0.15269168 | H55: =OFFSET(H55,$C$12,) -> 0.145 | I55: =OFFSET(I55,$C$12,) -> 0.125 | J55: =OFFSET(J55,$C$12,) -> 0.115 | K55: =OFFSET(K55,$C$12,) -> 0.105 | L55: =OFFSET(L55,$C$12,) -> 0.1
C56: =$C$13 -> 1 | D56: =$D$13 -> [Case 1] | F56: =(F21-E21)/E21 -> 0.14688652 | G56: =(G21-F21)/F21 -> 0.15269168 | H56: 0.145 | I56: 0.125 | J56: 0.115 | K56: 0.105 | L56: 0.1
C57: =$C$14 -> 2 | D57: =$D$14 -> [Case 2] | H57: 0.12 | I57: 0.1 | J57: 0.09 | K57: 0.08 | L57: 0.07 | N57: Haircut by 2–3pts Because supply chain parts availability risk and LEAP ramp execution uncertainty are flagged as key risks in the 10-K Item 1A.
C58: =$C$15 -> 3 | D58: =$D$15 -> [Case 3]
C60: Component Repair Service growth rate | F60: =OFFSET(F60,$C$12,) -> 0.15388301 | G60: =OFFSET(G60,$C$12,) -> 0.19603931 | H60: =OFFSET(H60,$C$12,) -> 0.17 | I60: =OFFSET(I60,$C$12,) -> 0.16 | J60: =OFFSET(J60,$C$12,) -> 0.155 | K60: =OFFSET(K60,$C$12,) -> 0.155 | L60: =OFFSET(L60,$C$12,) -> 0.15
C61: =$C$13 -> 1 | D61: =$D$13 -> [Case 1] | F61: =(F22-E22)/E22 -> 0.15388301 | G61: =(G22-F22)/F22 -> 0.19603931 | H61: 0.17 | I61: 0.16 | J61: 0.155 | K61: 0.155 | L61: 0.15
C62: =$C$14 -> 2 | D62: =$D$14 -> [Case 2] | H62: 0.14 | I62: 0.12 | J62: 0.11 | K62: 0.1 | L62: 0.09 | N62: Component Repair has been the faster-growing segment (19.6% growth in 2025) driven by Aero Turbine and military demand. But 28.6% Adj EBITDA margins can't expand forever, and the military helicopter market is cyclical.
C63: =$C$15 -> 3 | D63: =$D$15 -> [Case 3]
C65: Gross profit margin | E65: =OFFSET(E65,$C$12,) -> 0.13922408 | F65: =OFFSET(F65,$C$12,) -> 0.14399825 | G65: =OFFSET(G65,$C$12,) -> 0.14803303 | H65: =OFFSET(H65,$C$12,) -> 0.152 | I65: =OFFSET(I65,$C$12,) -> 0.155 | J65: =OFFSET(J65,$C$12,) -> 0.16 | K65: =OFFSET(K65,$C$12,) -> 0.163 | L65: =OFFSET(L65,$C$12,) -> 0.165
C66: =$C$13 -> 1 | D66: =$D$13 -> [Case 1] | E66: =E25/E23 -> 0.13922408 | F66: =F25/F23 -> 0.14399825 | G66: =G25/G23 -> 0.14803303 | H66: 0.152 | I66: 0.155 | J66: 0.16 | K66: 0.163 | L66: 0.165 | N66: LEAP learning curve progressively reduces industrialization costs; mix shift toward higher-margin Component Repair Services; operating leverage on fixed overhead as volumes scale; partially offset by material cost inflation pass-through
C67: =$C$14 -> 2 | D67: =$D$14 -> [Case 2] | H67: 0.148 | I67: 0.15 | J67: 0.152 | K67: 0.153 | L67: 0.154 | N67: Materials are 71.5% of COGS, and tariff risk remains live even after the IEEPA ruling was struck down. LEAP industrialization savings are real but partially offset by inflationary labor pressures. The 10-K explicitly says "timing delays may impact margins" on tariff pass-throughs.
C68: =$C$15 -> 3 | D68: =$D$15 -> [Case 3]
C70: SG&A % of sales | E70: =OFFSET(E70,$C$12,) -> 0.044434228 | F70: =OFFSET(F70,$C$12,) -> 0.048517126 | G70: =OFFSET(G70,$C$12,) -> 0.040858146 | H70: =OFFSET(H70,$C$12,) -> 0.041 | I70: =OFFSET(I70,$C$12,) -> 0.04 | J70: =OFFSET(J70,$C$12,) -> 0.039 | K70: =OFFSET(K70,$C$12,) -> 0.038 | L70: =OFFSET(L70,$C$12,) -> 0.037
C71: =$C$13 -> 1 | D71: =$D$13 -> [Case 1] | E71: =-E27/E23 -> 0.044434228 | F71: =-F27/F23 -> 0.048517126 | G71: =-G27/G23 -> 0.040858146 | H71: 0.041 | I71: 0.04 | J71: 0.039 | K71: 0.038 | L71: 0.037 | N71: SG&A already declined to 4.1% in 2025 (from 4.9% in 2024). Post-IPO one-time costs are behind the company. Further leverage expected as revenue scales against relatively fixed corporate overhead and sales force
C72: =$C$14 -> 2 | D72: =$D$14 -> [Case 2] | H72: 0.041 | I72: 0.04 | J72: 0.04 | K72: 0.039 | L72: 0.039 | N72: The 10-K notes material weaknesses in internal controls requiring additional personnel and compliance investment. Remediation costs will partially offset the operating leverage from revenue growth.
C73: =$C$15 -> 3 | D73: =$D$15 -> [Case 3]
C75: Tax rate | E75: =OFFSET(E75,$C$12,) -> 7.8491893 | F75: =OFFSET(F75,$C$12,) -> 0.86577296 | G75: =OFFSET(G75,$C$12,) -> 0.2638576 | H75: =OFFSET(H75,$C$12,) -> 0.25 | I75: =OFFSET(I75,$C$12,) -> 0.25 | J75: =OFFSET(J75,$C$12,) -> 0.25 | K75: =OFFSET(K75,$C$12,) -> 0.25 | L75: =OFFSET(L75,$C$12,) -> 0.25
C76: =$C$13 -> 1 | D76: =$D$13 -> [Case 1] | E76: =-E36/E35 -> 7.8491893 | F76: =-F36/F35 -> 0.86577296 | G76: =-G36/G35 -> 0.2638576 | H76: 0.25 | I76: 0.25 | J76: 0.25 | K76: 0.25 | L76: 0.25 | N76: 2025 effective rate of 26.4% includes GILTI, state taxes (California heavy), and changes in uncertain tax benefits. OBBBA provisions (signed Jul 4, 2025) restore favorable business tax treatment in 2026–2027 rate likely drifts toward 24–26% as Canada/foreign mix optimizes and interest carryforwards begin to release
C77: =$C$14 -> 2 | D77: =$D$14 -> [Case 2] | H77: 0.26 | I77: 0.26 | J77: 0.26 | K77: 0.26 | L77: 0.26 | N77: The OBBBA provisions are recent and their permanence is uncertain
C78: =$C$15 -> 3 | D78: =$D$15 -> [Case 3]
C80: Adjusted EBITDA Margin | E80: =OFFSET(E80,$C$12,) -> 0.12295969 | F80: =OFFSET(F80,$C$12,) -> 0.13185254 | G80: =OFFSET(G80,$C$12,) -> 0.13330646 | H80: =OFFSET(H80,$C$12,) -> 0.13 | I80: =OFFSET(I80,$C$12,) -> 0.13 | J80: =OFFSET(J80,$C$12,) -> 0.13 | K80: =OFFSET(K80,$C$12,) -> 0.13 | L80: =OFFSET(L80,$C$12,) -> 0.13
C81: =$C$13 -> 1 | D81: =$D$13 -> [Case 1] | E81: =E50/E23 -> 0.12295969 | F81: =F50/F23 -> 0.13185254 | G81: =G50/G23 -> 0.13330646 | H81: 0.13 | I81: 0.13 | J81: 0.13 | K81: 0.13 | L81: 0.13
C82: =$C$14 -> 2 | D82: =$D$14 -> [Case 2] | H82: 0.125 | I82: 0.125 | J82: 0.128 | K82: 0.13 | L82: 0.13 | N82: Business transformation costs ($26M in 2025) won't go to zero as the company is still ramping LEAP and may need ongoing industrialization investment.
C83: =$C$15 -> 3 | D83: =$D$15 -> [Case 3]
C85: Acquisitions net of Cash | E85: =OFFSET(E85,$C$12,) -> 0 | F85: =OFFSET(F85,$C$12,) -> 0 | G85: =OFFSET(G85,$C$12,) -> 0 | H85: =OFFSET(H85,$C$12,) -> 0 | I85: =OFFSET(I85,$C$12,) -> 75000 | J85: =OFFSET(J85,$C$12,) -> 75000 | K85: =OFFSET(K85,$C$12,) -> 100000 | L85: =OFFSET(L85,$C$12,) -> 100000
C86: =$C$13 -> 1 | D86: =$D$13 -> [Case 1] | H86: 0 | I86: 75000 | J86: 75000 | K86: 100000 | L86: 100000
C87: =$C$14 -> 2 | D87: =$D$14 -> [Case 2] | H87: 0 | I87: 50000 | J87: 50000 | K87: 75000 | L87: 75000 | N87: We assume the company acquires but at a lower cadence since integration capacity is constrained (the 10-K discloses $5.6M of integration costs still flowing through in 2025)
C88: =$C$15 -> 3 | D88: =$D$15 -> [Case 3]
C90: Share Repurchases | E90: =OFFSET(E90,$C$12,) -> 0 | F90: =OFFSET(F90,$C$12,) -> 0 | G90: =OFFSET(G90,$C$12,) -> 0 | H90: =OFFSET(H90,$C$12,) -> 50000 | I90: =OFFSET(I90,$C$12,) -> 100000 | J90: =OFFSET(J90,$C$12,) -> 100000 | K90: =OFFSET(K90,$C$12,) -> 100000 | L90: =OFFSET(L90,$C$12,) -> 100000
C91: =$C$13 -> 1 | D91: =$D$13 -> [Case 1] | H91: 50000 | I91: 100000 | J91: 100000 | K91: 100000 | L91: 100000
C92: =$C$14 -> 2 | D92: =$D$14 -> [Case 2] | H92: 50000 | I92: 75000 | J92: 75000 | K92: 75000 | L92: 75000 | N92: The New Credit Agreement also has restricted payment covenants that may limit buyback pace at higher leverage.
C93: =$C$15 -> 3 | D93: =$D$15 -> [Case 3]
C95: Voluntary Debt Prepayment | E95: =OFFSET(E95,$C$12,) -> 0 | F95: =OFFSET(F95,$C$12,) -> 0 | G95: =OFFSET(G95,$C$12,) -> 0 | H95: =OFFSET(H95,$C$12,) -> 0 | I95: =OFFSET(I95,$C$12,) -> 100000 | J95: =OFFSET(J95,$C$12,) -> 100000 | K95: =OFFSET(K95,$C$12,) -> 150000 | L95: =OFFSET(L95,$C$12,) -> 150000
C96: =$C$13 -> 1 | D96: =$D$13 -> [Case 1] | H96: 0 | I96: 100000 | J96: 100000 | K96: 150000 | L96: 150000
C97: =$C$14 -> 2 | D97: =$D$14 -> [Case 2] | H97: 0 | I97: 75000 | J97: 100000 | K97: 100000 | L97: 125000 | N97: We assume slightly less prepayment since lower revenue growth means lower FCF. But deleveraging is still a priority
C98: =$C$15 -> 3 | D98: =$D$15 -> [Case 3]
B101: X | C101: BALANCE SHEET
C102: =C18 -> Fiscal year | E102: =E18 -> 2023 | F102: =F18 -> 2024 | G102: =G18 -> 2025 | H102: =H18 -> 2026 | I102: =I18 -> 2027 | J102: =J18 -> 2028 | K102: =K18 -> 2029 | L102: =L18 -> 2030
C103: =C19 -> Fiscal year end date | E103: =E19 -> 45291 | F103: =F19 -> 45657 | G103: =G19 -> 46022 | H103: =H19 -> 46387 | I103: =I19 -> 46752 | J103: =J19 -> 47118 | K103: =K19 -> 47483 | L103: =L19 -> 47848
C104: ASSETS
C105: Current Assets
C106: Cash & equivalents, ST and LT marketable securities | F106: 102581 | G106: 289717 | H106: =G106+H173 -> 510769.65 | I106: =H106+I173 -> 601266.37 | J106: =I106+J173 -> 806291.5 | K106: =J106+K173 -> 1048912.7 | L106: =K106+L173 -> 1404460.5
C107: Accounts receivable | F107: 580668 | G107: 654390 | H107: =G107*(1+H53) -> 751188.61 | I107: =H107*(1+I53) -> 848219.13 | J107: =I107*(1+J53) -> 949916.4 | K107: =J107*(1+K53) -> 1055652.2 | L107: =K107*(1+L53) -> 1168141.1
C108: Contract Assets | F108: 915200 | G108: 1071703 | H108: =G108*(1+H53) -> 1230231.3 | I108: =H108*(1+I53) -> 1389139.5 | J108: =I108*(1+J53) -> 1555690.4 | K108: =J108*(1+K53) -> 1728855.3 | L108: =K108*(1+L53) -> 1913079.8
C109: Inventories | F109: 847018 | G109: 827691 | H109: =G109*(1+((H24-G24)/G24)) -> 945700.6 | I109: =H109*(1+((I24-H24)/H24)) -> 1064078.3 | J109: =I109*(1+((J24-I24)/I24)) -> 1184604.8 | K109: =J109*(1+((K24-J24)/J24)) -> 1311762.2 | L109: =K109*(1+((L24-K24)/K24)) -> 1448073.5
C110: Other current assets | F110: 29707 | G110: 42776 | H110: =G110*(1+H53) -> 49103.507 | I110: =H110*(1+I53) -> 55446.174 | J110: =I110*(1+J53) -> 62093.895 | K110: =J110*(1+K53) -> 69005.604 | L110: =K110*(1+L53) -> 76358.751
C111: Income tax receivable | F111: 9960 | G111: 10182 | H111: =G111 -> 10182 | I111: =H111 -> 10182 | J111: =I111 -> 10182 | K111: =J111 -> 10182 | L111: =K111 -> 10182
C112: Total current assets | F112: =SUM(F106:F111) -> 2485134 | G112: =SUM(G106:G111) -> 2896459 | H112: =SUM(H106:H111) -> 3497175.7 | I112: =SUM(I106:I111) -> 3968331.5 | J112: =SUM(J106:J111) -> 4568779 | K112: =SUM(K106:K111) -> 5224370 | L112: =SUM(L106:L111) -> 6020295.7
C113: Property, plant & equipment | F113: 568607 | G113: 579971 | H113: =H182 -> 602929.44 | I113: =I182 -> 628853.4 | J113: =J182 -> 657885.52 | K113: =K182 -> 690149.22 | L113: =L182 -> 725850.9
C114: Operating lease right of use asset | F114: 172206 | G114: 222151 | H114: =G114 -> 222151 | I114: =H114 -> 222151 | J114: =I114 -> 222151 | K114: =J114 -> 222151 | L114: =K114 -> 222151
C115: Customer relationships | F115: 1004701 | G115: 920432 | H115: =G115 - H187*0.6425 + (-H163)*0.4 -> 842417.72 | I115: =H115 - I187*0.6425 + (-I163)*0.4 -> 801005.13 | J115: =I115 - J187*0.6425 + (-J163)*0.4 -> 760594.2 | K115: =J115 - K187*0.6425 + (-K163)*0.4 -> 732224.49 | L115: =K115 - L187*0.6425 + (-L163)*0.4 -> 704520.41 | N115: Formula: Prior year − amort (Note 9 × 64.2% CR share) + new CRs from M&A (Row 110 × 40% allocation).
C116: Other intangible assets | F116: 291487 | G116: 244877 | H116: =G116 - H187*0.3575 + (-H166) -> 228468.28 | I116: =H116 - I187*0.3575 + (-I166) -> 215732.87 | J116: =I116 - J187*0.3575 + (-J166) -> 203554.8 | K116: =J116 - K187*0.3575 + (-K166) -> 192512.51 | L116: =K116 - L187*0.3575 + (-L166) -> 181840.59 | N116: Formula: Prior year − amort (Note 9 × 35.8% Other share) + OEM license purchases (Row 113)
C117: Goodwill | F117: 1685970 | G117: 1684255 | H117: =G117 + (-H163)*0.6 -> 1684255 | I117: =H117 + (-I163)*0.6 -> 1729255 | J117: =I117 + (-J163)*0.6 -> 1774255 | K117: =J117 + (-K163)*0.6 -> 1834255 | L117: =K117 + (-L163)*0.6 -> 1894255 | N117: Formula: Prior year + M&A goodwill (Row 110 × 60% allocation). Per Aero Turbine: ~60% of purchase price allocated to goodwill, ~40% to customer relationships.
...

Sheet vF (2)
B2: X | C2: ="Financial Statement Model for "&D5 -> Financial Statement Model for StandardAero
C3: $ in thousands except per share
C5: Company name | D5: StandardAero
C6: Ticker | D6: SARO
D7: 1
C8: Latest closing share price | D8: 25.59
C9: Latest closing share price date | D9: 46119
C10: Latest fiscal year end date | D10: 46022
C11: Shares outstanding (millions) | D11: 334294 | M11: Outstanding at Dec 31, 2025 per 10-K BS. Jan 2026 repurchase of 1,637k shares (subsequent event) reduces to 332,657k.
B13: X | C13: INCOME STATEMENT
C14: Fiscal year | D14: =E14-1 -> 2023 | E14: =F14-1 -> 2024 | F14: =YEAR(D10) -> 2025 | G14: =F14+1 -> 2026 | H14: =G14+1 -> 2027 | I14: =H14+1 -> 2028 | J14: =I14+1 -> 2029 | K14: =J14+1 -> 2030
C15: Fiscal year end date | D15: =EOMONTH(E15,-12) -> 45291 | E15: =EOMONTH(F15,-12) -> 45657 | F15: =D10 -> 46022 | G15: =EOMONTH(F15,12) -> 46387 | H15: =EOMONTH(G15,12) -> 46752 | I15: =EOMONTH(H15,12) -> 47118 | J15: =EOMONTH(I15,12) -> 47483 | K15: =EOMONTH(J15,12) -> 47848 | M15: Comments
C17: Revenue from Engine Repair | D17: 4049868 | E17: 4644739 | F17: 5353952 | G17: =F17*(1+G50) -> 6130275 | H17: =G17*(1+H50) -> 6896559.4 | I17: =H17*(1+I50) -> 7689663.8 | J17: =I17*(1+J50) -> 8497078.4 | K17: =J17*(1+K50) -> 9346786.3
C18: Revenue from Component Repair | D18: 513416 | E18: 592422 | F18: 708560 | G18: =F18*(1+G51) -> 829015.2 | H18: =G18*(1+H51) -> 961657.63 | I18: =H18*(1+I51) -> 1110714.6 | J18: =I18*(1+J51) -> 1282875.3 | K18: =J18*(1+K51) -> 1475306.6
C19: Total Revenue | D19: =D18+D17 -> 4563284 | E19: =E18+E17 -> 5237161 | F19: =F18+F17 -> 6062512 | G19: =G18+G17 -> 6959290.2 | H19: =H18+H17 -> 7858217.1 | I19: =I18+I17 -> 8800378.3 | J19: =J18+J17 -> 9779953.8 | K19: =K18+K17 -> 10822093
C20: Cost of sales | D20: -3927965 | E20: -4483019 | F20: -5165060 | G20: =G21-G19 -> -5901478.1 | H20: =H21-H19 -> -6640193.4 | I20: =I21-I19 -> -7392317.8 | J20: =J21-J19 -> -8185821.3 | K20: =K21-K19 -> -9036447.6
C21: Gross Profit | D21: =SUM(D19:D20) -> 635319 | E21: =SUM(E19:E20) -> 754142 | F21: =SUM(F19:F20) -> 897452 | G21: =G19*G52 -> 1057812.1 | H21: =H19*H52 -> 1218023.6 | I21: =I19*I52 -> 1408060.5 | J21: =J19*J52 -> 1594132.5 | K21: =K19*K52 -> 1785645.3
C22: Amortisation of intangible assets | D22: -93681 | E22: -95457 | F22: -98681 | G22: =-G143*75% -> -91067.25 | H22: =-H143*75% -> -83361 | I22: =-I143*75% -> -82191.75 | J22: =-J143*75% -> -79809 | K22: =-K143*75% -> -79032 | M22: Formula: Total Amortization from intangible Assets acc to note 9× 75% to excludes OEM auth amort which goes through COGS per Note 9.
C23: Selling, general & administrative | D23: -202766 | E23: -254092 | F23: -247703 | G23: =-G19*G53 -> -285330.9 | H23: =-H19*H53 -> -314328.68 | I23: =-I19*I53 -> -343214.75 | J23: =-J19*J53 -> -371638.24 | K23: =-K19*K53 -> -400417.44
C24: Acquisition Cost | D24: -1514 | E24: -1374 | F24: 0 | G24: =F24 -> 0 | H24: =G24 -> 0 | I24: =H24 -> 0 | J24: =I24 -> 0 | K24: =J24 -> 0
C25: Operating profit (EBIT) | D25: =SUM(D21:D24) -> 337358 | E25: =SUM(E21:E24) -> 403219 | F25: =SUM(F21:F24) -> 551068 | G25: =SUM(G21:G24) -> 681413.97 | H25: =SUM(H21:H24) -> 820333.96 | I25: =SUM(I21:I24) -> 982654.03 | J25: =SUM(J21:J24) -> 1142685.2 | K25: =SUM(K21:K24) -> 1306195.9
C26: Interest income | D26: 0 | E26: 0 | F26: 0 | G26: =G189 -> 0 | H26: =H189 -> 0 | I26: =I189 -> 0 | J26: =J189 -> 0 | K26: =K189 -> 0
C27: Interest expense | D27: -309645 | E27: -282507 | F27: -174217 | G27: =G175 -> -138781.63 | H27: =H175 -> -134154.66 | I27: =I175 -> -126377.68 | J27: =J175 -> -117025.71 | K27: =K175 -> -106098.74
C28: Refinancing costs | D28: -19921 | E28: -23700 | F28: 0 | G28: =F28 -> 0 | H28: =G28 -> 0 | I28: =H28 -> 0 | J28: =I28 -> 0 | K28: =J28 -> 0
C29: Loss on debt extinguishment | D29: -6182 | E29: -15255 | F29: 0 | G29: =F29 -> 0 | H29: =G29 -> 0 | I29: =H29 -> 0 | J29: =I29 -> 0 | K29: =J29 -> 0
C30: Other expense, net | D30: 3509 | E30: 0 | F30: 0 | G30: 0 | H30: 0 | I30: 0 | J30: 0 | K30: 0
C31: Pretax profit | D31: =SUM(D25:D30) -> 5119 | E31: =SUM(E25:E30) -> 81757 | F31: =SUM(F25:F30) -> 376851 | G31: =SUM(G25:G30) -> 542632.34 | H31: =SUM(H25:H30) -> 686179.3 | I31: =SUM(I25:I30) -> 856276.34 | J31: =SUM(J25:J30) -> 1025659.5 | K31: =SUM(K25:K30) -> 1200097.2
C32: Taxes | D32: -40180 | E32: -70783 | F32: -99435 | G32: =-G31*G54 -> -135658.08 | H32: =-H31*H54 -> -171544.83 | I32: =-I31*I54 -> -214069.09 | J32: =-J31*J54 -> -256414.88 | K32: =-K31*K54 -> -300024.29
C33: Net income | D33: =SUM(D31:D32) -> -35061 | E33: =SUM(E31:E32) -> 10974 | F33: =SUM(F31:F32) -> 277416 | G33: =SUM(G31:G32) -> 406974.25 | H33: =SUM(H31:H32) -> 514634.48 | I33: =SUM(I31:I32) -> 642207.26 | J33: =SUM(J31:J32) -> 769244.63 | K33: =SUM(K31:K32) -> 900072.86
C35: Depreciation & amortization | D35: 197104 | E35: 188164 | F35: 193664 | G35: =G145 -> 193053.33 | H35: =H145 -> 192030.77 | I35: =I145 -> 200169.21 | J35: =J145 -> 207074.75 | K35: =K145 -> 216765.24
C36: EBITDA | D36: =D25+D35 -> 534462 | E36: =E25+E35 -> 591383 | F36: =F25+F35 -> 744732 | G36: =G25+G35 -> 874467.29 | H36: =H25+H35 -> 1012364.7 | I36: =I25+I35 -> 1182823.2 | J36: =J25+J35 -> 1349760 | K36: =K25+K35 -> 1522961.1
C37: Stock based compensation | E37: 17376 | F37: 13237
C38: Business transformation costs | E38: 43239 | F38: 26028
C39: IPO related cost | E39: 26909 | F39: 0
C40: Integration costs and severance | E40: 2782 | F40: 5601
C41: Acquisition costs | E41: 1374 | F41: 0
C42: Insureance recovery | E42: 0 | F42: -3000
C43: Loss on disposals | E43: 0 | F43: 2764
C44: Secondary offering costs | E44: 0 | F44: 4990
C45: Other | E45: 7470 | F45: 13820
C46: Adj EBITDA | D46: 561100 | E46: =SUM(E36:E45) -> 690533 | F46: =SUM(F36:F45) -> 808172 | G46: =G19*G55 -> 904707.73 | H46: =H19*H55 -> 1021568.2 | I46: =I19*I55 -> 1144049.2 | J46: =J19*J55 -> 1271394 | K46: =K19*K55 -> 1406872.1
C48: Growth rates & margins
C49: Revenue growth | E49: =(E19-D19)/D19 -> 0.14767369 | F49: =(F19-E19)/E19 -> 0.15759512 | G49: =(G19-F19)/F19 -> 0.14792189 | H49: =(H19-G19)/G19 -> 0.12916932 | I49: =(I19-H19)/H19 -> 0.11989504 | J49: =(J19-I19)/I19 -> 0.11131061 | K49: =(K19-J19)/J19 -> 0.1065587 | M49: LEAP/CFM56 shop visits ramping; ~80% of revenue under long-term agreements; aging installed base drives MRO demand through 2030; military spending elevated due to geopolitical tensions; business aviation fleet growth
C50: Engine Service growth rate | E50: =(E17-D17)/D17 -> 0.14688652 | F50: =(F17-E17)/E17 -> 0.15269168 | G50: 0.145 | H50: 0.125 | I50: 0.115 | J50: 0.105 | K50: 0.1
C51: Component Repair Service growth rate | E51: =(E18-D18)/D18 -> 0.15388301 | F51: =(F18-E18)/E18 -> 0.19603931 | G51: 0.17 | H51: 0.16 | I51: 0.155 | J51: 0.155 | K51: 0.15
C52: Gross profit margin | D52: =D21/D19 -> 0.13922408 | E52: =E21/E19 -> 0.14399825 | F52: =F21/F19 -> 0.14803303 | G52: 0.152 | H52: 0.155 | I52: 0.16 | J52: 0.163 | K52: 0.165 | M52: LEAP learning curve progressively reduces industrialization costs; mix shift toward higher-margin Component Repair Services; operating leverage on fixed overhead as volumes scale; partially offset by material cost inflation pass-through
C53: SG&A % of sales | D53: =-D23/D19 -> 0.044434228 | E53: =-E23/E19 -> 0.048517126 | F53: =-F23/F19 -> 0.040858146 | G53: 0.041 | H53: 0.04 | I53: 0.039 | J53: 0.038 | K53: 0.037 | M53: SG&A already declined to 4.1% in 2025 (from 4.9% in 2024). Post-IPO one-time costs are behind the company. Further leverage expected as revenue scales against relatively fixed corporate overhead and sales force
C54: Tax rate | D54: =-D32/D31 -> 7.8491893 | E54: =-E32/E31 -> 0.86577296 | F54: =-F32/F31 -> 0.2638576 | G54: 0.25 | H54: 0.25 | I54: 0.25 | J54: 0.25 | K54: 0.25 | M54: 2025 effective rate of 26.4% includes GILTI, state taxes (California heavy), and changes in uncertain tax benefits. OBBBA provisions (signed Jul 4, 2025) restore favorable business tax treatment in 2026–2027 rate likely drifts toward 24–26% as Canada/foreign mix optimizes and interest carryforwards begin to release
C55: Adjusted EBITDA Margin | D55: =D46/D19 -> 0.12295969 | E55: =E46/E19 -> 0.13185254 | F55: =F46/F19 -> 0.13330646 | G55: 0.13 | H55: 0.13 | I55: 0.13 | J55: 0.13 | K55: 0.13
B57: X | C57: BALANCE SHEET
C58: =C14 -> Fiscal year | D58: =D14 -> 2023 | E58: =E14 -> 2024 | F58: =F14 -> 2025 | G58: =G14 -> 2026 | H58: =H14 -> 2027 | I58: =I14 -> 2028 | J58: =J14 -> 2029 | K58: =K14 -> 2030
C59: =C15 -> Fiscal year end date | D59: =D15 -> 45291 | E59: =E15 -> 45657 | F59: =F15 -> 46022 | G59: =G15 -> 46387 | H59: =H15 -> 46752 | I59: =I15 -> 47118 | J59: =J15 -> 47483 | K59: =K15 -> 47848
C60: ASSETS
C61: Current Assets
C62: Cash & equivalents, ST and LT marketable securities | E62: 102581 | F62: 289717 | G62: =F62+G129 -> 497415.36 | H62: =G62+H129 -> 574045.46 | I62: =H62+I129 -> 764702.1 | J62: =I62+J129 -> 992451.03 | K62: =J62+K129 -> 1332625.3
C63: Accounts receivable | E63: 580668 | F63: 654390 | G63: =F63*(1+G49) -> 751188.61 | H63: =G63*(1+H49) -> 848219.13 | I63: =H63*(1+I49) -> 949916.4 | J63: =I63*(1+J49) -> 1055652.2 | K63: =J63*(1+K49) -> 1168141.1
C64: Contract Assets | E64: 915200 | F64: 1071703 | G64: =F64*(1+G49) -> 1230231.3 | H64: =G64*(1+H49) -> 1389139.5 | I64: =H64*(1+I49) -> 1555690.4 | J64: =I64*(1+J49) -> 1728855.3 | K64: =J64*(1+K49) -> 1913079.8
C65: Inventories | E65: 847018 | F65: 827691 | G65: =F65*(1+((G20-F20)/F20)) -> 945700.6 | H65: =G65*(1+((H20-G20)/G20)) -> 1064078.3 | I65: =H65*(1+((I20-H20)/H20)) -> 1184604.8 | J65: =I65*(1+((J20-I20)/I20)) -> 1311762.2 | K65: =J65*(1+((K20-J20)/J20)) -> 1448073.5
C66: Other current assets | E66: 29707 | F66: 42776 | G66: =F66*(1+G49) -> 49103.507 | H66: =G66*(1+H49) -> 55446.174 | I66: =H66*(1+I49) -> 62093.895 | J66: =I66*(1+J49) -> 69005.604 | K66: =J66*(1+K49) -> 76358.751
C67: Income tax receivable | E67: 9960 | F67: 10182 | G67: =F67 -> 10182 | H67: =G67 -> 10182 | I67: =H67 -> 10182 | J67: =I67 -> 10182 | K67: =J67 -> 10182
C68: Total current assets | E68: =SUM(E62:E67) -> 2485134 | F68: =SUM(F62:F67) -> 2896459 | G68: =SUM(G62:G67) -> 3483821.4 | H68: =SUM(H62:H67) -> 3941110.6 | I68: =SUM(I62:I67) -> 4527189.6 | J68: =SUM(J62:J67) -> 5167908.3 | K68: =SUM(K62:K67) -> 5948460.4
C69: Property, plant & equipment | E69: 568607 | F69: 579971 | G69: =G138 -> 602929.44 | H69: =H138 -> 628853.4 | I69: =I138 -> 657885.52 | J69: =J138 -> 690149.22 | K69: =K138 -> 725850.9
C70: Operating lease right of use asset | E70: 172206 | F70: 222151 | G70: =F70 -> 222151 | H70: =G70 -> 222151 | I70: =H70 -> 222151 | J70: =I70 -> 222151 | K70: =J70 -> 222151
C71: Customer relationships | E71: 1004701 | F71: 920432 | G71: =F71 - G143*0.6425 + (-G119)*0.4 -> 842417.72 | H71: =G71 - H143*0.6425 + (-H119)*0.4 -> 801005.13 | I71: =H71 - I143*0.6425 + (-I119)*0.4 -> 760594.2 | J71: =I71 - J143*0.6425 + (-J119)*0.4 -> 732224.49 | K71: =J71 - K143*0.6425 + (-K119)*0.4 -> 704520.41 | M71: Formula: Prior year − amort (Note 9 × 64.2% CR share) + new CRs from M&A (Row 110 × 40% allocation).
C72: Other intangible assets | E72: 291487 | F72: 244877 | G72: =F72 - G143*0.3575 + (-G122) -> 228468.28 | H72: =G72 - H143*0.3575 + (-H122) -> 215732.87 | I72: =H72 - I143*0.3575 + (-I122) -> 203554.8 | J72: =I72 - J143*0.3575 + (-J122) -> 192512.51 | K72: =J72 - K143*0.3575 + (-K122) -> 181840.59 | M72: Formula: Prior year − amort (Note 9 × 35.8% Other share) + OEM license purchases (Row 113)
C73: Goodwill | E73: 1685970 | F73: 1684255 | G73: =F73 + (-G119)*0.6 -> 1684255 | H73: =G73 + (-H119)*0.6 -> 1729255 | I73: =H73 + (-I119)*0.6 -> 1774255 | J73: =I73 + (-J119)*0.6 -> 1834255 | K73: =J73 + (-K119)*0.6 -> 1894255 | M73: Formula: Prior year + M&A goodwill (Row 110 × 60% allocation). Per Aero Turbine: ~60% of purchase price allocated to goodwill, ~40% to customer relationships.
C74: Deferred income tax assets | E74: 1079 | F74: 2832 | G74: =F74 -> 2832 | H74: =G74 -> 2832 | I74: =H74 -> 2832 | J74: =I74 -> 2832 | K74: =J74 -> 2832
C75: Other non current assets | E75: 4417 | F75: 6434 | G75: =F75*(1+G49) -> 7385.7294 | H75: =G75*(1+H49) -> 8339.7391 | I75: =H75*(1+I49) -> 9339.6325 | J75: =I75*(1+J49) -> 10379.233 | K75: =J75*(1+K49) -> 11485.23
C76: Total assets | E76: =SUM(E68:E75) -> 6213601 | F76: =SUM(F68:F75) -> 6557411 | G76: =SUM(G68:G75) -> 7074260.6 | H76: =SUM(H68:H75) -> 7549279.7 | I76: =SUM(I68:I75) -> 8157801.8 | J76: =SUM(J68:J75) -> 8852411.8 | K76: =SUM(K68:K75) -> 9691395.5
C77: LIABILITIES AND STOCKHOLDERS' EQUITY
C78: Current Liabilities
C79: Accounts payable | E79: 645701 | F79: 679772 | G79: =F79*(1+(G20-F20)/F20) -> 776691.77 | H79: =G79*(1+(H20-G20)/G20) -> 873913.87 | I79: =H79*(1+(I20-H20)/H20) -> 972900.73 | J79: =I79*(1+(J20-I20)/I20) -> 1077333.5 | K79: =J79*(1+(K20-J20)/J20) -> 1189284.2
C80: Accrued expenses and other current liabilities | E80: 99572 | F80: 91499 | G80: =F80*(1+G49) -> 105033.71 | H80: =G80*(1+H49) -> 118600.84 | I80: =H80*(1+I49) -> 132820.49 | J80: =I80*(1+J49) -> 147604.82 | K80: =J80*(1+K49) -> 163333.4
C81: Accrued employ costs | E81: 79134 | F81: 74008 | G81: =F81*(1+G49) -> 84955.403 | H81: =G81*(1+H49) -> 95929.035 | I81: =H81*(1+I49) -> 107430.45 | J81: =I81*(1+J49) -> 119388.6 | K81: =J81*(1+K49) -> 132110.49
C82: Operating lease liabilities, current | E82: 17663 | F82: 22308 | G82: =F82 -> 22308 | H82: =G82 -> 22308 | I82: =H82 -> 22308 | J82: =I82 -> 22308 | K82: =J82 -> 22308
C83: Due to related parties | E83: 1345 | F83: 438 | G83: =F83 -> 438 | H83: =G83 -> 438 | I83: =H83 -> 438 | J83: =I83 -> 438 | K83: =J83 -> 438
C84: Contract liabilities | E84: 400025 | F84: 411321 | G84: =F84*(1+G49) -> 472164.38 | H84: =G84*(1+H49) -> 533153.53 | I84: =H84*(1+I49) -> 597076 | J84: =I84*(1+J49) -> 663536.89 | K84: =J84*(1+K49) -> 734242.52
C85: Income taxes payable, current | E85: 6655 | F85: 13547 | G85: =F85 -> 13547 | H85: =G85 -> 13547 | I85: =H85 -> 13547 | J85: =I85 -> 13547 | K85: =J85 -> 13547
C86: Long-term debt, current portion | E86: 23449 | F86: 23444 | G86: =F86 -> 23444 | H86: =G86 -> 23444 | I86: =H86 -> 23444 | J86: =I86 -> 23444 | K86: =J86 -> 23444
C87: Total current liabilities | E87: =SUM(E79:E86) -> 1273544 | F87: =SUM(F79:F86) -> 1316337 | G87: =SUM(G79:G86) -> 1498582.3 | H87: =SUM(H79:H86) -> 1681334.3 | I87: =SUM(I79:I86) -> 1869964.7 | J87: =SUM(J79:J86) -> 2067600.8 | K87: =SUM(K79:K86) -> 2278707.6
C88: Long term debt | E88: 2207977 | F88: 2191161 | G88: =F88-F86+G168+G128 -> 2167717 | H88: =G88-G86+H168-G168+H128 -> 2044273 | I88: =H88-H86+I168-H168+I128 -> 1920829 | J88: =I88-I86+J168-I168+J128 -> 1747385 | K88: =J88-J86+K168-J168+K128 -> 1573941
C89: Operating Lease Liabilities Non Current | E89: 164224 | F89: 212365 | G89: =F89 -> 212365 | H89: =G89 -> 212365 | I89: =H89 -> 212365 | J89: =I89 -> 212365 | K89: =J89 -> 212365
C90: Deferred income tax liabilities | E90: 169824 | F90: 157206 | G90: =F90 -> 157206 | H90: =G90 -> 157206 | I90: =H90 -> 157206 | J90: =I90 -> 157206 | K90: =J90 -> 157206
C91: Income tax payable, non-current | E91: 0 | F91: 5770 | G91: =F91 -> 5770 | H91: =G91 -> 5770 | I91: =H91 -> 5770 | J91: =I91 -> 5770 | K91: =J91 -> 5770
C92: Other non current liabilities | E92: 24628 | F92: 7261 | G92: =F92*(1+G49) -> 8335.0609 | H92: =G92*(1+H49) -> 9411.695 | I92: =H92*(1+I49) -> 10540.111 | J92: =I92*(1+J49) -> 11713.337 | K92: =J92*(1+K49) -> 12961.495
C93: Total liabilities | E93: =SUM(E87:E92) -> 3840197 | F93: =SUM(F87:F92) -> 3890100 | G93: =SUM(G87:G92) -> 4049975.3 | H93: =SUM(H87:H92) -> 4110360 | I93: =SUM(I87:I92) -> 4176674.8 | J93: =SUM(J87:J92) -> 4202040.1 | K93: =SUM(K87:K92) -> 4240951.1
C94: Commitments and contingencies | E94: 0 | F94: 0 | G94: 0 | H94: 0 | I94: 0 | J94: 0 | K94: 0
C95: Stockholders Equity:
C96: Common stock | E96: 3345 | F96: 3345 | G96: =F96 -> 3345 | H96: =G96 -> 3345 | I96: =H96 -> 3345 | J96: =I96 -> 3345 | K96: =J96 -> 3345
C97: Preferred stock | E97: 0 | F97: 0 | G97: 0 | H97: 0 | I97: 0 | J97: 0 | K97: 0
C98: Adittional paid-in capital | E98: 3944802 | F98: 3958039 | G98: =F98+G37 -> 3958039 | H98: =G98+H37 -> 3958039 | I98: =H98+I37 -> 3958039 | J98: =I98+J37 -> 3958039 | K98: =J98+K37 -> 3958039
C99: Accumulated deficit | E99: -1563321 | F99: -1285904 | G99: =F99+G33 -> -878929.75 | H99: =G99+H33 -> -364295.27 | I99: =H99+I33 -> 277911.99 | J99: =I99+J33 -> 1047156.6 | K99: =J99+K33 -> 1947229.5
C100: Accumulated other comprehensive loss | E100: -11422 | F100: -8169 | G100: =F100 -> -8169 | H100: =G100 -> -8169 | I100: =H100 -> -8169 | J100: =I100 -> -8169 | K100: =J100 -> -8169
C101: Treasury stock | E101: 0 | F101: 0 | G101: =F101+G125 -> -50000 | H101: =G101+H125 -> -150000 | I101: =H101+I125 -> -250000 | J101: =I101+J125 -> -350000 | K101: =J101+K125 -> -450000
C102: Total equity | E102: =SUM(E96:E101) -> 2373404 | F102: =SUM(F96:F101) -> 2667311 | G102: =SUM(G96:G101) -> 3024285.3 | H102: =SUM(H96:H101) -> 3438919.7 | I102: =SUM(I96:I101) -> 3981127 | J102: =SUM(J96:J101) -> 4650371.6 | K102: =SUM(K96:K101) -> 5450444.5
C103: Total liabilities and stockholders' equity | E103: =SUM(E102,E93) -> 6213601 | F103: =SUM(F102,F93) -> 6557411 | G103: =SUM(G102,G93) -> 7074260.6 | H103: =SUM(H102,H93) -> 7549279.7 | I103: =SUM(I102,I93) -> 8157801.8 | J103: =SUM(J102,J93) -> 8852411.8 | K103: =SUM(K102,K93) -> 9691395.5
C105: Balance check | E105: =E76-E103 -> 0 | F105: =F76-F103 -> 0 | G105: =G76-G103 -> 0 | H105: =H76-H103 -> 0 | I105: =I76-I103 -> 0 | J105: =J76-J103 -> 0 | K105: =K76-K103 -> 0
B107: X | C107: CASH FLOW STATEMENT
C108: =C14 -> Fiscal year | G108: =G14 -> 2026 | H108: =H14 -> 2027 | I108: =I14 -> 2028 | J108: =J14 -> 2029 | K108: =K14 -> 2030
C109: =C15 -> Fiscal year end date | G109: =G15 -> 46387 | H109: =H15 -> 46752 | I109: =I15 -> 47118 | J109: =J15 -> 47483 | K109: =K15 -> 47848
...

Sheet Backup
B2: X | C2: ="Financial Statement Model for "&D5 -> Financial Statement Model for StandardAero
C3: $ in thousands except per share
C5: Company name | D5: StandardAero
C6: Ticker | D6: SARO
D7: 1
C8: Latest closing share price | D8: 25.59
C9: Latest closing share price date | D9: 46119
C10: Latest fiscal year end date | D10: 46022
C11: Shares outstanding (millions) | D11: 334294 | M11: Outstanding at Dec 31, 2025 per 10-K BS. Jan 2026 repurchase of 1,637k shares (subsequent event) reduces to 332,657k.
B13: X | C13: INCOME STATEMENT
C14: Fiscal year | D14: =E14-1 -> 2023 | E14: =F14-1 -> 2024 | F14: =YEAR(D10) -> 2025 | G14: =F14+1 -> 2026 | H14: =G14+1 -> 2027 | I14: =H14+1 -> 2028 | J14: =I14+1 -> 2029 | K14: =J14+1 -> 2030
C15: Fiscal year end date | D15: =EOMONTH(E15,-12) -> 45291 | E15: =EOMONTH(F15,-12) -> 45657 | F15: =D10 -> 46022 | G15: =EOMONTH(F15,12) -> 46387 | H15: =EOMONTH(G15,12) -> 46752 | I15: =EOMONTH(H15,12) -> 47118 | J15: =EOMONTH(I15,12) -> 47483 | K15: =EOMONTH(J15,12) -> 47848 | M15: Comments
C17: Revenue from Engine Repair | D17: 4049868 | E17: 4644739 | F17: 5353952 | G17: =F17*(1+G42) -> 6130275 | H17: =G17*(1+H42) -> 6896559.4 | I17: =H17*(1+I42) -> 7689663.8 | J17: =I17*(1+J42) -> 8497078.4 | K17: =J17*(1+K42) -> 9346786.3
C18: Revenue from Component Repair | D18: 513416 | E18: 592422 | F18: 708560 | G18: =F18*(1+G43) -> 829015.2 | H18: =G18*(1+H43) -> 961657.63 | I18: =H18*(1+I43) -> 1110714.6 | J18: =I18*(1+J43) -> 1282875.3 | K18: =J18*(1+K43) -> 1475306.6
C19: Total Revenue | D19: =D18+D17 -> 4563284 | E19: =E18+E17 -> 5237161 | F19: =F18+F17 -> 6062512 | G19: =G18+G17 -> 6959290.2 | H19: =H18+H17 -> 7858217.1 | I19: =I18+I17 -> 8800378.3 | J19: =J18+J17 -> 9779953.8 | K19: =K18+K17 -> 10822093
C20: Cost of sales | D20: -3927965 | E20: -4483019 | F20: -5165060 | G20: =G21-G19 -> -5901478.1 | H20: =H21-H19 -> -6640193.4 | I20: =I21-I19 -> -7392317.8 | J20: =J21-J19 -> -8185821.3 | K20: =K21-K19 -> -9036447.6
C21: Gross Profit | D21: =SUM(D19:D20) -> 635319 | E21: =SUM(E19:E20) -> 754142 | F21: =SUM(F19:F20) -> 897452 | G21: =G19*G44 -> 1057812.1 | H21: =H19*H44 -> 1218023.6 | I21: =I19*I44 -> 1408060.5 | J21: =J19*J44 -> 1594132.5 | K21: =K19*K44 -> 1785645.3
C22: Amortisation of intangible assets | D22: -93681 | E22: -95457 | F22: -98681 | G22: -91258 | H22: -84535 | I22: -85364 | J22: -84976 | K22: -87197 | M22: IS-line amort only (excl OEM auth amort in COGS). Total amort per Note 9 used for BS reduction in rows 62/63
C23: Selling, general & administrative | D23: -202766 | E23: -254092 | F23: -247703 | G23: =-G19*G45 -> -285330.9 | H23: =-H19*H45 -> -314328.68 | I23: =-I19*I45 -> -343214.75 | J23: =-J19*J45 -> -371638.24 | K23: =-K19*K45 -> -400417.44
C24: Acquisition Cost | D24: -1514 | E24: -1374 | F24: 0 | G24: =F24 -> 0 | H24: =G24 -> 0 | I24: =H24 -> 0 | J24: =I24 -> 0 | K24: =J24 -> 0
C25: Operating profit (EBIT) | D25: =SUM(D21:D24) -> 337358 | E25: =SUM(E21:E24) -> 403219 | F25: =SUM(F21:F24) -> 551068 | G25: =SUM(G21:G24) -> 681223.22 | H25: =SUM(H21:H24) -> 819159.96 | I25: =SUM(I21:I24) -> 979481.78 | J25: =SUM(J21:J24) -> 1137518.2 | K25: =SUM(K21:K24) -> 1298030.9
C26: Interest income | D26: 0 | E26: 0 | F26: 0 | G26: =G180 -> 0 | H26: =H180 -> 0 | I26: =I180 -> 0 | J26: =J180 -> 0 | K26: =K180 -> 0
C27: Interest expense | D27: -309645 | E27: -282507 | F27: -174217 | G27: =G166 -> -138781.63 | H27: =H166 -> -134154.66 | I27: =I166 -> -126377.68 | J27: =J166 -> -117025.71 | K27: =K166 -> -106098.74
C28: Refinancing costs | D28: -19921 | E28: -23700 | F28: 0 | G28: =F28 -> 0 | H28: =G28 -> 0 | I28: =H28 -> 0 | J28: =I28 -> 0 | K28: =J28 -> 0
C29: Loss on debt extinguishment | D29: -6182 | E29: -15255 | F29: 0 | G29: =F29 -> 0 | H29: =G29 -> 0 | I29: =H29 -> 0 | J29: =I29 -> 0 | K29: =J29 -> 0
C30: Other expense, net | D30: 3509 | E30: 0 | F30: 0 | G30: 0 | H30: 0 | I30: 0 | J30: 0 | K30: 0
C31: Pretax profit | D31: =SUM(D25:D30) -> 5119 | E31: =SUM(E25:E30) -> 81757 | F31: =SUM(F25:F30) -> 376851 | G31: =SUM(G25:G30) -> 542441.59 | H31: =SUM(H25:H30) -> 685005.3 | I31: =SUM(I25:I30) -> 853104.09 | J31: =SUM(J25:J30) -> 1020492.5 | K31: =SUM(K25:K30) -> 1191932.2
C32: Taxes | D32: -40180 | E32: -70783 | F32: -99435 | G32: =-G31*G46 -> -135610.4 | H32: =-H31*H46 -> -171251.33 | I32: =-I31*I46 -> -213276.02 | J32: =-J31*J46 -> -255123.13 | K32: =-K31*K46 -> -297983.04
C33: Net income | D33: =SUM(D31:D32) -> -35061 | E33: =SUM(E31:E32) -> 10974 | F33: =SUM(F31:F32) -> 277416 | G33: =SUM(G31:G32) -> 406831.19 | H33: =SUM(H31:H32) -> 513753.98 | I33: =SUM(I31:I32) -> 639828.07 | J33: =SUM(J31:J32) -> 765369.38 | K33: =SUM(K31:K32) -> 893949.11
C35: Depreciation & amortization | D35: 197104 | E35: 188164 | F35: 193664 | G35: =G136 -> 193053.33 | H35: =H136 -> 194030.77 | I35: =I136 -> 204169.21 | J35: =J136 -> 214074.75 | K35: =K136 -> 227765.24
C36: EBITDA | D36: =D25+D35 -> 534462 | E36: =E25+E35 -> 591383 | F36: =F25+F35 -> 744732 | G36: =G25+G35 -> 874276.54 | H36: =H25+H35 -> 1013190.7 | I36: =I25+I35 -> 1183651 | J36: =J25+J35 -> 1351593 | K36: =K25+K35 -> 1525796.1
C37: Stock based compensation | D37: 0 | E37: 17376 | F37: 13237 | G37: =F37 -> 13237 | H37: =G37 -> 13237 | I37: =H37 -> 13237 | J37: =I37 -> 13237 | K37: =J37 -> 13237
C40: Growth rates & margins
C41: Revenue growth | E41: =(E19-D19)/D19 -> 0.14767369 | F41: =(F19-E19)/E19 -> 0.15759512 | G41: =(G19-F19)/F19 -> 0.14792189 | H41: =(H19-G19)/G19 -> 0.12916932 | I41: =(I19-H19)/H19 -> 0.11989504 | J41: =(J19-I19)/I19 -> 0.11131061 | K41: =(K19-J19)/J19 -> 0.1065587 | M41: LEAP/CFM56 shop visits ramping; ~80% of revenue under long-term agreements; aging installed base drives MRO demand through 2030; military spending elevated due to geopolitical tensions; business aviation fleet growth
C42: Engine Service growth rate | E42: =(E17-D17)/D17 -> 0.14688652 | F42: =(F17-E17)/E17 -> 0.15269168 | G42: 0.145 | H42: 0.125 | I42: 0.115 | J42: 0.105 | K42: 0.1
C43: Component Repair Service growth rate | E43: =(E18-D18)/D18 -> 0.15388301 | F43: =(F18-E18)/E18 -> 0.19603931 | G43: 0.17 | H43: 0.16 | I43: 0.155 | J43: 0.155 | K43: 0.15
C44: Gross profit margin | D44: =D21/D19 -> 0.13922408 | E44: =E21/E19 -> 0.14399825 | F44: =F21/F19 -> 0.14803303 | G44: 0.152 | H44: 0.155 | I44: 0.16 | J44: 0.163 | K44: 0.165 | M44: LEAP learning curve progressively reduces industrialization costs; mix shift toward higher-margin Component Repair Services; operating leverage on fixed overhead as volumes scale; partially offset by material cost inflation pass-through
C45: SG&A % of sales | D45: =-D23/D19 -> 0.044434228 | E45: =-E23/E19 -> 0.048517126 | F45: =-F23/F19 -> 0.040858146 | G45: 0.041 | H45: 0.04 | I45: 0.039 | J45: 0.038 | K45: 0.037 | M45: SG&A already declined to 4.1% in 2025 (from 4.9% in 2024). Post-IPO one-time costs are behind the company. Further leverage expected as revenue scales against relatively fixed corporate overhead and sales force
C46: Tax rate | D46: =-D32/D31 -> 7.8491893 | E46: =-E32/E31 -> 0.86577296 | F46: =-F32/F31 -> 0.2638576 | G46: 0.25 | H46: 0.25 | I46: 0.25 | J46: 0.25 | K46: 0.25 | M46: 2025 effective rate of 26.4% includes GILTI, state taxes (California heavy), and changes in uncertain tax benefits. OBBBA provisions (signed Jul 4, 2025) restore favorable business tax treatment in 2026–2027 rate likely drifts toward 24–26% as Canada/foreign mix optimizes and interest carryforwards begin to release
B48: X | C48: BALANCE SHEET
C49: =C14 -> Fiscal year | D49: =D14 -> 2023 | E49: =E14 -> 2024 | F49: =F14 -> 2025 | G49: =G14 -> 2026 | H49: =H14 -> 2027 | I49: =I14 -> 2028 | J49: =J14 -> 2029 | K49: =K14 -> 2030
C50: =C15 -> Fiscal year end date | D50: =D15 -> 45291 | E50: =E15 -> 45657 | F50: =F15 -> 46022 | G50: =G15 -> 46387 | H50: =H15 -> 46752 | I50: =I15 -> 47118 | J50: =J15 -> 47483 | K50: =K15 -> 47848
C51: ASSETS
C52: Current Assets
C53: Cash & equivalents, ST and LT marketable securities | E53: 102581 | F53: 289717 | G53: =F53+G120 -> 510509.3 | H53: =G53+H120 -> 601495.9 | I53: =H53+I120 -> 807010.35 | J53: =I53+J120 -> 1051121 | K53: =J53+K120 -> 1409408.5
C54: Accounts receivable | E54: 580668 | F54: 654390 | G54: =F54*(1+G41) -> 751188.61 | H54: =G54*(1+H41) -> 848219.13 | I54: =H54*(1+I41) -> 949916.4 | J54: =I54*(1+J41) -> 1055652.2 | K54: =J54*(1+K41) -> 1168141.1
C55: Contract Assets | E55: 915200 | F55: 1071703 | G55: =F55*(1+G41) -> 1230231.3 | H55: =G55*(1+H41) -> 1389139.5 | I55: =H55*(1+I41) -> 1555690.4 | J55: =I55*(1+J41) -> 1728855.3 | K55: =J55*(1+K41) -> 1913079.8
C56: Inventories | E56: 847018 | F56: 827691 | G56: =F56*(1+((G20-F20)/F20)) -> 945700.6 | H56: =G56*(1+((H20-G20)/G20)) -> 1064078.3 | I56: =H56*(1+((I20-H20)/H20)) -> 1184604.8 | J56: =I56*(1+((J20-I20)/I20)) -> 1311762.2 | K56: =J56*(1+((K20-J20)/J20)) -> 1448073.5
C57: Other current assets | E57: 29707 | F57: 42776 | G57: =F57*(1+G41) -> 49103.507 | H57: =G57*(1+H41) -> 55446.174 | I57: =H57*(1+I41) -> 62093.895 | J57: =I57*(1+J41) -> 69005.604 | K57: =J57*(1+K41) -> 76358.751
C58: Income tax receivable | E58: 9960 | F58: 10182 | G58: =F58 -> 10182 | H58: =G58 -> 10182 | I58: =H58 -> 10182 | J58: =I58 -> 10182 | K58: =J58 -> 10182
C59: Total current assets | E59: =SUM(E53:E58) -> 2485134 | F59: =SUM(F53:F58) -> 2896459 | G59: =SUM(G53:G58) -> 3496915.3 | H59: =SUM(H53:H58) -> 3968561 | I59: =SUM(I53:I58) -> 4569497.9 | J59: =SUM(J53:J58) -> 5226578.3 | K59: =SUM(K53:K58) -> 6025243.7
C60: Property, plant & equipment | E60: 568607 | F60: 579971 | G60: =G129 -> 602929.44 | H60: =H129 -> 628853.4 | I60: =I129 -> 657885.52 | J60: =J129 -> 690149.22 | K60: =K129 -> 725850.9
C61: Operating lease right of use asset | E61: 172206 | F61: 222151 | G61: =F61 -> 222151 | H61: =G61 -> 222151 | I61: =H61 -> 222151 | J61: =I61 -> 222151 | K61: =J61 -> 222151
C62: Customer relationships | E62: 1004701 | F62: 920432 | G62: =F62+-77930 -> 842502 | H62: =G62+-42617 -> 799885 | I62: =H62+-42900 -> 756985 | J62: =I62+-32786 -> 724199 | K62: =J62+-34690 -> 689509
C63: Other intangible assets | E63: 291487 | F63: 244877 | G63: =F63+-16493 -> 228384 | H63: =G63+-13531 -> 214853 | I63: =H63+-13689 -> 201164 | J63: =I63+-13626 -> 187538 | K63: =J63+-14686 -> 172852
C64: Goodwill | E64: 1685970 | F64: 1684255 | G64: =F64 -> 1684255 | H64: =G64+45000 -> 1729255 | I64: =H64+45000 -> 1774255 | J64: =I64+60000 -> 1834255 | K64: =J64+60000 -> 1894255 | M64: Goodwill from bolt-on M&A: ~50% of purchase price per historical allocation
C65: Deferred income tax assets | E65: 1079 | F65: 2832 | G65: =F65 -> 2832 | H65: =G65 -> 2832 | I65: =H65 -> 2832 | J65: =I65 -> 2832 | K65: =J65 -> 2832
C66: Other non current assets | E66: 4417 | F66: 6434 | G66: =F66*(1+G41) -> 7385.7294 | H66: =G66*(1+H41) -> 8339.7391 | I66: =H66*(1+I41) -> 9339.6325 | J66: =I66*(1+J41) -> 10379.233 | K66: =J66*(1+K41) -> 11485.23
C67: Total assets | E67: =SUM(E59:E66) -> 6213601 | F67: =SUM(F59:F66) -> 6557411 | G67: =SUM(G59:G66) -> 7087354.5 | H67: =SUM(H59:H66) -> 7574730.1 | I67: =SUM(I59:I66) -> 8194110 | J67: =SUM(J59:J66) -> 8898081.8 | K67: =SUM(K59:K66) -> 9744178.8
C68: LIABILITIES AND STOCKHOLDERS' EQUITY
C69: Current Liabilities
C70: Accounts payable | E70: 645701 | F70: 679772 | G70: =F70*(1+(G20-F20)/F20) -> 776691.77 | H70: =G70*(1+(H20-G20)/G20) -> 873913.87 | I70: =H70*(1+(I20-H20)/H20) -> 972900.73 | J70: =I70*(1+(J20-I20)/I20) -> 1077333.5 | K70: =J70*(1+(K20-J20)/J20) -> 1189284.2
C71: Accrued expenses and other current liabilities | E71: 99572 | F71: 91499 | G71: =F71*(1+G41) -> 105033.71 | H71: =G71*(1+H41) -> 118600.84 | I71: =H71*(1+I41) -> 132820.49 | J71: =I71*(1+J41) -> 147604.82 | K71: =J71*(1+K41) -> 163333.4
C72: Accrued employ costs | E72: 79134 | F72: 74008 | G72: =F72*(1+G41) -> 84955.403 | H72: =G72*(1+H41) -> 95929.035 | I72: =H72*(1+I41) -> 107430.45 | J72: =I72*(1+J41) -> 119388.6 | K72: =J72*(1+K41) -> 132110.49
C73: Operating lease liabilities, current | E73: 17663 | F73: 22308 | G73: =F73 -> 22308 | H73: =G73 -> 22308 | I73: =H73 -> 22308 | J73: =I73 -> 22308 | K73: =J73 -> 22308
C74: Due to related parties | E74: 1345 | F74: 438 | G74: =F74 -> 438 | H74: =G74 -> 438 | I74: =H74 -> 438 | J74: =I74 -> 438 | K74: =J74 -> 438
C75: Contract liabilities | E75: 400025 | F75: 411321 | G75: =F75*(1+G41) -> 472164.38 | H75: =G75*(1+H41) -> 533153.53 | I75: =H75*(1+I41) -> 597076 | J75: =I75*(1+J41) -> 663536.89 | K75: =J75*(1+K41) -> 734242.52
C76: Income taxes payable, current | E76: 6655 | F76: 13547 | G76: =F76 -> 13547 | H76: =G76 -> 13547 | I76: =H76 -> 13547 | J76: =I76 -> 13547 | K76: =J76 -> 13547
C77: Long-term debt, current portion | E77: 23449 | F77: 23444 | G77: =F77 -> 23444 | H77: =G77 -> 23444 | I77: =H77 -> 23444 | J77: =I77 -> 23444 | K77: =J77 -> 23444
C78: Total current liabilities | E78: =SUM(E70:E77) -> 1273544 | F78: =SUM(F70:F77) -> 1316337 | G78: =SUM(G70:G77) -> 1498582.3 | H78: =SUM(H70:H77) -> 1681334.3 | I78: =SUM(I70:I77) -> 1869964.7 | J78: =SUM(J70:J77) -> 2067600.8 | K78: =SUM(K70:K77) -> 2278707.6
C79: Long term debt | E79: 2207977 | F79: 2191161 | G79: =F79-F77+G159+G119 -> 2167717 | H79: =G79-G77+H159-G159+H119 -> 2044273 | I79: =H79-H77+I159-H159+I119 -> 1920829 | J79: =I79-I77+J159-I159+J119 -> 1747385 | K79: =J79-J77+K159-J159+K119 -> 1573941
C80: Operating Lease Liabilities Non Current | E80: 164224 | F80: 212365 | G80: =F80 -> 212365 | H80: =G80 -> 212365 | I80: =H80 -> 212365 | J80: =I80 -> 212365 | K80: =J80 -> 212365
C81: Deferred income tax liabilities | E81: 169824 | F81: 157206 | G81: =F81 -> 157206 | H81: =G81 -> 157206 | I81: =H81 -> 157206 | J81: =I81 -> 157206 | K81: =J81 -> 157206
C82: Income tax payable, non-current | E82: 0 | F82: 5770 | G82: =F82 -> 5770 | H82: =G82 -> 5770 | I82: =H82 -> 5770 | J82: =I82 -> 5770 | K82: =J82 -> 5770
C83: Other non current liabilities | E83: 24628 | F83: 7261 | G83: =F83*(1+G41) -> 8335.0609 | H83: =G83*(1+H41) -> 9411.695 | I83: =H83*(1+I41) -> 10540.111 | J83: =I83*(1+J41) -> 11713.337 | K83: =J83*(1+K41) -> 12961.495
C84: Total liabilities | E84: =SUM(E78:E83) -> 3840197 | F84: =SUM(F78:F83) -> 3890100 | G84: =SUM(G78:G83) -> 4049975.3 | H84: =SUM(H78:H83) -> 4110360 | I84: =SUM(I78:I83) -> 4176674.8 | J84: =SUM(J78:J83) -> 4202040.1 | K84: =SUM(K78:K83) -> 4240951.1
C85: Commitments and contingencies | E85: 0 | F85: 0 | G85: 0 | H85: 0 | I85: 0 | J85: 0 | K85: 0
C86: Stockholders Equity:
C87: Common stock | E87: 3345 | F87: 3345 | G87: =F87 -> 3345 | H87: =G87 -> 3345 | I87: =H87 -> 3345 | J87: =I87 -> 3345 | K87: =J87 -> 3345
C88: Preferred stock | E88: 0 | F88: 0 | G88: 0 | H88: 0 | I88: 0 | J88: 0 | K88: 0
C89: Adittional paid-in capital | E89: 3944802 | F89: 3958039 | G89: =F89+G37 -> 3971276 | H89: =G89+H37 -> 3984513 | I89: =H89+I37 -> 3997750 | J89: =I89+J37 -> 4010987 | K89: =J89+K37 -> 4024224
C90: Accumulated deficit | E90: -1563321 | F90: -1285904 | G90: =F90+G33 -> -879072.81 | H90: =G90+H33 -> -365318.83 | I90: =H90+I33 -> 274509.24 | J90: =I90+J33 -> 1039878.6 | K90: =J90+K33 -> 1933827.7
C91: Accumulated other comprehensive loss | E91: -11422 | F91: -8169 | G91: =F91 -> -8169 | H91: =G91 -> -8169 | I91: =H91 -> -8169 | J91: =I91 -> -8169 | K91: =J91 -> -8169
C92: Treasury stock | E92: 0 | F92: 0 | G92: =F92+G116 -> -50000 | H92: =G92+H116 -> -150000 | I92: =H92+I116 -> -250000 | J92: =I92+J116 -> -350000 | K92: =J92+K116 -> -450000
C93: Total equity | E93: =SUM(E87:E92) -> 2373404 | F93: =SUM(F87:F92) -> 2667311 | G93: =SUM(G87:G92) -> 3037379.2 | H93: =SUM(H87:H92) -> 3464370.2 | I93: =SUM(I87:I92) -> 4017435.2 | J93: =SUM(J87:J92) -> 4696041.6 | K93: =SUM(K87:K92) -> 5503227.7
C94: Total liabilities and stockholders' equity | E94: =SUM(E93,E84) -> 6213601 | F94: =SUM(F93,F84) -> 6557411 | G94: =SUM(G93,G84) -> 7087354.5 | H94: =SUM(H93,H84) -> 7574730.1 | I94: =SUM(I93,I84) -> 8194110 | J94: =SUM(J93,J84) -> 8898081.8 | K94: =SUM(K93,K84) -> 9744178.8
C96: Balance check | E96: =E67-E94 -> 0 | F96: =F67-F94 -> 0 | G96: =G67-G94 -> 0 | H96: =H67-H94 -> 0 | I96: =I67-I94 -> 0 | J96: =J67-J94 -> 0 | K96: =K67-K94 -> 0
B98: X | C98: CASH FLOW STATEMENT
C99: =C14 -> Fiscal year | G99: =G14 -> 2026 | H99: =H14 -> 2027 | I99: =I14 -> 2028 | J99: =J14 -> 2029 | K99: =K14 -> 2030
C100: =C15 -> Fiscal year end date | G100: =G15 -> 46387 | H100: =H15 -> 46752 | I100: =I15 -> 47118 | J100: =J15 -> 47483 | K100: =K15 -> 47848
C102: Net income | G102: =G33 -> 406831.19 | H102: =H33 -> 513753.98 | I102: =I33 -> 639828.07 | J102: =J33 -> 765369.38 | K102: =K33 -> 893949.11
C103: Depreciation and amortization | G103: =G35 -> 193053.33 | H103: =H35 -> 194030.77 | I103: =I35 -> 204169.21 | J103: =J35 -> 214074.75 | K103: =K35 -> 227765.24
C104: Stock based compensation | G104: =G37 -> 13237 | H104: =H37 -> 13237 | I104: =I37 -> 13237 | J104: =J37 -> 13237 | K104: =K37 -> 13237
C105: Decreases / (Increases) in working capital assets | G105: =F54+F55+F56+F57-G54-G55-G56-G57 -> -379664.05 | H105: =G54+G55+G56+G57-H54-H55-H56-H57 -> -380659.05 | I105: =H54+H55+H56+H57-I54-I55-I56-I57 -> -395422.42 | J105: =I54+I55+I56+I57-J54-J55-J56-J57 -> -412969.75 | K105: =J54+J55+J56+J57-K54-K55-K56-K57 -> -440377.87
C106: Increases / (Decreases) in working capital liabilities | G106: =G70+G71+G72+G75-F70-F71-F72-F75 -> 182245.26 | H106: =H70+H71+H72+H75-G70-G71-G72-G75 -> 182752.02 | I106: =I70+I71+I72+I75-H70-H71-H72-H75 -> 188630.4 | J106: =J70+J71+J72+J75-I70-I71-I72-I75 -> 197636.13 | K106: =K70+K71+K72+K75-J70-J71-J72-J75 -> 211106.77
C107: Other non current assets | G107: =-G66+F66 -> -951.72945 | H107: =-H66+G66 -> -954.00968 | I107: =-I66+H66 -> -999.89338 | J107: =-J66+I66 -> -1039.6002 | K107: =-K66+J66 -> -1105.9975
C108: Other non current liabilities | G108: =G83-F83 -> 1074.0609 | H108: =H83-G83 -> 1076.6342 | I108: =I83-H83 -> 1128.4156 | J108: =J83-I83 -> 1173.2261 | K108: =K83-J83 -> 1248.1579
C109: Cash from operating activities | G109: =SUM(G102:G108) -> 415825.06 | H109: =SUM(H102:H108) -> 523237.33 | I109: =SUM(I102:I108) -> 650570.78 | J109: =SUM(J102:J108) -> 777481.14 | K109: =SUM(K102:K108) -> 905822.41
C110: Acquisitions, net of cash | G110: 0 | H110: -75000 | I110: -75000 | J110: -100000 | K110: -100000 | M110: Normalized bolt-on M&A based on Western Jet ($33M) and Aero Turbine ($132M) historical cadence; 10-K states company "continually acquiring and investing"
C111: Capital expenditures | G111: =-G127 -> -94588.764 | H111: =-H127 -> -106806.73 | I111: =-I127 -> -119612.33 | J111: =-J127 -> -132926.45 | K111: =-K127 -> -147090.92
...

Sheet vFixed
B2: X | C2: ="Financial Statement Model for "&D5 -> Financial Statement Model for StandardAero
C3: $ in thousands except per share
C5: Company name | D5: StandardAero
C6: Ticker | D6: SARO
D7: 1
C8: Latest closing share price | D8: 25.59
C9: Latest closing share price date | D9: 46119
C10: Latest fiscal year end date | D10: 46022
C11: Shares outstanding (millions) | D11: 334294 | M11: Outstanding at Dec 31, 2025 per 10-K BS. Jan 2026 repurchase of 1,637k shares (subsequent event) reduces to 332,657k.
B13: X | C13: INCOME STATEMENT
C14: Fiscal year | D14: =E14-1 -> 2023 | E14: =F14-1 -> 2024 | F14: =YEAR(D10) -> 2025 | G14: =F14+1 -> 2026 | H14: =G14+1 -> 2027 | I14: =H14+1 -> 2028 | J14: =I14+1 -> 2029 | K14: =J14+1 -> 2030
C15: Fiscal year end date | D15: =EOMONTH(E15,-12) -> 45291 | E15: =EOMONTH(F15,-12) -> 45657 | F15: =D10 -> 46022 | G15: =EOMONTH(F15,12) -> 46387 | H15: =EOMONTH(G15,12) -> 46752 | I15: =EOMONTH(H15,12) -> 47118 | J15: =EOMONTH(I15,12) -> 47483 | K15: =EOMONTH(J15,12) -> 47848 | M15: Comments
C17: Revenue from Engine Repair | D17: 4049868 | E17: 4644739 | F17: 5353952 | G17: =F17*(1+G42) -> 6130275 | H17: =G17*(1+H42) -> 6896559.4 | I17: =H17*(1+I42) -> 7689663.8 | J17: =I17*(1+J42) -> 8497078.4 | K17: =J17*(1+K42) -> 9346786.3
C18: Revenue from Component Repair | D18: 513416 | E18: 592422 | F18: 708560 | G18: =F18*(1+G43) -> 829015.2 | H18: =G18*(1+H43) -> 961657.63 | I18: =H18*(1+I43) -> 1110714.6 | J18: =I18*(1+J43) -> 1282875.3 | K18: =J18*(1+K43) -> 1475306.6
C19: Total Revenue | D19: =D18+D17 -> 4563284 | E19: =E18+E17 -> 5237161 | F19: =F18+F17 -> 6062512 | G19: =G18+G17 -> 6959290.2 | H19: =H18+H17 -> 7858217.1 | I19: =I18+I17 -> 8800378.3 | J19: =J18+J17 -> 9779953.8 | K19: =K18+K17 -> 10822093
C20: Cost of sales | D20: -3927965 | E20: -4483019 | F20: -5165060 | G20: =G21-G19 -> -5901478.1 | H20: =H21-H19 -> -6640193.4 | I20: =I21-I19 -> -7392317.8 | J20: =J21-J19 -> -8185821.3 | K20: =K21-K19 -> -9036447.6
C21: Gross Profit | D21: =SUM(D19:D20) -> 635319 | E21: =SUM(E19:E20) -> 754142 | F21: =SUM(F19:F20) -> 897452 | G21: =G19*G44 -> 1057812.1 | H21: =H19*H44 -> 1218023.6 | I21: =I19*I44 -> 1408060.5 | J21: =J19*J44 -> 1594132.5 | K21: =K19*K44 -> 1785645.3
C22: Amortisation of intangible assets | D22: -93681 | E22: -95457 | F22: -98681 | G22: -91258 | H22: -84535 | I22: -85364 | J22: -84976 | K22: -87197 | M22: IS-line amort only (excl OEM auth amort in COGS). Total amort per Note 9 used for BS reduction in rows 58/59.
C23: Selling, general & administrative | D23: -202766 | E23: -254092 | F23: -247703 | G23: =-G19*G45 -> -285330.9 | H23: =-H19*H45 -> -314328.68 | I23: =-I19*I45 -> -343214.75 | J23: =-J19*J45 -> -371638.24 | K23: =-K19*K45 -> -400417.44
C24: Acquisition Cost | D24: -1514 | E24: -1374 | F24: 0 | G24: =F24 -> 0 | H24: =G24 -> 0 | I24: =H24 -> 0 | J24: =I24 -> 0 | K24: =J24 -> 0
C25: Operating profit (EBIT) | D25: =SUM(D21:D24) -> 337358 | E25: =SUM(E21:E24) -> 403219 | F25: =SUM(F21:F24) -> 551068 | G25: =SUM(G21:G24) -> 681223.22 | H25: =SUM(H21:H24) -> 819159.96 | I25: =SUM(I21:I24) -> 979481.78 | J25: =SUM(J21:J24) -> 1137518.2 | K25: =SUM(K21:K24) -> 1298030.9
C26: Interest income | D26: 0 | E26: 0 | F26: 0 | G26: =G180 -> 0 | H26: =H180 -> 0 | I26: =I180 -> 0 | J26: =J180 -> 0 | K26: =K180 -> 0
C27: Interest expense | D27: -309645 | E27: -282507 | F27: -174217 | G27: =G166 -> -138781.63 | H27: =H166 -> -134154.66 | I27: =I166 -> -126377.68 | J27: =J166 -> -117025.71 | K27: =K166 -> -106098.74
C28: Refinancing costs | D28: -19921 | E28: -23700 | F28: 0 | G28: =F28 -> 0 | H28: =G28 -> 0 | I28: =H28 -> 0 | J28: =I28 -> 0 | K28: =J28 -> 0
C29: Loss on debt extinguishment | D29: -6182 | E29: -15255 | F29: 0 | G29: =F29 -> 0 | H29: =G29 -> 0 | I29: =H29 -> 0 | J29: =I29 -> 0 | K29: =J29 -> 0
C30: Other expense, net | D30: 3509 | E30: 0 | F30: 0 | G30: 0 | H30: 0 | I30: 0 | J30: 0 | K30: 0
C31: Pretax profit | D31: =SUM(D25:D30) -> 5119 | E31: =SUM(E25:E30) -> 81757 | F31: =SUM(F25:F30) -> 376851 | G31: =SUM(G25:G30) -> 542441.59 | H31: =SUM(H25:H30) -> 685005.3 | I31: =SUM(I25:I30) -> 853104.09 | J31: =SUM(J25:J30) -> 1020492.5 | K31: =SUM(K25:K30) -> 1191932.2
C32: Taxes | D32: -40180 | E32: -70783 | F32: -99435 | G32: =-G31*G46 -> -135610.4 | H32: =-H31*H46 -> -171251.33 | I32: =-I31*I46 -> -213276.02 | J32: =-J31*J46 -> -255123.13 | K32: =-K31*K46 -> -297983.04
C33: Net income | D33: =SUM(D31:D32) -> -35061 | E33: =SUM(E31:E32) -> 10974 | F33: =SUM(F31:F32) -> 277416 | G33: =SUM(G31:G32) -> 406831.19 | H33: =SUM(H31:H32) -> 513753.98 | I33: =SUM(I31:I32) -> 639828.07 | J33: =SUM(J31:J32) -> 765369.38 | K33: =SUM(K31:K32) -> 893949.11
C35: Depreciation & amortization | D35: 197104 | E35: 188164 | F35: 193664 | G35: =G136 -> 193053.33 | H35: =H136 -> 194030.77 | I35: =I136 -> 204169.21 | J35: =J136 -> 214074.75 | K35: =K136 -> 227765.24
C36: EBITDA | D36: =D25+D35 -> 534462 | E36: =E25+E35 -> 591383 | F36: =F25+F35 -> 744732 | G36: =G25+G35 -> 874276.54 | H36: =H25+H35 -> 1013190.7 | I36: =I25+I35 -> 1183651 | J36: =J25+J35 -> 1351593 | K36: =K25+K35 -> 1525796.1
C37: Stock based compensation | D37: 0 | E37: 17376 | F37: 13237 | G37: =F37 -> 13237 | H37: =G37 -> 13237 | I37: =H37 -> 13237 | J37: =I37 -> 13237 | K37: =J37 -> 13237
C38: Adjusted EBITDA | D38: =D36+D37 -> 534462 | E38: =E36+E37 -> 608759 | F38: =F36+F37 -> 757969 | G38: =G36+G37 -> 887513.54 | H38: =H36+H37 -> 1026427.7 | I38: =I36+I37 -> 1196888 | J38: =J36+J37 -> 1364830 | K38: =K36+K37 -> 1539033.1
C40: Growth rates & margins
C41: Revenue growth | E41: =(E19-D19)/D19 -> 0.14767369 | F41: =(F19-E19)/E19 -> 0.15759512 | G41: =(G19-F19)/F19 -> 0.14792189 | H41: =(H19-G19)/G19 -> 0.12916932 | I41: =(I19-H19)/H19 -> 0.11989504 | J41: =(J19-I19)/I19 -> 0.11131061 | K41: =(K19-J19)/J19 -> 0.1065587 | M41: LEAP/CFM56 shop visits ramping; ~80% of revenue under long-term agreements; aging installed base drives MRO demand through 2030; military spending elevated due to geopolitical tensions; business aviation fleet growth
C42: Engine Service growth rate | E42: =(E17-D17)/D17 -> 0.14688652 | F42: =(F17-E17)/E17 -> 0.15269168 | G42: 0.145 | H42: 0.125 | I42: 0.115 | J42: 0.105 | K42: 0.1
C43: Component Repair Service growth rate | E43: =(E18-D18)/D18 -> 0.15388301 | F43: =(F18-E18)/E18 -> 0.19603931 | G43: 0.17 | H43: 0.16 | I43: 0.155 | J43: 0.155 | K43: 0.15
C44: Gross profit margin | D44: =D21/D19 -> 0.13922408 | E44: =E21/E19 -> 0.14399825 | F44: =F21/F19 -> 0.14803303 | G44: 0.152 | H44: 0.155 | I44: 0.16 | J44: 0.163 | K44: 0.165 | M44: LEAP learning curve progressively reduces industrialization costs; mix shift toward higher-margin Component Repair Services; operating leverage on fixed overhead as volumes scale; partially offset by material cost inflation pass-through
C45: SG&A % of sales | D45: =-D23/D19 -> 0.044434228 | E45: =-E23/E19 -> 0.048517126 | F45: =-F23/F19 -> 0.040858146 | G45: 0.041 | H45: 0.04 | I45: 0.039 | J45: 0.038 | K45: 0.037 | M45: SG&A already declined to 4.1% in 2025 (from 4.9% in 2024). Post-IPO one-time costs are behind the company. Further leverage expected as revenue scales against relatively fixed corporate overhead and sales force
C46: Tax rate | D46: =-D32/D31 -> 7.8491893 | E46: =-E32/E31 -> 0.86577296 | F46: =-F32/F31 -> 0.2638576 | G46: 0.25 | H46: 0.25 | I46: 0.25 | J46: 0.25 | K46: 0.25 | M46: 2025 effective rate of 26.4% includes GILTI, state taxes (California heavy), and changes in uncertain tax benefits. OBBBA provisions (signed Jul 4, 2025) restore favorable business tax treatment in 2026–2027 rate likely drifts toward 24–26% as Canada/foreign mix optimizes and interest carryforwards begin to release
B48: X | C48: BALANCE SHEET
C49: =C14 -> Fiscal year | D49: =D14 -> 2023 | E49: =E14 -> 2024 | F49: =F14 -> 2025 | G49: =G14 -> 2026 | H49: =H14 -> 2027 | I49: =I14 -> 2028 | J49: =J14 -> 2029 | K49: =K14 -> 2030
C50: =C15 -> Fiscal year end date | D50: =D15 -> 45291 | E50: =E15 -> 45657 | F50: =F15 -> 46022 | G50: =G15 -> 46387 | H50: =H15 -> 46752 | I50: =I15 -> 47118 | J50: =J15 -> 47483 | K50: =K15 -> 47848
C51: ASSETS
C52: Current Assets
C53: Cash & equivalents, ST and LT marketable securities | E53: 102581 | F53: 289717 | G53: =F53+G120 -> 510509.3 | H53: =G53+H120 -> 601495.9 | I53: =H53+I120 -> 807010.35 | J53: =I53+J120 -> 1051121 | K53: =J53+K120 -> 1409408.5
C54: Accounts receivable | E54: 580668 | F54: 654390 | G54: =F54*(1+G41) -> 751188.61 | H54: =G54*(1+H41) -> 848219.13 | I54: =H54*(1+I41) -> 949916.4 | J54: =I54*(1+J41) -> 1055652.2 | K54: =J54*(1+K41) -> 1168141.1
C55: Contract Assets | E55: 915200 | F55: 1071703 | G55: =F55*(1+G41) -> 1230231.3 | H55: =G55*(1+H41) -> 1389139.5 | I55: =H55*(1+I41) -> 1555690.4 | J55: =I55*(1+J41) -> 1728855.3 | K55: =J55*(1+K41) -> 1913079.8
C56: Inventories | E56: 847018 | F56: 827691 | G56: =F56*(1+((G20-F20)/F20)) -> 945700.6 | H56: =G56*(1+((H20-G20)/G20)) -> 1064078.3 | I56: =H56*(1+((I20-H20)/H20)) -> 1184604.8 | J56: =I56*(1+((J20-I20)/I20)) -> 1311762.2 | K56: =J56*(1+((K20-J20)/J20)) -> 1448073.5
C57: Other current assets | E57: 29707 | F57: 42776 | G57: =F57*(1+G41) -> 49103.507 | H57: =G57*(1+H41) -> 55446.174 | I57: =H57*(1+I41) -> 62093.895 | J57: =I57*(1+J41) -> 69005.604 | K57: =J57*(1+K41) -> 76358.751
C58: Income tax receivable | E58: 9960 | F58: 10182 | G58: =F58 -> 10182 | H58: =G58 -> 10182 | I58: =H58 -> 10182 | J58: =I58 -> 10182 | K58: =J58 -> 10182
C59: Total current assets | E59: =SUM(E53:E58) -> 2485134 | F59: =SUM(F53:F58) -> 2896459 | G59: =SUM(G53:G58) -> 3496915.3 | H59: =SUM(H53:H58) -> 3968561 | I59: =SUM(I53:I58) -> 4569497.9 | J59: =SUM(J53:J58) -> 5226578.3 | K59: =SUM(K53:K58) -> 6025243.7
C60: Property, plant & equipment | E60: 568607 | F60: 579971 | G60: =G129 -> 602929.44 | H60: =H129 -> 628853.4 | I60: =I129 -> 657885.52 | J60: =J129 -> 690149.22 | K60: =K129 -> 725850.9
C61: Operating lease right of use asset | E61: 172206 | F61: 222151 | G61: =F61 -> 222151 | H61: =G61 -> 222151 | I61: =H61 -> 222151 | J61: =I61 -> 222151 | K61: =J61 -> 222151
C62: Customer relationships | E62: 1004701 | F62: 920432 | G62: =F62+-77930 -> 842502 | H62: =G62+-42617 -> 799885 | I62: =H62+-42900 -> 756985 | J62: =I62+-32786 -> 724199 | K62: =J62+-34690 -> 689509
C63: Other intangible assets | E63: 291487 | F63: 244877 | G63: =F63+-16493 -> 228384 | H63: =G63+-13531 -> 214853 | I63: =H63+-13689 -> 201164 | J63: =I63+-13626 -> 187538 | K63: =J63+-14686 -> 172852
C64: Goodwill | E64: 1685970 | F64: 1684255 | G64: =F64 -> 1684255 | H64: =G64+45000 -> 1729255 | I64: =H64+45000 -> 1774255 | J64: =I64+60000 -> 1834255 | K64: =J64+60000 -> 1894255 | M64: Goodwill from bolt-on M&A: ~50% of purchase price per historical allocation
C65: Deferred income tax assets | E65: 1079 | F65: 2832 | G65: =F65 -> 2832 | H65: =G65 -> 2832 | I65: =H65 -> 2832 | J65: =I65 -> 2832 | K65: =J65 -> 2832
C66: Other non current assets | E66: 4417 | F66: 6434 | G66: =F66*(1+G41) -> 7385.7294 | H66: =G66*(1+H41) -> 8339.7391 | I66: =H66*(1+I41) -> 9339.6325 | J66: =I66*(1+J41) -> 10379.233 | K66: =J66*(1+K41) -> 11485.23
C67: Total assets | E67: =SUM(E59:E66) -> 6213601 | F67: =SUM(F59:F66) -> 6557411 | G67: =SUM(G59:G66) -> 7087354.5 | H67: =SUM(H59:H66) -> 7574730.1 | I67: =SUM(I59:I66) -> 8194110 | J67: =SUM(J59:J66) -> 8898081.8 | K67: =SUM(K59:K66) -> 9744178.8
C68: LIABILITIES AND STOCKHOLDERS' EQUITY
C69: Current Liabilities
C70: Accounts payable | E70: 645701 | F70: 679772 | G70: =F70*(1+(G20-F20)/F20) -> 776691.77 | H70: =G70*(1+(H20-G20)/G20) -> 873913.87 | I70: =H70*(1+(I20-H20)/H20) -> 972900.73 | J70: =I70*(1+(J20-I20)/I20) -> 1077333.5 | K70: =J70*(1+(K20-J20)/J20) -> 1189284.2
C71: Accrued expenses and other current liabilities | E71: 99572 | F71: 91499 | G71: =F71*(1+G41) -> 105033.71 | H71: =G71*(1+H41) -> 118600.84 | I71: =H71*(1+I41) -> 132820.49 | J71: =I71*(1+J41) -> 147604.82 | K71: =J71*(1+K41) -> 163333.4
C72: Accrued employ costs | E72: 79134 | F72: 74008 | G72: =F72*(1+G41) -> 84955.403 | H72: =G72*(1+H41) -> 95929.035 | I72: =H72*(1+I41) -> 107430.45 | J72: =I72*(1+J41) -> 119388.6 | K72: =J72*(1+K41) -> 132110.49
C73: Operating lease liabilities, current | E73: 17663 | F73: 22308 | G73: =F73 -> 22308 | H73: =G73 -> 22308 | I73: =H73 -> 22308 | J73: =I73 -> 22308 | K73: =J73 -> 22308
C74: Due to related parties | E74: 1345 | F74: 438 | G74: =F74 -> 438 | H74: =G74 -> 438 | I74: =H74 -> 438 | J74: =I74 -> 438 | K74: =J74 -> 438
C75: Contract liabilities | E75: 400025 | F75: 411321 | G75: =F75*(1+G41) -> 472164.38 | H75: =G75*(1+H41) -> 533153.53 | I75: =H75*(1+I41) -> 597076 | J75: =I75*(1+J41) -> 663536.89 | K75: =J75*(1+K41) -> 734242.52
C76: Income taxes payable, current | E76: 6655 | F76: 13547 | G76: =F76 -> 13547 | H76: =G76 -> 13547 | I76: =H76 -> 13547 | J76: =I76 -> 13547 | K76: =J76 -> 13547
C77: Long-term debt, current portion | E77: 23449 | F77: 23444 | G77: =F77 -> 23444 | H77: =G77 -> 23444 | I77: =H77 -> 23444 | J77: =I77 -> 23444 | K77: =J77 -> 23444
C78: Total current liabilities | E78: =SUM(E70:E77) -> 1273544 | F78: =SUM(F70:F77) -> 1316337 | G78: =SUM(G70:G77) -> 1498582.3 | H78: =SUM(H70:H77) -> 1681334.3 | I78: =SUM(I70:I77) -> 1869964.7 | J78: =SUM(J70:J77) -> 2067600.8 | K78: =SUM(K70:K77) -> 2278707.6
C79: Long term debt | E79: 2207977 | F79: 2191161 | G79: =F79-F77+G159+G119 -> 2167717 | H79: =G79-G77+H159-G159+H119 -> 2044273 | I79: =H79-H77+I159-H159+I119 -> 1920829 | J79: =I79-I77+J159-I159+J119 -> 1747385 | K79: =J79-J77+K159-J159+K119 -> 1573941
C80: Operating Lease Liabilities Non Current | E80: 164224 | F80: 212365 | G80: =F80 -> 212365 | H80: =G80 -> 212365 | I80: =H80 -> 212365 | J80: =I80 -> 212365 | K80: =J80 -> 212365
C81: Deferred income tax liabilities | E81: 169824 | F81: 157206 | G81: =F81 -> 157206 | H81: =G81 -> 157206 | I81: =H81 -> 157206 | J81: =I81 -> 157206 | K81: =J81 -> 157206
C82: Income tax payable, non-current | E82: 0 | F82: 5770 | G82: =F82 -> 5770 | H82: =G82 -> 5770 | I82: =H82 -> 5770 | J82: =I82 -> 5770 | K82: =J82 -> 5770
C83: Other non current liabilities | E83: 24628 | F83: 7261 | G83: =F83*(1+G41) -> 8335.0609 | H83: =G83*(1+H41) -> 9411.695 | I83: =H83*(1+I41) -> 10540.111 | J83: =I83*(1+J41) -> 11713.337 | K83: =J83*(1+K41) -> 12961.495
C84: Total liabilities | E84: =SUM(E78:E83) -> 3840197 | F84: =SUM(F78:F83) -> 3890100 | G84: =SUM(G78:G83) -> 4049975.3 | H84: =SUM(H78:H83) -> 4110360 | I84: =SUM(I78:I83) -> 4176674.8 | J84: =SUM(J78:J83) -> 4202040.1 | K84: =SUM(K78:K83) -> 4240951.1
C85: Commitments and contingencies | E85: 0 | F85: 0 | G85: 0 | H85: 0 | I85: 0 | J85: 0 | K85: 0
C86: Stockholders Equity:
C87: Common stock | E87: 3345 | F87: 3345 | G87: =F87 -> 3345 | H87: =G87 -> 3345 | I87: =H87 -> 3345 | J87: =I87 -> 3345 | K87: =J87 -> 3345
C88: Preferred stock | E88: 0 | F88: 0 | G88: 0 | H88: 0 | I88: 0 | J88: 0 | K88: 0
C89: Adittional paid-in capital | E89: 3944802 | F89: 3958039 | G89: =F89+G37 -> 3971276 | H89: =G89+H37 -> 3984513 | I89: =H89+I37 -> 3997750 | J89: =I89+J37 -> 4010987 | K89: =J89+K37 -> 4024224
C90: Accumulated deficit | E90: -1563321 | F90: -1285904 | G90: =F90+G33 -> -879072.81 | H90: =G90+H33 -> -365318.83 | I90: =H90+I33 -> 274509.24 | J90: =I90+J33 -> 1039878.6 | K90: =J90+K33 -> 1933827.7
C91: Accumulated other comprehensive loss | E91: -11422 | F91: -8169 | G91: =F91 -> -8169 | H91: =G91 -> -8169 | I91: =H91 -> -8169 | J91: =I91 -> -8169 | K91: =J91 -> -8169
C92: Treasury stock | E92: 0 | F92: 0 | G92: =F92+G116 -> -50000 | H92: =G92+H116 -> -150000 | I92: =H92+I116 -> -250000 | J92: =I92+J116 -> -350000 | K92: =J92+K116 -> -450000
C93: Total equity | E93: =SUM(E87:E92) -> 2373404 | F93: =SUM(F87:F92) -> 2667311 | G93: =SUM(G87:G92) -> 3037379.2 | H93: =SUM(H87:H92) -> 3464370.2 | I93: =SUM(I87:I92) -> 4017435.2 | J93: =SUM(J87:J92) -> 4696041.6 | K93: =SUM(K87:K92) -> 5503227.7
C94: Total liabilities and stockholders' equity | E94: =SUM(E93,E84) -> 6213601 | F94: =SUM(F93,F84) -> 6557411 | G94: =SUM(G93,G84) -> 7087354.5 | H94: =SUM(H93,H84) -> 7574730.1 | I94: =SUM(I93,I84) -> 8194110 | J94: =SUM(J93,J84) -> 8898081.8 | K94: =SUM(K93,K84) -> 9744178.8
C96: Balance check | E96: =E67-E94 -> 0 | F96: =F67-F94 -> 0 | G96: =G67-G94 -> 0 | H96: =H67-H94 -> 0 | I96: =I67-I94 -> 0 | J96: =J67-J94 -> 0 | K96: =K67-K94 -> 0
B98: X | C98: CASH FLOW STATEMENT
C99: =C14 -> Fiscal year | G99: =G14 -> 2026 | H99: =H14 -> 2027 | I99: =I14 -> 2028 | J99: =J14 -> 2029 | K99: =K14 -> 2030
C100: =C15 -> Fiscal year end date | G100: =G15 -> 46387 | H100: =H15 -> 46752 | I100: =I15 -> 47118 | J100: =J15 -> 47483 | K100: =K15 -> 47848
C102: Net income | G102: =G33 -> 406831.19 | H102: =H33 -> 513753.98 | I102: =I33 -> 639828.07 | J102: =J33 -> 765369.38 | K102: =K33 -> 893949.11
C103: Depreciation and amortization | G103: =G35 -> 193053.33 | H103: =H35 -> 194030.77 | I103: =I35 -> 204169.21 | J103: =J35 -> 214074.75 | K103: =K35 -> 227765.24
C104: Stock based compensation | G104: =G37 -> 13237 | H104: =H37 -> 13237 | I104: =I37 -> 13237 | J104: =J37 -> 13237 | K104: =K37 -> 13237
C105: Decreases / (Increases) in working capital assets | G105: =F54+F55+F56+F57-G54-G55-G56-G57 -> -379664.05 | H105: =G54+G55+G56+G57-H54-H55-H56-H57 -> -380659.05 | I105: =H54+H55+H56+H57-I54-I55-I56-I57 -> -395422.42 | J105: =I54+I55+I56+I57-J54-J55-J56-J57 -> -412969.75 | K105: =J54+J55+J56+J57-K54-K55-K56-K57 -> -440377.87
C106: Increases / (Decreases) in working capital liabilities | G106: =G70+G71+G72+G75-F70-F71-F72-F75 -> 182245.26 | H106: =H70+H71+H72+H75-G70-G71-G72-G75 -> 182752.02 | I106: =I70+I71+I72+I75-H70-H71-H72-H75 -> 188630.4 | J106: =J70+J71+J72+J75-I70-I71-I72-I75 -> 197636.13 | K106: =K70+K71+K72+K75-J70-J71-J72-J75 -> 211106.77
C107: Other non current assets | G107: =-G66+F66 -> -951.72945 | H107: =-H66+G66 -> -954.00968 | I107: =-I66+H66 -> -999.89338 | J107: =-J66+I66 -> -1039.6002 | K107: =-K66+J66 -> -1105.9975
C108: Other non current liabilities | G108: =G83-F83 -> 1074.0609 | H108: =H83-G83 -> 1076.6342 | I108: =I83-H83 -> 1128.4156 | J108: =J83-I83 -> 1173.2261 | K108: =K83-J83 -> 1248.1579
C109: Cash from operating activities | G109: =SUM(G102:G108) -> 415825.06 | H109: =SUM(H102:H108) -> 523237.33 | I109: =SUM(I102:I108) -> 650570.78 | J109: =SUM(J102:J108) -> 777481.14 | K109: =SUM(K102:K108) -> 905822.41
C110: Acquisitions, net of cash | G110: 0 | H110: -75000 | I110: -75000 | J110: -100000 | K110: -100000 | M110: Normalized bolt-on M&A based on Western Jet ($33M) and Aero Turbine ($132M) historical cadence; 10-K states company "continually acquiring and investing"
...

Sheet vF with M&A and Prepayment (2)
B2: X | C2: ="Financial Statement Model for "&D5 -> Financial Statement Model for StandardAero
C3: $ in thousands except per share
C5: Company name | D5: StandardAero
C6: Ticker | D6: SARO
D7: 1
C8: Latest closing share price | D8: 25.59
C9: Latest closing share price date | D9: 46119
C10: Latest fiscal year end date | D10: 46022
C11: Shares outstanding (millions) | D11: 334294 | M11: Outstanding at Dec 31, 2025 per 10-K BS. Jan 2026 repurchase of 1,637k shares (subsequent event) reduces to 332,657k.
B13: X | C13: INCOME STATEMENT
C14: Fiscal year | D14: =E14-1 -> 2023 | E14: =F14-1 -> 2024 | F14: =YEAR(D10) -> 2025 | G14: =F14+1 -> 2026 | H14: =G14+1 -> 2027 | I14: =H14+1 -> 2028 | J14: =I14+1 -> 2029 | K14: =J14+1 -> 2030
C15: Fiscal year end date | D15: =EOMONTH(E15,-12) -> 45291 | E15: =EOMONTH(F15,-12) -> 45657 | F15: =D10 -> 46022 | G15: =EOMONTH(F15,12) -> 46387 | H15: =EOMONTH(G15,12) -> 46752 | I15: =EOMONTH(H15,12) -> 47118 | J15: =EOMONTH(I15,12) -> 47483 | K15: =EOMONTH(J15,12) -> 47848 | M15: Comments
C17: Revenue from Engine Repair | D17: 4049868 | E17: 4644739 | F17: 5353952 | G17: =F17*(1+G42) -> 6130275 | H17: =G17*(1+H42) -> 6896559.4 | I17: =H17*(1+I42) -> 7689663.8 | J17: =I17*(1+J42) -> 8497078.4 | K17: =J17*(1+K42) -> 9346786.3
C18: Revenue from Component Repair | D18: 513416 | E18: 592422 | F18: 708560 | G18: =F18*(1+G43) -> 829015.2 | H18: =G18*(1+H43) -> 961657.63 | I18: =H18*(1+I43) -> 1110714.6 | J18: =I18*(1+J43) -> 1282875.3 | K18: =J18*(1+K43) -> 1475306.6
C19: Total Revenue | D19: =D18+D17 -> 4563284 | E19: =E18+E17 -> 5237161 | F19: =F18+F17 -> 6062512 | G19: =G18+G17 -> 6959290.2 | H19: =H18+H17 -> 7858217.1 | I19: =I18+I17 -> 8800378.3 | J19: =J18+J17 -> 9779953.8 | K19: =K18+K17 -> 10822093
C20: Cost of sales | D20: -3927965 | E20: -4483019 | F20: -5165060 | G20: =G21-G19 -> -5901478.1 | H20: =H21-H19 -> -6640193.4 | I20: =I21-I19 -> -7392317.8 | J20: =J21-J19 -> -8185821.3 | K20: =K21-K19 -> -9036447.6
C21: Gross Profit | D21: =SUM(D19:D20) -> 635319 | E21: =SUM(E19:E20) -> 754142 | F21: =SUM(F19:F20) -> 897452 | G21: =G19*G44 -> 1057812.1 | H21: =H19*H44 -> 1218023.6 | I21: =I19*I44 -> 1408060.5 | J21: =J19*J44 -> 1594132.5 | K21: =K19*K44 -> 1785645.3
C22: Amortisation of intangible assets | D22: -93681 | E22: -95457 | F22: -98681 | G22: -91258 | H22: -84535 | I22: -85364 | J22: -84976 | K22: -87197 | M22: IS-line amort only (excl OEM auth amort in COGS). Total amort per Note 9 used for BS reduction in rows 58/59.
C23: Selling, general & administrative | D23: -202766 | E23: -254092 | F23: -247703 | G23: =-G19*G45 -> -285330.9 | H23: =-H19*H45 -> -314328.68 | I23: =-I19*I45 -> -343214.75 | J23: =-J19*J45 -> -371638.24 | K23: =-K19*K45 -> -400417.44
C24: Acquisition Cost | D24: -1514 | E24: -1374 | F24: 0 | G24: =F24 -> 0 | H24: =G24 -> 0 | I24: =H24 -> 0 | J24: =I24 -> 0 | K24: =J24 -> 0
C25: Operating profit (EBIT) | D25: =SUM(D21:D24) -> 337358 | E25: =SUM(E21:E24) -> 403219 | F25: =SUM(F21:F24) -> 551068 | G25: =SUM(G21:G24) -> 681223.22 | H25: =SUM(H21:H24) -> 819159.96 | I25: =SUM(I21:I24) -> 979481.78 | J25: =SUM(J21:J24) -> 1137518.2 | K25: =SUM(K21:K24) -> 1298030.9
C26: Interest income | D26: 0 | E26: 0 | F26: 0 | G26: =G180 -> 0 | H26: =H180 -> 0 | I26: =I180 -> 0 | J26: =J180 -> 0 | K26: =K180 -> 0
C27: Interest expense | D27: -309645 | E27: -282507 | F27: -174217 | G27: =G166 -> -138781.63 | H27: =H166 -> -134154.66 | I27: =I166 -> -126377.68 | J27: =J166 -> -117025.71 | K27: =K166 -> -106098.74
C28: Refinancing costs | D28: -19921 | E28: -23700 | F28: 0 | G28: =F28 -> 0 | H28: =G28 -> 0 | I28: =H28 -> 0 | J28: =I28 -> 0 | K28: =J28 -> 0
C29: Loss on debt extinguishment | D29: -6182 | E29: -15255 | F29: 0 | G29: =F29 -> 0 | H29: =G29 -> 0 | I29: =H29 -> 0 | J29: =I29 -> 0 | K29: =J29 -> 0
C30: Other expense, net | D30: 3509 | E30: 0 | F30: 0 | G30: 0 | H30: 0 | I30: 0 | J30: 0 | K30: 0
C31: Pretax profit | D31: =SUM(D25:D30) -> 5119 | E31: =SUM(E25:E30) -> 81757 | F31: =SUM(F25:F30) -> 376851 | G31: =SUM(G25:G30) -> 542441.59 | H31: =SUM(H25:H30) -> 685005.3 | I31: =SUM(I25:I30) -> 853104.09 | J31: =SUM(J25:J30) -> 1020492.5 | K31: =SUM(K25:K30) -> 1191932.2
C32: Taxes | D32: -40180 | E32: -70783 | F32: -99435 | G32: =-G31*G46 -> -135610.4 | H32: =-H31*H46 -> -171251.33 | I32: =-I31*I46 -> -213276.02 | J32: =-J31*J46 -> -255123.13 | K32: =-K31*K46 -> -297983.04
C33: Net income | D33: =SUM(D31:D32) -> -35061 | E33: =SUM(E31:E32) -> 10974 | F33: =SUM(F31:F32) -> 277416 | G33: =SUM(G31:G32) -> 406831.19 | H33: =SUM(H31:H32) -> 513753.98 | I33: =SUM(I31:I32) -> 639828.07 | J33: =SUM(J31:J32) -> 765369.38 | K33: =SUM(K31:K32) -> 893949.11
C35: Depreciation & amortization | D35: 197104 | E35: 188164 | F35: 193664 | G35: =G136 -> 193053.33 | H35: =H136 -> 194030.77 | I35: =I136 -> 204169.21 | J35: =J136 -> 214074.75 | K35: =K136 -> 227765.24
C36: EBITDA | D36: =D25+D35 -> 534462 | E36: =E25+E35 -> 591383 | F36: =F25+F35 -> 744732 | G36: =G25+G35 -> 874276.54 | H36: =H25+H35 -> 1013190.7 | I36: =I25+I35 -> 1183651 | J36: =J25+J35 -> 1351593 | K36: =K25+K35 -> 1525796.1
C37: Stock based compensation | D37: 0 | E37: 17376 | F37: 13237 | G37: =F37 -> 13237 | H37: =G37 -> 13237 | I37: =H37 -> 13237 | J37: =I37 -> 13237 | K37: =J37 -> 13237
C38: Adjusted EBITDA | D38: =D36+D37 -> 534462 | E38: =E36+E37 -> 608759 | F38: =F36+F37 -> 757969 | G38: =G36+G37 -> 887513.54 | H38: =H36+H37 -> 1026427.7 | I38: =I36+I37 -> 1196888 | J38: =J36+J37 -> 1364830 | K38: =K36+K37 -> 1539033.1
C40: Growth rates & margins
C41: Revenue growth | E41: =(E19-D19)/D19 -> 0.14767369 | F41: =(F19-E19)/E19 -> 0.15759512 | G41: =(G19-F19)/F19 -> 0.14792189 | H41: =(H19-G19)/G19 -> 0.12916932 | I41: =(I19-H19)/H19 -> 0.11989504 | J41: =(J19-I19)/I19 -> 0.11131061 | K41: =(K19-J19)/J19 -> 0.1065587 | M41: LEAP/CFM56 shop visits ramping; ~80% of revenue under long-term agreements; aging installed base drives MRO demand through 2030; military spending elevated due to geopolitical tensions; business aviation fleet growth
C42: Engine Service growth rate | E42: =(E17-D17)/D17 -> 0.14688652 | F42: =(F17-E17)/E17 -> 0.15269168 | G42: 0.145 | H42: 0.125 | I42: 0.115 | J42: 0.105 | K42: 0.1
C43: Component Repair Service growth rate | E43: =(E18-D18)/D18 -> 0.15388301 | F43: =(F18-E18)/E18 -> 0.19603931 | G43: 0.17 | H43: 0.16 | I43: 0.155 | J43: 0.155 | K43: 0.15
C44: Gross profit margin | D44: =D21/D19 -> 0.13922408 | E44: =E21/E19 -> 0.14399825 | F44: =F21/F19 -> 0.14803303 | G44: 0.152 | H44: 0.155 | I44: 0.16 | J44: 0.163 | K44: 0.165 | M44: LEAP learning curve progressively reduces industrialization costs; mix shift toward higher-margin Component Repair Services; operating leverage on fixed overhead as volumes scale; partially offset by material cost inflation pass-through
C45: SG&A % of sales | D45: =-D23/D19 -> 0.044434228 | E45: =-E23/E19 -> 0.048517126 | F45: =-F23/F19 -> 0.040858146 | G45: 0.041 | H45: 0.04 | I45: 0.039 | J45: 0.038 | K45: 0.037 | M45: SG&A already declined to 4.1% in 2025 (from 4.9% in 2024). Post-IPO one-time costs are behind the company. Further leverage expected as revenue scales against relatively fixed corporate overhead and sales force
C46: Tax rate | D46: =-D32/D31 -> 7.8491893 | E46: =-E32/E31 -> 0.86577296 | F46: =-F32/F31 -> 0.2638576 | G46: 0.25 | H46: 0.25 | I46: 0.25 | J46: 0.25 | K46: 0.25 | M46: 2025 effective rate of 26.4% includes GILTI, state taxes (California heavy), and changes in uncertain tax benefits. OBBBA provisions (signed Jul 4, 2025) restore favorable business tax treatment in 2026–2027 rate likely drifts toward 24–26% as Canada/foreign mix optimizes and interest carryforwards begin to release
B48: X | C48: BALANCE SHEET
C49: =C14 -> Fiscal year | D49: =D14 -> 2023 | E49: =E14 -> 2024 | F49: =F14 -> 2025 | G49: =G14 -> 2026 | H49: =H14 -> 2027 | I49: =I14 -> 2028 | J49: =J14 -> 2029 | K49: =K14 -> 2030
C50: =C15 -> Fiscal year end date | D50: =D15 -> 45291 | E50: =E15 -> 45657 | F50: =F15 -> 46022 | G50: =G15 -> 46387 | H50: =H15 -> 46752 | I50: =I15 -> 47118 | J50: =J15 -> 47483 | K50: =K15 -> 47848
C51: ASSETS
C52: Current Assets
C53: Cash & equivalents, ST and LT marketable securities | E53: 102581 | F53: 289717 | G53: =F53+G120 -> 510509.3 | H53: =G53+H120 -> 601495.9 | I53: =H53+I120 -> 807010.35 | J53: =I53+J120 -> 1051121 | K53: =J53+K120 -> 1409408.5
C54: Accounts receivable | E54: 580668 | F54: 654390 | G54: =F54*(1+G41) -> 751188.61 | H54: =G54*(1+H41) -> 848219.13 | I54: =H54*(1+I41) -> 949916.4 | J54: =I54*(1+J41) -> 1055652.2 | K54: =J54*(1+K41) -> 1168141.1
C55: Contract Assets | E55: 915200 | F55: 1071703 | G55: =F55*(1+G41) -> 1230231.3 | H55: =G55*(1+H41) -> 1389139.5 | I55: =H55*(1+I41) -> 1555690.4 | J55: =I55*(1+J41) -> 1728855.3 | K55: =J55*(1+K41) -> 1913079.8
C56: Inventories | E56: 847018 | F56: 827691 | G56: =F56*(1+((G20-F20)/F20)) -> 945700.6 | H56: =G56*(1+((H20-G20)/G20)) -> 1064078.3 | I56: =H56*(1+((I20-H20)/H20)) -> 1184604.8 | J56: =I56*(1+((J20-I20)/I20)) -> 1311762.2 | K56: =J56*(1+((K20-J20)/J20)) -> 1448073.5
C57: Other current assets | E57: 29707 | F57: 42776 | G57: =F57*(1+G41) -> 49103.507 | H57: =G57*(1+H41) -> 55446.174 | I57: =H57*(1+I41) -> 62093.895 | J57: =I57*(1+J41) -> 69005.604 | K57: =J57*(1+K41) -> 76358.751
C58: Income tax receivable | E58: 9960 | F58: 10182 | G58: =F58 -> 10182 | H58: =G58 -> 10182 | I58: =H58 -> 10182 | J58: =I58 -> 10182 | K58: =J58 -> 10182
C59: Total current assets | E59: =SUM(E53:E58) -> 2485134 | F59: =SUM(F53:F58) -> 2896459 | G59: =SUM(G53:G58) -> 3496915.3 | H59: =SUM(H53:H58) -> 3968561 | I59: =SUM(I53:I58) -> 4569497.9 | J59: =SUM(J53:J58) -> 5226578.3 | K59: =SUM(K53:K58) -> 6025243.7
C60: Property, plant & equipment | E60: 568607 | F60: 579971 | G60: =G129 -> 602929.44 | H60: =H129 -> 628853.4 | I60: =I129 -> 657885.52 | J60: =J129 -> 690149.22 | K60: =K129 -> 725850.9
C61: Operating lease right of use asset | E61: 172206 | F61: 222151 | G61: =F61 -> 222151 | H61: =G61 -> 222151 | I61: =H61 -> 222151 | J61: =I61 -> 222151 | K61: =J61 -> 222151
C62: Customer relationships | E62: 1004701 | F62: 920432 | G62: =F62+-77930 -> 842502 | H62: =G62+-42617 -> 799885 | I62: =H62+-42900 -> 756985 | J62: =I62+-32786 -> 724199 | K62: =J62+-34690 -> 689509
C63: Other intangible assets | E63: 291487 | F63: 244877 | G63: =F63+-16493 -> 228384 | H63: =G63+-13531 -> 214853 | I63: =H63+-13689 -> 201164 | J63: =I63+-13626 -> 187538 | K63: =J63+-14686 -> 172852
C64: Goodwill | E64: 1685970 | F64: 1684255 | G64: =F64 -> 1684255 | H64: =G64+45000 -> 1729255 | I64: =H64+45000 -> 1774255 | J64: =I64+60000 -> 1834255 | K64: =J64+60000 -> 1894255 | M64: Goodwill from bolt-on M&A: ~50% of purchase price per historical allocation
C65: Deferred income tax assets | E65: 1079 | F65: 2832 | G65: =F65 -> 2832 | H65: =G65 -> 2832 | I65: =H65 -> 2832 | J65: =I65 -> 2832 | K65: =J65 -> 2832
C66: Other non current assets | E66: 4417 | F66: 6434 | G66: =F66*(1+G41) -> 7385.7294 | H66: =G66*(1+H41) -> 8339.7391 | I66: =H66*(1+I41) -> 9339.6325 | J66: =I66*(1+J41) -> 10379.233 | K66: =J66*(1+K41) -> 11485.23
C67: Total assets | E67: =SUM(E59:E66) -> 6213601 | F67: =SUM(F59:F66) -> 6557411 | G67: =SUM(G59:G66) -> 7087354.5 | H67: =SUM(H59:H66) -> 7574730.1 | I67: =SUM(I59:I66) -> 8194110 | J67: =SUM(J59:J66) -> 8898081.8 | K67: =SUM(K59:K66) -> 9744178.8
C68: LIABILITIES AND STOCKHOLDERS' EQUITY
C69: Current Liabilities
C70: Accounts payable | E70: 645701 | F70: 679772 | G70: =F70*(1+(G20-F20)/F20) -> 776691.77 | H70: =G70*(1+(H20-G20)/G20) -> 873913.87 | I70: =H70*(1+(I20-H20)/H20) -> 972900.73 | J70: =I70*(1+(J20-I20)/I20) -> 1077333.5 | K70: =J70*(1+(K20-J20)/J20) -> 1189284.2
C71: Accrued expenses and other current liabilities | E71: 99572 | F71: 91499 | G71: =F71*(1+G41) -> 105033.71 | H71: =G71*(1+H41) -> 118600.84 | I71: =H71*(1+I41) -> 132820.49 | J71: =I71*(1+J41) -> 147604.82 | K71: =J71*(1+K41) -> 163333.4
C72: Accrued employ costs | E72: 79134 | F72: 74008 | G72: =F72*(1+G41) -> 84955.403 | H72: =G72*(1+H41) -> 95929.035 | I72: =H72*(1+I41) -> 107430.45 | J72: =I72*(1+J41) -> 119388.6 | K72: =J72*(1+K41) -> 132110.49
C73: Operating lease liabilities, current | E73: 17663 | F73: 22308 | G73: =F73 -> 22308 | H73: =G73 -> 22308 | I73: =H73 -> 22308 | J73: =I73 -> 22308 | K73: =J73 -> 22308
C74: Due to related parties | E74: 1345 | F74: 438 | G74: =F74 -> 438 | H74: =G74 -> 438 | I74: =H74 -> 438 | J74: =I74 -> 438 | K74: =J74 -> 438
C75: Contract liabilities | E75: 400025 | F75: 411321 | G75: =F75*(1+G41) -> 472164.38 | H75: =G75*(1+H41) -> 533153.53 | I75: =H75*(1+I41) -> 597076 | J75: =I75*(1+J41) -> 663536.89 | K75: =J75*(1+K41) -> 734242.52
C76: Income taxes payable, current | E76: 6655 | F76: 13547 | G76: =F76 -> 13547 | H76: =G76 -> 13547 | I76: =H76 -> 13547 | J76: =I76 -> 13547 | K76: =J76 -> 13547
C77: Long-term debt, current portion | E77: 23449 | F77: 23444 | G77: =F77 -> 23444 | H77: =G77 -> 23444 | I77: =H77 -> 23444 | J77: =I77 -> 23444 | K77: =J77 -> 23444
C78: Total current liabilities | E78: =SUM(E70:E77) -> 1273544 | F78: =SUM(F70:F77) -> 1316337 | G78: =SUM(G70:G77) -> 1498582.3 | H78: =SUM(H70:H77) -> 1681334.3 | I78: =SUM(I70:I77) -> 1869964.7 | J78: =SUM(J70:J77) -> 2067600.8 | K78: =SUM(K70:K77) -> 2278707.6
C79: Long term debt | E79: 2207977 | F79: 2191161 | G79: =F79-F77+G159+G119 -> 2167717 | H79: =G79-G77+H159-G159+H119 -> 2044273 | I79: =H79-H77+I159-H159+I119 -> 1920829 | J79: =I79-I77+J159-I159+J119 -> 1747385 | K79: =J79-J77+K159-J159+K119 -> 1573941
C80: Operating Lease Liabilities Non Current | E80: 164224 | F80: 212365 | G80: =F80 -> 212365 | H80: =G80 -> 212365 | I80: =H80 -> 212365 | J80: =I80 -> 212365 | K80: =J80 -> 212365
C81: Deferred income tax liabilities | E81: 169824 | F81: 157206 | G81: =F81 -> 157206 | H81: =G81 -> 157206 | I81: =H81 -> 157206 | J81: =I81 -> 157206 | K81: =J81 -> 157206
C82: Income tax payable, non-current | E82: 0 | F82: 5770 | G82: =F82 -> 5770 | H82: =G82 -> 5770 | I82: =H82 -> 5770 | J82: =I82 -> 5770 | K82: =J82 -> 5770
C83: Other non current liabilities | E83: 24628 | F83: 7261 | G83: =F83*(1+G41) -> 8335.0609 | H83: =G83*(1+H41) -> 9411.695 | I83: =H83*(1+I41) -> 10540.111 | J83: =I83*(1+J41) -> 11713.337 | K83: =J83*(1+K41) -> 12961.495
C84: Total liabilities | E84: =SUM(E78:E83) -> 3840197 | F84: =SUM(F78:F83) -> 3890100 | G84: =SUM(G78:G83) -> 4049975.3 | H84: =SUM(H78:H83) -> 4110360 | I84: =SUM(I78:I83) -> 4176674.8 | J84: =SUM(J78:J83) -> 4202040.1 | K84: =SUM(K78:K83) -> 4240951.1
C85: Commitments and contingencies | E85: 0 | F85: 0 | G85: 0 | H85: 0 | I85: 0 | J85: 0 | K85: 0
C86: Stockholders Equity:
C87: Common stock | E87: 3345 | F87: 3345 | G87: =F87 -> 3345 | H87: =G87 -> 3345 | I87: =H87 -> 3345 | J87: =I87 -> 3345 | K87: =J87 -> 3345
C88: Preferred stock | E88: 0 | F88: 0 | G88: 0 | H88: 0 | I88: 0 | J88: 0 | K88: 0
C89: Adittional paid-in capital | E89: 3944802 | F89: 3958039 | G89: =F89+G37 -> 3971276 | H89: =G89+H37 -> 3984513 | I89: =H89+I37 -> 3997750 | J89: =I89+J37 -> 4010987 | K89: =J89+K37 -> 4024224
C90: Accumulated deficit | E90: -1563321 | F90: -1285904 | G90: =F90+G33 -> -879072.81 | H90: =G90+H33 -> -365318.83 | I90: =H90+I33 -> 274509.24 | J90: =I90+J33 -> 1039878.6 | K90: =J90+K33 -> 1933827.7
C91: Accumulated other comprehensive loss | E91: -11422 | F91: -8169 | G91: =F91 -> -8169 | H91: =G91 -> -8169 | I91: =H91 -> -8169 | J91: =I91 -> -8169 | K91: =J91 -> -8169
C92: Treasury stock | E92: 0 | F92: 0 | G92: =F92+G116 -> -50000 | H92: =G92+H116 -> -150000 | I92: =H92+I116 -> -250000 | J92: =I92+J116 -> -350000 | K92: =J92+K116 -> -450000
C93: Total equity | E93: =SUM(E87:E92) -> 2373404 | F93: =SUM(F87:F92) -> 2667311 | G93: =SUM(G87:G92) -> 3037379.2 | H93: =SUM(H87:H92) -> 3464370.2 | I93: =SUM(I87:I92) -> 4017435.2 | J93: =SUM(J87:J92) -> 4696041.6 | K93: =SUM(K87:K92) -> 5503227.7
C94: Total liabilities and stockholders' equity | E94: =SUM(E93,E84) -> 6213601 | F94: =SUM(F93,F84) -> 6557411 | G94: =SUM(G93,G84) -> 7087354.5 | H94: =SUM(H93,H84) -> 7574730.1 | I94: =SUM(I93,I84) -> 8194110 | J94: =SUM(J93,J84) -> 8898081.8 | K94: =SUM(K93,K84) -> 9744178.8
C96: Balance check | E96: =E67-E94 -> 0 | F96: =F67-F94 -> 0 | G96: =G67-G94 -> 0 | H96: =H67-H94 -> 0 | I96: =I67-I94 -> 0 | J96: =J67-J94 -> 0 | K96: =K67-K94 -> 0
B98: X | C98: CASH FLOW STATEMENT
C99: =C14 -> Fiscal year | G99: =G14 -> 2026 | H99: =H14 -> 2027 | I99: =I14 -> 2028 | J99: =J14 -> 2029 | K99: =K14 -> 2030
C100: =C15 -> Fiscal year end date | G100: =G15 -> 46387 | H100: =H15 -> 46752 | I100: =I15 -> 47118 | J100: =J15 -> 47483 | K100: =K15 -> 47848
C102: Net income | G102: =G33 -> 406831.19 | H102: =H33 -> 513753.98 | I102: =I33 -> 639828.07 | J102: =J33 -> 765369.38 | K102: =K33 -> 893949.11
C103: Depreciation and amortization | G103: =G35 -> 193053.33 | H103: =H35 -> 194030.77 | I103: =I35 -> 204169.21 | J103: =J35 -> 214074.75 | K103: =K35 -> 227765.24
C104: Stock based compensation | G104: =G37 -> 13237 | H104: =H37 -> 13237 | I104: =I37 -> 13237 | J104: =J37 -> 13237 | K104: =K37 -> 13237
C105: Decreases / (Increases) in working capital assets | G105: =F54+F55+F56+F57-G54-G55-G56-G57 -> -379664.05 | H105: =G54+G55+G56+G57-H54-H55-H56-H57 -> -380659.05 | I105: =H54+H55+H56+H57-I54-I55-I56-I57 -> -395422.42 | J105: =I54+I55+I56+I57-J54-J55-J56-J57 -> -412969.75 | K105: =J54+J55+J56+J57-K54-K55-K56-K57 -> -440377.87
C106: Increases / (Decreases) in working capital liabilities | G106: =G70+G71+G72+G75-F70-F71-F72-F75 -> 182245.26 | H106: =H70+H71+H72+H75-G70-G71-G72-G75 -> 182752.02 | I106: =I70+I71+I72+I75-H70-H71-H72-H75 -> 188630.4 | J106: =J70+J71+J72+J75-I70-I71-I72-I75 -> 197636.13 | K106: =K70+K71+K72+K75-J70-J71-J72-J75 -> 211106.77
C107: Other non current assets | G107: =-G66+F66 -> -951.72945 | H107: =-H66+G66 -> -954.00968 | I107: =-I66+H66 -> -999.89338 | J107: =-J66+I66 -> -1039.6002 | K107: =-K66+J66 -> -1105.9975
C108: Other non current liabilities | G108: =G83-F83 -> 1074.0609 | H108: =H83-G83 -> 1076.6342 | I108: =I83-H83 -> 1128.4156 | J108: =J83-I83 -> 1173.2261 | K108: =K83-J83 -> 1248.1579
C109: Cash from operating activities | G109: =SUM(G102:G108) -> 415825.06 | H109: =SUM(H102:H108) -> 523237.33 | I109: =SUM(I102:I108) -> 650570.78 | J109: =SUM(J102:J108) -> 777481.14 | K109: =SUM(K102:K108) -> 905822.41
C110: Acquisitions, net of cash | G110: 0 | H110: -75000 | I110: -75000 | J110: -100000 | K110: -100000 | M110: Normalized bolt-on M&A based on Western Jet ($33M) and Aero Turbine ($132M) historical cadence; 10-K states company "continually acquiring and investing"
...

Sheet vF with M&A and Prepayment
B2: X | C2: ="Financial Statement Model for "&D5 -> Financial Statement Model for StandardAero
C3: $ in thousands except per share
C5: Company name | D5: StandardAero
C6: Ticker | D6: SARO
D7: 1
C8: Latest closing share price | D8: 25.59
C9: Latest closing share price date | D9: 46119
C10: Latest fiscal year end date | D10: 46022
C11: Shares outstanding (millions) | D11: 334294 | M11: Outstanding at Dec 31, 2025 per 10-K BS. Jan 2026 repurchase of 1,637k shares (subsequent event) reduces to 332,657k.
B13: X | C13: INCOME STATEMENT
C14: Fiscal year | D14: =E14-1 -> 2023 | E14: =F14-1 -> 2024 | F14: =YEAR(D10) -> 2025 | G14: =F14+1 -> 2026 | H14: =G14+1 -> 2027 | I14: =H14+1 -> 2028 | J14: =I14+1 -> 2029 | K14: =J14+1 -> 2030
C15: Fiscal year end date | D15: =EOMONTH(E15,-12) -> 45291 | E15: =EOMONTH(F15,-12) -> 45657 | F15: =D10 -> 46022 | G15: =EOMONTH(F15,12) -> 46387 | H15: =EOMONTH(G15,12) -> 46752 | I15: =EOMONTH(H15,12) -> 47118 | J15: =EOMONTH(I15,12) -> 47483 | K15: =EOMONTH(J15,12) -> 47848 | M15: Comments
C17: Revenue | D17: 4563284 | E17: 5237161 | F17: 6062513 | G17: =F17*(1+G39) -> 6971889.9 | H17: =G17*(1+H39) -> 7878235.6 | I17: =H17*(1+I39) -> 8823623.9 | J17: =I17*(1+J39) -> 9794222.6 | K17: =J17*(1+K39) -> 10773645
C18: Cost of sales | D18: -3927965 | E18: -4483019 | F18: -5165060 | G18: =G19-G17 -> -5912162.7 | H18: =H19-H17 -> -6657109.1 | I18: =I19-I17 -> -7411844.1 | J18: =J19-J17 -> -8197764.3 | K18: =K19-K17 -> -8995993.4
C19: Gross Profit | D19: =SUM(D17:D18) -> 635319 | E19: =SUM(E17:E18) -> 754142 | F19: =SUM(F17:F18) -> 897453 | G19: =G17*G40 -> 1059727.3 | H19: =H17*H40 -> 1221126.5 | I19: =I17*I40 -> 1411779.8 | J19: =J17*J40 -> 1596458.3 | K19: =K17*K40 -> 1777651.4
C20: Amortisation of intangible assets | D20: -93681 | E20: -95457 | F20: -98681 | G20: -91258 | H20: -84535 | I20: -85364 | J20: -84976 | K20: -87197 | M20: IS-line amort only (excl OEM auth amort in COGS). Total amort per Note 9 used for BS reduction in rows 58/59.
C21: Selling, general & administrative | D21: -202766 | E21: -254092 | F21: -247703 | G21: =-G17*G41 -> -285847.49 | H21: =-H17*H41 -> -315129.43 | I21: =-I17*I41 -> -344121.33 | J21: =-J17*J41 -> -372180.46 | K21: =-K17*K41 -> -398624.86
C22: Acquisition Cost | D22: -1514 | E22: -1374 | F22: 0 | G22: =F22 -> 0 | H22: =G22 -> 0 | I22: =H22 -> 0 | J22: =I22 -> 0 | K22: =J22 -> 0
C23: Operating profit (EBIT) | D23: =SUM(D19:D22) -> 337358 | E23: =SUM(E19:E22) -> 403219 | F23: =SUM(F19:F22) -> 551069 | G23: =SUM(G19:G22) -> 682621.78 | H23: =SUM(H19:H22) -> 821462.1 | I23: =SUM(I19:I22) -> 982294.49 | J23: =SUM(J19:J22) -> 1139301.8 | K23: =SUM(K19:K22) -> 1291829.5
C24: Interest income | D24: 0 | E24: 0 | F24: 0 | G24: =G176 -> 0 | H24: =H176 -> 0 | I24: =I176 -> 0 | J24: =J176 -> 0 | K24: =K176 -> 0
C25: Interest expense | D25: -309645 | E25: -282507 | F25: -174217 | G25: =G162 -> -138781.63 | H25: =H162 -> -134154.66 | I25: =I162 -> -126377.68 | J25: =J162 -> -117025.71 | K25: =K162 -> -106098.74
C26: Refinancing costs | D26: -19921 | E26: -23700 | F26: 0 | G26: =F26 -> 0 | H26: =G26 -> 0 | I26: =H26 -> 0 | J26: =I26 -> 0 | K26: =J26 -> 0
C27: Loss on debt extinguishment | D27: -6182 | E27: -15255 | F27: 0 | G27: =F27 -> 0 | H27: =G27 -> 0 | I27: =H27 -> 0 | J27: =I27 -> 0 | K27: =J27 -> 0
C28: Other expense, net | D28: 3509 | E28: 0 | F28: 0 | G28: 0 | H28: 0 | I28: 0 | J28: 0 | K28: 0
C29: Pretax profit | D29: =SUM(D23:D28) -> 5119 | E29: =SUM(E23:E28) -> 81757 | F29: =SUM(F23:F28) -> 376852 | G29: =SUM(G23:G28) -> 543840.16 | H29: =SUM(H23:H28) -> 687307.44 | I29: =SUM(I23:I28) -> 855916.81 | J29: =SUM(J23:J28) -> 1022276.1 | K29: =SUM(K23:K28) -> 1185730.8
C30: Taxes | D30: -40180 | E30: -70783 | F30: -99435 | G30: =-G29*G42 -> -135960.04 | H30: =-H29*H42 -> -171826.86 | I30: =-I29*I42 -> -213979.2 | J30: =-J29*J42 -> -255569.03 | K30: =-K29*K42 -> -296432.7
C31: Net income | D31: =SUM(D29:D30) -> -35061 | E31: =SUM(E29:E30) -> 10974 | F31: =SUM(F29:F30) -> 277417 | G31: =SUM(G29:G30) -> 407880.12 | H31: =SUM(H29:H30) -> 515480.58 | I31: =SUM(I29:I30) -> 641937.61 | J31: =SUM(J29:J30) -> 766707.08 | K31: =SUM(K29:K30) -> 889298.1
C33: Depreciation & amortization | D33: 197104 | E33: 188164 | F33: 193664 | G33: =G132 -> 193183 | H33: =H132 -> 194236.8 | I33: =I132 -> 204408.46 | J33: =J132 -> 214221.6 | K33: =K132 -> 227266.56
C34: EBITDA | D34: =D23+D33 -> 534462 | E34: =E23+E33 -> 591383 | F34: =F23+F33 -> 744733 | G34: =G23+G33 -> 875804.78 | H34: =H23+H33 -> 1015698.9 | I34: =I23+I33 -> 1186703 | J34: =J23+J33 -> 1353523.4 | K34: =K23+K33 -> 1519096.1
C35: Stock based compensation | D35: 0 | E35: 17376 | F35: 13237 | G35: =F35 -> 13237 | H35: =G35 -> 13237 | I35: =H35 -> 13237 | J35: =I35 -> 13237 | K35: =J35 -> 13237
C36: Adjusted EBITDA | D36: =D34+D35 -> 534462 | E36: =E34+E35 -> 608759 | F36: =F34+F35 -> 757970 | G36: =G34+G35 -> 889041.78 | H36: =H34+H35 -> 1028935.9 | I36: =I34+I35 -> 1199940 | J36: =J34+J35 -> 1366760.4 | K36: =K34+K35 -> 1532333.1
C38: Growth rates & margins
C39: Revenue growth | E39: =(E17-D17)/D17 -> 0.14767369 | F39: =(F17-E17)/E17 -> 0.15759531 | G39: 0.15 | H39: 0.13 | I39: 0.12 | J39: 0.11 | K39: 0.1 | M39: LEAP/CFM56 shop visits ramping; ~80% of revenue under long-term agreements; aging installed base drives MRO demand through 2030; military spending elevated due to geopolitical tensions; business aviation fleet growth
C40: Gross profit margin | D40: =D19/D17 -> 0.13922408 | E40: =E19/E17 -> 0.14399825 | F40: =F19/F17 -> 0.14803317 | G40: 0.152 | H40: 0.155 | I40: 0.16 | J40: 0.163 | K40: 0.165 | M40: LEAP learning curve progressively reduces industrialization costs; mix shift toward higher-margin Component Repair Services; operating leverage on fixed overhead as volumes scale; partially offset by material cost inflation pass-through
C41: SG&A % of sales | D41: =-D21/D17 -> 0.044434228 | E41: =-E21/E17 -> 0.048517126 | F41: =-F21/F17 -> 0.040858139 | G41: 0.041 | H41: 0.04 | I41: 0.039 | J41: 0.038 | K41: 0.037 | M41: SG&A already declined to 4.1% in 2025 (from 4.9% in 2024). Post-IPO one-time costs are behind the company. Further leverage expected as revenue scales against relatively fixed corporate overhead and sales force
C42: Tax rate | D42: =-D30/D29 -> 7.8491893 | E42: =-E30/E29 -> 0.86577296 | F42: =-F30/F29 -> 0.2638569 | G42: 0.25 | H42: 0.25 | I42: 0.25 | J42: 0.25 | K42: 0.25 | M42: 2025 effective rate of 26.4% includes GILTI, state taxes (California heavy), and changes in uncertain tax benefits. OBBBA provisions (signed Jul 4, 2025) restore favorable business tax treatment in 2026–2027 rate likely drifts toward 24–26% as Canada/foreign mix optimizes and interest carryforwards begin to release
B44: X | C44: BALANCE SHEET
C45: =C14 -> Fiscal year | D45: =D14 -> 2023 | E45: =E14 -> 2024 | F45: =F14 -> 2025 | G45: =G14 -> 2026 | H45: =H14 -> 2027 | I45: =I14 -> 2028 | J45: =J14 -> 2029 | K45: =K14 -> 2030
C46: =C15 -> Fiscal year end date | D46: =D15 -> 45291 | E46: =E15 -> 45657 | F46: =F15 -> 46022 | G46: =G15 -> 46387 | H46: =H15 -> 46752 | I46: =I15 -> 47118 | J46: =J15 -> 47483 | K46: =K15 -> 47848
C47: ASSETS
C48: Current Assets
C49: Cash & equivalents, ST and LT marketable securities | E49: 102581 | F49: 289717 | G49: =F49+G116 -> 508735.2 | H49: =G49+H116 -> 599746.22 | I49: =H49+I116 -> 806584.72 | J49: =I49+J116 -> 1053967.1 | K49: =J49+K116 -> 1421587.1
C50: Accounts receivable | E50: 580668 | F50: 654390 | G50: =F50*(1+G39) -> 752548.5 | H50: =G50*(1+H39) -> 850379.8 | I50: =H50*(1+I39) -> 952425.38 | J50: =I50*(1+J39) -> 1057192.2 | K50: =J50*(1+K39) -> 1162911.4
C51: Contract Assets | E51: 915200 | F51: 1071703 | G51: =F51*(1+G39) -> 1232458.4 | H51: =G51*(1+H39) -> 1392678 | I51: =H51*(1+I39) -> 1559799.4 | J51: =I51*(1+J39) -> 1731377.3 | K51: =J51*(1+K39) -> 1904515.1
C52: Inventories | E52: 847018 | F52: 827691 | G52: =F52*(1+((G18-F18)/F18)) -> 947412.78 | H52: =G52*(1+((H18-G18)/G18)) -> 1066789 | I52: =H52*(1+((I18-H18)/H18)) -> 1187733.9 | J52: =I52*(1+((J18-I18)/I18)) -> 1313676.1 | K52: =J52*(1+((K18-J18)/J18)) -> 1441590.8
C53: Other current assets | E53: 29707 | F53: 42776 | G53: =F53*(1+G39) -> 49192.4 | H53: =G53*(1+H39) -> 55587.412 | I53: =H53*(1+I39) -> 62257.901 | J53: =I53*(1+J39) -> 69106.271 | K53: =J53*(1+K39) -> 76016.898
C54: Income tax receivable | E54: 9960 | F54: 10182 | G54: =F54 -> 10182 | H54: =G54 -> 10182 | I54: =H54 -> 10182 | J54: =I54 -> 10182 | K54: =J54 -> 10182
C55: Total current assets | E55: =SUM(E49:E54) -> 2485134 | F55: =SUM(F49:F54) -> 2896459 | G55: =SUM(G49:G54) -> 3500529.3 | H55: =SUM(H49:H54) -> 3975362.5 | I55: =SUM(I49:I54) -> 4578983.3 | J55: =SUM(J49:J54) -> 5235501 | K55: =SUM(K49:K54) -> 6016803.3
C56: Property, plant & equipment | E56: 568607 | F56: 579971 | G56: =G125 -> 602971 | H56: =H125 -> 628961 | I56: =I125 -> 658069.8 | J56: =J125 -> 690380.57 | K56: =K125 -> 725922.41
C57: Operating lease right of use asset | E57: 172206 | F57: 222151 | G57: =F57 -> 222151 | H57: =G57 -> 222151 | I57: =H57 -> 222151 | J57: =I57 -> 222151 | K57: =J57 -> 222151
C58: Customer relationships | E58: 1004701 | F58: 920432 | G58: =F58+-77930 -> 842502 | H58: =G58+-42617 -> 799885 | I58: =H58+-42900 -> 756985 | J58: =I58+-32786 -> 724199 | K58: =J58+-34690 -> 689509
C59: Other intangible assets | E59: 291487 | F59: 244877 | G59: =F59+-16493 -> 228384 | H59: =G59+-13531 -> 214853 | I59: =H59+-13689 -> 201164 | J59: =I59+-13626 -> 187538 | K59: =J59+-14686 -> 172852
C60: Goodwill | E60: 1685970 | F60: 1684255 | G60: =F60 -> 1684255 | H60: =G60+45000 -> 1729255 | I60: =H60+45000 -> 1774255 | J60: =I60+60000 -> 1834255 | K60: =J60+60000 -> 1894255 | M60: Goodwill from bolt-on M&A: ~50% of purchase price per historical allocation
C61: Deferred income tax assets | E61: 1079 | F61: 2832 | G61: =F61 -> 2832 | H61: =G61 -> 2832 | I61: =H61 -> 2832 | J61: =I61 -> 2832 | K61: =J61 -> 2832
C62: Other non current assets | E62: 4417 | F62: 6434 | G62: =F62*(1+G39) -> 7399.1 | H62: =G62*(1+H39) -> 8360.983 | I62: =H62*(1+I39) -> 9364.301 | J62: =I62*(1+J39) -> 10394.374 | K62: =J62*(1+K39) -> 11433.811
C63: Total assets | E63: =SUM(E55:E62) -> 6213601 | F63: =SUM(F55:F62) -> 6557411 | G63: =SUM(G55:G62) -> 7091023.4 | H63: =SUM(H55:H62) -> 7581660.5 | I63: =SUM(I55:I62) -> 8203804.4 | J63: =SUM(J55:J62) -> 8907250.9 | K63: =SUM(K55:K62) -> 9735758.5
C64: LIABILITIES AND STOCKHOLDERS' EQUITY
C65: Current Liabilities
C66: Accounts payable | E66: 645701 | F66: 679772 | G66: =F66*(1+(G18-F18)/F18) -> 778097.96 | H66: =G66*(1+(H18-G18)/G18) -> 876140.14 | I66: =H66*(1+(I18-H18)/H18) -> 975470.58 | J66: =I66*(1+(J18-I18)/I18) -> 1078905.3 | K66: =J66*(1+(K18-J18)/J18) -> 1183960
C67: Accrued expenses and other current liabilities | E67: 99572 | F67: 91499 | G67: =F67*(1+G39) -> 105223.85 | H67: =G67*(1+H39) -> 118902.95 | I67: =H67*(1+I39) -> 133171.3 | J67: =I67*(1+J39) -> 147820.15 | K67: =J67*(1+K39) -> 162602.16
C68: Accrued employ costs | E68: 79134 | F68: 74008 | G68: =F68*(1+G39) -> 85109.2 | H68: =G68*(1+H39) -> 96173.396 | I68: =H68*(1+I39) -> 107714.2 | J68: =I68*(1+J39) -> 119562.77 | K68: =J68*(1+K39) -> 131519.04
C69: Operating lease liabilities, current | E69: 17663 | F69: 22308 | G69: =F69 -> 22308 | H69: =G69 -> 22308 | I69: =H69 -> 22308 | J69: =I69 -> 22308 | K69: =J69 -> 22308
C70: Due to related parties | E70: 1345 | F70: 438 | G70: =F70 -> 438 | H70: =G70 -> 438 | I70: =H70 -> 438 | J70: =I70 -> 438 | K70: =J70 -> 438
C71: Contract liabilities | E71: 400025 | F71: 411321 | G71: =F71*(1+G39) -> 473019.15 | H71: =G71*(1+H39) -> 534511.64 | I71: =H71*(1+I39) -> 598653.04 | J71: =I71*(1+J39) -> 664504.87 | K71: =J71*(1+K39) -> 730955.36
C72: Income taxes payable, current | E72: 6655 | F72: 13547 | G72: =F72 -> 13547 | H72: =G72 -> 13547 | I72: =H72 -> 13547 | J72: =I72 -> 13547 | K72: =J72 -> 13547
C73: Long-term debt, current portion | E73: 23449 | F73: 23444 | G73: =F73 -> 23444 | H73: =G73 -> 23444 | I73: =H73 -> 23444 | J73: =I73 -> 23444 | K73: =J73 -> 23444
C74: Total current liabilities | E74: =SUM(E66:E73) -> 1273544 | F74: =SUM(F66:F73) -> 1316337 | G74: =SUM(G66:G73) -> 1501187.2 | H74: =SUM(H66:H73) -> 1685465.1 | I74: =SUM(I66:I73) -> 1874746.1 | J74: =SUM(J66:J73) -> 2070530.1 | K74: =SUM(K66:K73) -> 2268773.6
C75: Long term debt | E75: 2207977 | F75: 2191161 | G75: =F75-F73+G155+G115 -> 2167717 | H75: =G75-G73+H155-G155+H115 -> 2044273 | I75: =H75-H73+I155-H155+I115 -> 1920829 | J75: =I75-I73+J155-I155+J115 -> 1747385 | K75: =J75-J73+K155-J155+K115 -> 1573941
C76: Operating Lease Liabilities Non Current | E76: 164224 | F76: 212365 | G76: =F76 -> 212365 | H76: =G76 -> 212365 | I76: =H76 -> 212365 | J76: =I76 -> 212365 | K76: =J76 -> 212365
C77: Deferred income tax liabilities | E77: 169824 | F77: 157206 | G77: =F77 -> 157206 | H77: =G77 -> 157206 | I77: =H77 -> 157206 | J77: =I77 -> 157206 | K77: =J77 -> 157206
C78: Income tax payable, non-current | E78: 0 | F78: 5770 | G78: =F78 -> 5770 | H78: =G78 -> 5770 | I78: =H78 -> 5770 | J78: =I78 -> 5770 | K78: =J78 -> 5770
C79: Other non current liabilities | E79: 24628 | F79: 7261 | G79: =F79*(1+G39) -> 8350.15 | H79: =G79*(1+H39) -> 9435.6695 | I79: =H79*(1+I39) -> 10567.95 | J79: =I79*(1+J39) -> 11730.424 | K79: =J79*(1+K39) -> 12903.467
C80: Total liabilities | E80: =SUM(E74:E79) -> 3840197 | F80: =SUM(F74:F79) -> 3890100 | G80: =SUM(G74:G79) -> 4052595.3 | H80: =SUM(H74:H79) -> 4114514.8 | I80: =SUM(I74:I79) -> 4181484.1 | J80: =SUM(J74:J79) -> 4204986.5 | K80: =SUM(K74:K79) -> 4230959
C81: Commitments and contingencies | E81: 0 | F81: 0 | G81: 0 | H81: 0 | I81: 0 | J81: 0 | K81: 0
C82: Stockholders Equity:
C83: Common stock | E83: 3345 | F83: 3345 | G83: =F83 -> 3345 | H83: =G83 -> 3345 | I83: =H83 -> 3345 | J83: =I83 -> 3345 | K83: =J83 -> 3345
C84: Preferred stock | E84: 0 | F84: 0 | G84: 0 | H84: 0 | I84: 0 | J84: 0 | K84: 0
C85: Adittional paid-in capital | E85: 3944802 | F85: 3958039 | G85: =F85+G35 -> 3971276 | H85: =G85+H35 -> 3984513 | I85: =H85+I35 -> 3997750 | J85: =I85+J35 -> 4010987 | K85: =J85+K35 -> 4024224
C86: Accumulated deficit | E86: -1563321 | F86: -1285904 | G86: =F86+G31 -> -878023.88 | H86: =G86+H31 -> -362543.3 | I86: =H86+I31 -> 279394.31 | J86: =I86+J31 -> 1046101.4 | K86: =J86+K31 -> 1935399.5
C87: Accumulated other comprehensive loss | E87: -11422 | F87: -8169 | G87: =F87 -> -8169 | H87: =G87 -> -8169 | I87: =H87 -> -8169 | J87: =I87 -> -8169 | K87: =J87 -> -8169
C88: Treasury stock | E88: 0 | F88: 0 | G88: =F88+G112 -> -50000 | H88: =G88+H112 -> -150000 | I88: =H88+I112 -> -250000 | J88: =I88+J112 -> -350000 | K88: =J88+K112 -> -450000
C89: Total equity | E89: =SUM(E83:E88) -> 2373404 | F89: =SUM(F83:F88) -> 2667311 | G89: =SUM(G83:G88) -> 3038428.1 | H89: =SUM(H83:H88) -> 3467145.7 | I89: =SUM(I83:I88) -> 4022320.3 | J89: =SUM(J83:J88) -> 4702264.4 | K89: =SUM(K83:K88) -> 5504799.5
C90: Total liabilities and stockholders' equity | E90: =SUM(E89,E80) -> 6213601 | F90: =SUM(F89,F80) -> 6557411 | G90: =SUM(G89,G80) -> 7091023.4 | H90: =SUM(H89,H80) -> 7581660.5 | I90: =SUM(I89,I80) -> 8203804.4 | J90: =SUM(J89,J80) -> 8907250.9 | K90: =SUM(K89,K80) -> 9735758.5
C92: Balance check | E92: =E63-E90 -> 0 | F92: =F63-F90 -> 0 | G92: =G63-G90 -> 0 | H92: =H63-H90 -> 0 | I92: =I63-I90 -> 0 | J92: =J63-J90 -> 0 | K92: =K63-K90 -> 0
B94: X | C94: CASH FLOW STATEMENT
C95: =C14 -> Fiscal year | G95: =G14 -> 2026 | H95: =H14 -> 2027 | I95: =I14 -> 2028 | J95: =J14 -> 2029 | K95: =K14 -> 2030
C96: =C15 -> Fiscal year end date | G96: =G15 -> 46387 | H96: =H15 -> 46752 | I96: =I15 -> 47118 | J96: =J15 -> 47483 | K96: =K15 -> 47848
C98: Net income | G98: =G31 -> 407880.12 | H98: =H31 -> 515480.58 | I98: =I31 -> 641937.61 | J98: =J31 -> 766707.08 | K98: =K31 -> 889298.1
C99: Depreciation and amortization | G99: =G33 -> 193183 | H99: =H33 -> 194236.8 | I99: =I33 -> 204408.46 | J99: =J33 -> 214221.6 | K99: =K33 -> 227266.56
C100: Stock based compensation | G100: =G35 -> 13237 | H100: =H35 -> 13237 | I100: =I35 -> 13237 | J100: =J35 -> 13237 | K100: =K35 -> 13237
C101: Decreases / (Increases) in working capital assets | G101: =F50+F51+F52+F53-G50-G51-G52-G53 -> -385052.13 | H101: =G50+G51+G52+G53-H50-H51-H52-H53 -> -383822.16 | I101: =H50+H51+H52+H53-I50-I51-I52-I53 -> -396782.27 | J101: =I50+I51+I52+I53-J50-J51-J52-J53 -> -409135.3 | K101: =J50+J51+J52+J53-K50-K51-K52-K53 -> -413682.27
C102: Increases / (Decreases) in working capital liabilities | G102: =G66+G67+G68+G71-F66-F67-F68-F71 -> 184850.16 | H102: =H66+H67+H68+H71-G66-G67-G68-G71 -> 184277.96 | I102: =I66+I67+I68+I71-H66-H67-H68-H71 -> 189281 | J102: =J66+J67+J68+J71-I66-I67-I68-I71 -> 195783.96 | K102: =K66+K67+K68+K71-J66-J67-J68-J71 -> 198243.48
C103: Other non current assets | G103: =-G62+F62 -> -965.1 | H103: =-H62+G62 -> -961.883 | I103: =-I62+H62 -> -1003.318 | J103: =-J62+I62 -> -1030.0731 | K103: =-K62+J62 -> -1039.4374
C104: Other non current liabilities | G104: =G79-F79 -> 1089.15 | H104: =H79-G79 -> 1085.5195 | I104: =I79-H79 -> 1132.2803 | J104: =J79-I79 -> 1162.4745 | K104: =K79-J79 -> 1173.0424
C105: Cash from operating activities | G105: =SUM(G98:G104) -> 414222.2 | H105: =SUM(H98:H104) -> 523533.82 | I105: =SUM(I98:I104) -> 652210.76 | J105: =SUM(J98:J104) -> 780946.73 | K105: =SUM(K98:K104) -> 914496.46
C106: Acquisitions, net of cash | G106: 0 | H106: -75000 | I106: -75000 | J106: -100000 | K106: -100000 | M106: Normalized bolt-on M&A based on Western Jet ($33M) and Aero Turbine ($132M) historical cadence; 10-K states company "continually acquiring and investing"
C107: Capital expenditures | G107: =-G123 -> -94760 | H107: =-H123 -> -107078.8 | I107: =-I123 -> -119928.26 | J107: =-J123 -> -133120.36 | K107: =-K123 -> -146432.4
C108: Cash from investing activities | G108: =G107+G106+G109 -> -121760 | H108: =H107+H106+H109 -> -209078.8 | I108: =I107+I106+I109 -> -221928.26 | J108: =J107+J106+J109 -> -260120.36 | K108: =K107+K106+K109 -> -273432.4
C109: Intangible asset purchases | G109: -27000 | H109: -27000 | I109: -27000 | J109: -27000 | K109: -27000 | M109: OEM authorizations & licenses: 3-yr avg of $27M (2023: $30.2M, 2024: $20.3M, 2025: $30.4M)
C110: Long term debt | G110: =-G73 -> -23444 | H110: =-H73 -> -23444 | I110: =-I73 -> -23444 | J110: =-J73 -> -23444 | K110: =-K73 -> -23444
...

Sheet v3
B2: X | C2: ="Financial Statement Model for "&D5 -> Financial Statement Model for StandardAero
C3: $ in thousands except per share
C5: Company name | D5: StandardAero
C6: Ticker | D6: SARO
D7: 1
C8: Latest closing share price | D8: 25.59
C9: Latest closing share price date | D9: 46119
C10: Latest fiscal year end date | D10: 46022
C11: Shares outstanding (millions) | D11: 334294
B13: X | C13: INCOME STATEMENT
C14: Fiscal year | D14: =E14-1 -> 2023 | E14: =F14-1 -> 2024 | F14: =YEAR(D10) -> 2025 | G14: =F14+1 -> 2026 | H14: =G14+1 -> 2027 | I14: =H14+1 -> 2028 | J14: =I14+1 -> 2029 | K14: =J14+1 -> 2030
C15: Fiscal year end date | D15: =EOMONTH(E15,-12) -> 45291 | E15: =EOMONTH(F15,-12) -> 45657 | F15: =D10 -> 46022 | G15: =EOMONTH(F15,12) -> 46387 | H15: =EOMONTH(G15,12) -> 46752 | I15: =EOMONTH(H15,12) -> 47118 | J15: =EOMONTH(I15,12) -> 47483 | K15: =EOMONTH(J15,12) -> 47848 | M15: Comments
C17: Revenue | D17: 4563284 | E17: 5237161 | F17: 6062513 | G17: =F17*(1+G39) -> 6971889.9 | H17: =G17*(1+H39) -> 7878235.6 | I17: =H17*(1+I39) -> 8823623.9 | J17: =I17*(1+J39) -> 9794222.6 | K17: =J17*(1+K39) -> 10773645
C18: Cost of sales | D18: -3927965 | E18: -4483019 | F18: -5165060 | G18: =G19-G17 -> -5912162.7 | H18: =H19-H17 -> -6657109.1 | I18: =I19-I17 -> -7411844.1 | J18: =J19-J17 -> -8197764.3 | K18: =K19-K17 -> -8995993.4
C19: Gross Profit | D19: =SUM(D17:D18) -> 635319 | E19: =SUM(E17:E18) -> 754142 | F19: =SUM(F17:F18) -> 897453 | G19: =G17*G40 -> 1059727.3 | H19: =H17*H40 -> 1221126.5 | I19: =I17*I40 -> 1411779.8 | J19: =J17*J40 -> 1596458.3 | K19: =K17*K40 -> 1777651.4
C20: Amortisation of intangible assets | D20: -93681 | E20: -95457 | F20: -98681 | G20: -91258 | H20: -83535 | I20: -82364 | J20: -79976 | K20: -79197
C21: Selling, general & administrative | D21: -202766 | E21: -254092 | F21: -247703 | G21: =-G17*G41 -> -285847.49 | H21: =-H17*H41 -> -315129.43 | I21: =-I17*I41 -> -344121.33 | J21: =-J17*J41 -> -372180.46 | K21: =-K17*K41 -> -398624.86
C22: Acquisition Cost | D22: -1514 | E22: -1374 | F22: 0 | G22: =F22 -> 0 | H22: =G22 -> 0 | I22: =H22 -> 0 | J22: =I22 -> 0 | K22: =J22 -> 0
C23: Operating profit (EBIT) | D23: =SUM(D19:D22) -> 337358 | E23: =SUM(E19:E22) -> 403219 | F23: =SUM(F19:F22) -> 551069 | G23: =SUM(G19:G22) -> 682621.78 | H23: =SUM(H19:H22) -> 822462.1 | I23: =SUM(I19:I22) -> 985294.49 | J23: =SUM(J19:J22) -> 1144301.8 | K23: =SUM(K19:K22) -> 1299829.5
C24: Interest income | D24: 0 | E24: 0 | F24: 0 | G24: 0 | H24: 0 | I24: 0 | J24: 0 | K24: 0
C25: Interest expense | D25: -309645 | E25: -282507 | F25: -174217 | G25: =G162 -> -138781.63 | H25: =H162 -> -137304.66 | I25: =I162 -> -135827.68 | J25: =J162 -> -134350.71 | K25: =K162 -> -132873.74
C26: Refinancing costs | D26: -19921 | E26: -23700 | F26: 0 | G26: =F26 -> 0 | H26: =G26 -> 0 | I26: =H26 -> 0 | J26: =I26 -> 0 | K26: =J26 -> 0
C27: Loss on debt extinguishment | D27: -6182 | E27: -15255 | F27: 0 | G27: =F27 -> 0 | H27: =G27 -> 0 | I27: =H27 -> 0 | J27: =I27 -> 0 | K27: =J27 -> 0
C28: Other expense, net | D28: 3509 | E28: 0 | F28: 0 | G28: 0 | H28: 0 | I28: 0 | J28: 0 | K28: 0
C29: Pretax profit | D29: =SUM(D23:D28) -> 5119 | E29: =SUM(E23:E28) -> 81757 | F29: =SUM(F23:F28) -> 376852 | G29: =SUM(G23:G28) -> 543840.16 | H29: =SUM(H23:H28) -> 685157.44 | I29: =SUM(I23:I28) -> 849466.81 | J29: =SUM(J23:J28) -> 1009951.1 | K29: =SUM(K23:K28) -> 1166955.8
C30: Taxes | D30: -40180 | E30: -70783 | F30: -99435 | G30: =-G29*G42 -> -135960.04 | H30: =-H29*H42 -> -171289.36 | I30: =-I29*I42 -> -212366.7 | J30: =-J29*J42 -> -252487.78 | K30: =-K29*K42 -> -291738.95
C31: Net income | D31: =SUM(D29:D30) -> -35061 | E31: =SUM(E29:E30) -> 10974 | F31: =SUM(F29:F30) -> 277417 | G31: =SUM(G29:G30) -> 407880.12 | H31: =SUM(H29:H30) -> 513868.08 | I31: =SUM(I29:I30) -> 637100.11 | J31: =SUM(J29:J30) -> 757463.33 | K31: =SUM(K29:K30) -> 875216.85
C33: Depreciation & amortization | D33: 197104 | E33: 188164 | F33: 193664 | G33: =G132 -> 193183 | H33: =H132 -> 192236.8 | I33: =I132 -> 200408.46 | J33: =J132 -> 207221.6 | K33: =K132 -> 216266.56
C34: EBITDA | D34: =D23+D33 -> 534462 | E34: =E23+E33 -> 591383 | F34: =F23+F33 -> 744733 | G34: =G23+G33 -> 875804.78 | H34: =H23+H33 -> 1014698.9 | I34: =I23+I33 -> 1185703 | J34: =J23+J33 -> 1351523.4 | K34: =K23+K33 -> 1516096.1
C35: Stock based compensation | D35: 0 | E35: 17376 | F35: 13237 | G35: 13500 | H35: 14000 | I35: 14500 | J35: 15000 | K35: 15500
C36: Adjusted EBITDA | D36: =D34+D35 -> 534462 | E36: =E34+E35 -> 608759 | F36: =F34+F35 -> 757970 | G36: =G34+G35 -> 889304.78 | H36: =H34+H35 -> 1028698.9 | I36: =I34+I35 -> 1200203 | J36: =J34+J35 -> 1366523.4 | K36: =K34+K35 -> 1531596.1
C38: Growth rates & margins
C39: Revenue growth | E39: =(E17-D17)/D17 -> 0.14767369 | F39: =(F17-E17)/E17 -> 0.15759531 | G39: 0.15 | H39: 0.13 | I39: 0.12 | J39: 0.11 | K39: 0.1 | M39: LEAP/CFM56 shop visits ramping; ~80% of revenue under long-term agreements; aging installed base drives MRO demand through 2030; military spending elevated due to geopolitical tensions; business aviation fleet growth
C40: Gross profit margin | D40: =D19/D17 -> 0.13922408 | E40: =E19/E17 -> 0.14399825 | F40: =F19/F17 -> 0.14803317 | G40: 0.152 | H40: 0.155 | I40: 0.16 | J40: 0.163 | K40: 0.165 | M40: LEAP learning curve progressively reduces industrialization costs; mix shift toward higher-margin Component Repair Services; operating leverage on fixed overhead as volumes scale; partially offset by material cost inflation pass-through
C41: SG&A % of sales | D41: =-D21/D17 -> 0.044434228 | E41: =-E21/E17 -> 0.048517126 | F41: =-F21/F17 -> 0.040858139 | G41: 0.041 | H41: 0.04 | I41: 0.039 | J41: 0.038 | K41: 0.037 | M41: SG&A already declined to 4.1% in 2025 (from 4.9% in 2024). Post-IPO one-time costs are behind the company. Further leverage expected as revenue scales against relatively fixed corporate overhead and sales force
C42: Tax rate | D42: =-D30/D29 -> 7.8491893 | E42: =-E30/E29 -> 0.86577296 | F42: =-F30/F29 -> 0.2638569 | G42: 0.25 | H42: 0.25 | I42: 0.25 | J42: 0.25 | K42: 0.25 | M42: 2025 effective rate of 26.4% includes GILTI, state taxes (California heavy), and changes in uncertain tax benefits. OBBBA provisions (signed Jul 4, 2025) restore favorable business tax treatment in 2026–2027 — rate likely drifts toward 24–26% as Canada/foreign mix optimizes and interest carryforwards begin to release
B44: X | C44: BALANCE SHEET
C45: =C14 -> Fiscal year | D45: =D14 -> 2023 | E45: =E14 -> 2024 | F45: =F14 -> 2025 | G45: =G14 -> 2026 | H45: =H14 -> 2027 | I45: =I14 -> 2028 | J45: =J14 -> 2029 | K45: =K14 -> 2030
C46: =C15 -> Fiscal year end date | D46: =D15 -> 45291 | E46: =E15 -> 45657 | F46: =F15 -> 46022 | G46: =G15 -> 46387 | H46: =H15 -> 46752 | I46: =I15 -> 47118 | J46: =J15 -> 47483 | K46: =K15 -> 47848
C47: ASSETS
C48: Current Assets
C49: Cash & equivalents, ST and LT marketable securities | E49: 102581 | F49: 289717 | G49: =F49+G116 -> 585998.2 | H49: =G49+H116 -> 976159.72 | I49: =H49+I116 -> 1477423.7 | J49: =I49+J116 -> 2087325.3 | K49: =J49+K116 -> 2809127.1
C50: Accounts receivable | E50: 580668 | F50: 654390 | G50: =F50*(1+G39) -> 752548.5 | H50: =G50*(1+H39) -> 850379.8 | I50: =H50*(1+I39) -> 952425.38 | J50: =I50*(1+J39) -> 1057192.2 | K50: =J50*(1+K39) -> 1162911.4
C51: Contract Assets | E51: 915200 | F51: 1071703 | G51: =F51*(1+G39) -> 1232458.4 | H51: =G51*(1+H39) -> 1392678 | I51: =H51*(1+I39) -> 1559799.4 | J51: =I51*(1+J39) -> 1731377.3 | K51: =J51*(1+K39) -> 1904515.1
C52: Inventories | E52: 847018 | F52: 827691 | G52: =F52*(1+((G18-F18)/F18)) -> 947412.78 | H52: =G52*(1+((H18-G18)/G18)) -> 1066789 | I52: =H52*(1+((I18-H18)/H18)) -> 1187733.9 | J52: =I52*(1+((J18-I18)/I18)) -> 1313676.1 | K52: =J52*(1+((K18-J18)/J18)) -> 1441590.8
C53: Other current assets | E53: 29707 | F53: 42776 | G53: =F53*(1+G39) -> 49192.4 | H53: =G53*(1+H39) -> 55587.412 | I53: =H53*(1+I39) -> 62257.901 | J53: =I53*(1+J39) -> 69106.271 | K53: =J53*(1+K39) -> 76016.898
C54: Income tax receivable | E54: 9960 | F54: 10182 | G54: =F54 -> 10182 | H54: =G54 -> 10182 | I54: =H54 -> 10182 | J54: =I54 -> 10182 | K54: =J54 -> 10182
C55: Total current assets | E55: =SUM(E49:E54) -> 2485134 | F55: =SUM(F49:F54) -> 2896459 | G55: =SUM(G49:G54) -> 3577792.3 | H55: =SUM(H49:H54) -> 4351776 | I55: =SUM(I49:I54) -> 5249822.3 | J55: =SUM(J49:J54) -> 6268859.2 | K55: =SUM(K49:K54) -> 7404343.3
C56: Property, plant & equipment | E56: 568607 | F56: 579971 | G56: =G125 -> 602971 | H56: =H125 -> 628961 | I56: =I125 -> 658069.8 | J56: =J125 -> 690380.57 | K56: =K125 -> 725922.41
C57: Operating lease right of use asset | E57: 172206 | F57: 222151 | G57: =F57 -> 222151 | H57: =G57 -> 222151 | I57: =H57 -> 222151 | J57: =I57 -> 222151 | K57: =J57 -> 222151
C58: Customer relationships | E58: 1004701 | F58: 920432 | G58: =F58+-77930 -> 842502 | H58: =G58+-71335 -> 771167 | I58: =H58+-70335 -> 700832 | J58: =I58+-68296 -> 632536 | K58: =J58+-67631 -> 564905
C59: Other intangible assets | E59: 291487 | F59: 244877 | G59: =F59+-43493 -> 201384 | H59: =G59+-39813 -> 161571 | I59: =H59+-39254 -> 122317 | J59: =I59+-38116 -> 84201 | K59: =J59+-37745 -> 46456
C60: Goodwill | E60: 1685970 | F60: 1684255 | G60: =F60 -> 1684255 | H60: =G60 -> 1684255 | I60: =H60 -> 1684255 | J60: =I60 -> 1684255 | K60: =J60 -> 1684255
C61: Deferred income tax assets | E61: 1079 | F61: 2832 | G61: =F61 -> 2832 | H61: =G61 -> 2832 | I61: =H61 -> 2832 | J61: =I61 -> 2832 | K61: =J61 -> 2832
C62: Other non current assets | E62: 4417 | F62: 6434 | G62: =F62*(1+G39) -> 7399.1 | H62: =G62*(1+H39) -> 8360.983 | I62: =H62*(1+I39) -> 9364.301 | J62: =I62*(1+J39) -> 10394.374 | K62: =J62*(1+K39) -> 11433.811
C63: Total assets | E63: =SUM(E55:E62) -> 6213601 | F63: =SUM(F55:F62) -> 6557411 | G63: =SUM(G55:G62) -> 7141286.4 | H63: =SUM(H55:H62) -> 7831074 | I63: =SUM(I55:I62) -> 8649643.4 | J63: =SUM(J55:J62) -> 9595609.1 | K63: =SUM(K55:K62) -> 10662299
C64: LIABILITIES AND STOCKHOLDERS' EQUITY
C65: Current Liabilities
C66: Accounts payable | E66: 645701 | F66: 679772 | G66: =F66*(1+(G18-F18)/F18) -> 778097.96 | H66: =G66*(1+(H18-G18)/G18) -> 876140.14 | I66: =H66*(1+(I18-H18)/H18) -> 975470.58 | J66: =I66*(1+(J18-I18)/I18) -> 1078905.3 | K66: =J66*(1+(K18-J18)/J18) -> 1183960
C67: Accrued expenses and other current liabilities | E67: 99572 | F67: 91499 | G67: =F67*(1+G39) -> 105223.85 | H67: =G67*(1+H39) -> 118902.95 | I67: =H67*(1+I39) -> 133171.3 | J67: =I67*(1+J39) -> 147820.15 | K67: =J67*(1+K39) -> 162602.16
C68: Accrued employ costs | E68: 79134 | F68: 74008 | G68: =F68*(1+G39) -> 85109.2 | H68: =G68*(1+H39) -> 96173.396 | I68: =H68*(1+I39) -> 107714.2 | J68: =I68*(1+J39) -> 119562.77 | K68: =J68*(1+K39) -> 131519.04
C69: Operating lease liabilities, current | E69: 17663 | F69: 22308 | G69: =F69 -> 22308 | H69: =G69 -> 22308 | I69: =H69 -> 22308 | J69: =I69 -> 22308 | K69: =J69 -> 22308
C70: Due to related parties | E70: 1345 | F70: 438 | G70: =F70 -> 438 | H70: =G70 -> 438 | I70: =H70 -> 438 | J70: =I70 -> 438 | K70: =J70 -> 438
C71: Contract liabilities | E71: 400025 | F71: 411321 | G71: =F71*(1+G39) -> 473019.15 | H71: =G71*(1+H39) -> 534511.64 | I71: =H71*(1+I39) -> 598653.04 | J71: =I71*(1+J39) -> 664504.87 | K71: =J71*(1+K39) -> 730955.36
C72: Income taxes payable, current | E72: 6655 | F72: 13547 | G72: =F72 -> 13547 | H72: =G72 -> 13547 | I72: =H72 -> 13547 | J72: =I72 -> 13547 | K72: =J72 -> 13547
C73: Long-term debt, current portion | E73: 23449 | F73: 23444 | G73: =F73 -> 23444 | H73: =G73 -> 23444 | I73: =H73 -> 23444 | J73: =I73 -> 23444 | K73: =J73 -> 23444
C74: Total current liabilities | E74: =SUM(E66:E73) -> 1273544 | F74: =SUM(F66:F73) -> 1316337 | G74: =SUM(G66:G73) -> 1501187.2 | H74: =SUM(H66:H73) -> 1685465.1 | I74: =SUM(I66:I73) -> 1874746.1 | J74: =SUM(J66:J73) -> 2070530.1 | K74: =SUM(K66:K73) -> 2268773.6
C75: Long term debt | E75: 2207977 | F75: 2191161 | G75: =F75-F73+G155 -> 2167717 | H75: =G75-G73+H155-G155 -> 2144273 | I75: =H75-H73+I155-H155 -> 2120829 | J75: =I75-I73+J155-I155 -> 2097385 | K75: =J75-J73+K155-J155 -> 2073941
C76: Operating Lease Liabilities Non Current | E76: 164224 | F76: 212365 | G76: =F76 -> 212365 | H76: =G76 -> 212365 | I76: =H76 -> 212365 | J76: =I76 -> 212365 | K76: =J76 -> 212365
C77: Deferred income tax liabilities | E77: 169824 | F77: 157206 | G77: =F77 -> 157206 | H77: =G77 -> 157206 | I77: =H77 -> 157206 | J77: =I77 -> 157206 | K77: =J77 -> 157206
C78: Income tax payable, non-current | E78: 0 | F78: 5770 | G78: =F78 -> 5770 | H78: =G78 -> 5770 | I78: =H78 -> 5770 | J78: =I78 -> 5770 | K78: =J78 -> 5770
C79: Other non current liabilities | E79: 24628 | F79: 7261 | G79: =F79*(1+G39) -> 8350.15 | H79: =G79*(1+H39) -> 9435.6695 | I79: =H79*(1+I39) -> 10567.95 | J79: =I79*(1+J39) -> 11730.424 | K79: =J79*(1+K39) -> 12903.467
C80: Total liabilities | E80: =SUM(E74:E79) -> 3840197 | F80: =SUM(F74:F79) -> 3890100 | G80: =SUM(G74:G79) -> 4052595.3 | H80: =SUM(H74:H79) -> 4214514.8 | I80: =SUM(I74:I79) -> 4381484.1 | J80: =SUM(J74:J79) -> 4554986.5 | K80: =SUM(K74:K79) -> 4730959
C81: Commitments and contingencies | E81: 0 | F81: 0 | G81: 0 | H81: 0 | I81: 0 | J81: 0 | K81: 0
C82: Stockholders Equity:
C83: Common stock | E83: 3345 | F83: 3345 | G83: =F83 -> 3345 | H83: =G83 -> 3345 | I83: =H83 -> 3345 | J83: =I83 -> 3345 | K83: =J83 -> 3345
C84: Preferred stock | E84: 0 | F84: 0 | G84: 0 | H84: 0 | I84: 0 | J84: 0 | K84: 0
C85: Adittional paid-in capital | E85: 3944802 | F85: 3958039 | G85: =F85+G35 -> 3971539 | H85: =G85+H35 -> 3985539 | I85: =H85+I35 -> 4000039 | J85: =I85+J35 -> 4015039 | K85: =J85+K35 -> 4030539
C86: Accumulated deficit | E86: -1563321 | F86: -1285904 | G86: =F86+G31 -> -878023.88 | H86: =G86+H31 -> -364155.8 | I86: =H86+I31 -> 272944.31 | J86: =I86+J31 -> 1030407.6 | K86: =J86+K31 -> 1905624.5
C87: Accumulated other comprehensive loss | E87: -11422 | F87: -8169 | G87: =F87 -> -8169 | H87: =G87 -> -8169 | I87: =H87 -> -8169 | J87: =I87 -> -8169 | K87: =J87 -> -8169
C88: Treasury stock | E88: 0 | F88: 0 | G88: 0 | H88: 0 | I88: 0 | J88: 0 | K88: 0
C89: Total equity | E89: =SUM(E83:E88) -> 2373404 | F89: =SUM(F83:F88) -> 2667311 | G89: =SUM(G83:G88) -> 3088691.1 | H89: =SUM(H83:H88) -> 3616559.2 | I89: =SUM(I83:I88) -> 4268159.3 | J89: =SUM(J83:J88) -> 5040622.6 | K89: =SUM(K83:K88) -> 5931339.5
C90: Total liabilities and stockholders' equity | E90: =SUM(E89,E80) -> 6213601 | F90: =SUM(F89,F80) -> 6557411 | G90: =SUM(G89,G80) -> 7141286.4 | H90: =SUM(H89,H80) -> 7831074 | I90: =SUM(I89,I80) -> 8649643.4 | J90: =SUM(J89,J80) -> 9595609.1 | K90: =SUM(K89,K80) -> 10662299
C92: Balance check | E92: =E63-E90 -> 0 | F92: =F63-F90 -> 0 | G92: =G63-G90 -> 0 | H92: =H63-H90 -> 0 | I92: =I63-I90 -> 0 | J92: =J63-J90 -> 0 | K92: =K63-K90 -> 0
B94: X | C94: CASH FLOW STATEMENT
C95: =C14 -> Fiscal year | G95: =G14 -> 2026 | H95: =H14 -> 2027 | I95: =I14 -> 2028 | J95: =J14 -> 2029 | K95: =K14 -> 2030
C96: =C15 -> Fiscal year end date | G96: =G15 -> 46387 | H96: =H15 -> 46752 | I96: =I15 -> 47118 | J96: =J15 -> 47483 | K96: =K15 -> 47848
C98: Net income | G98: =G31 -> 407880.12 | H98: =H31 -> 513868.08 | I98: =I31 -> 637100.11 | J98: =J31 -> 757463.33 | K98: =K31 -> 875216.85
C99: Depreciation and amortization | G99: =G33 -> 193183 | H99: =H33 -> 192236.8 | I99: =I33 -> 200408.46 | J99: =J33 -> 207221.6 | K99: =K33 -> 216266.56
C100: Stock based compensation | G100: =G35 -> 13500 | H100: =H35 -> 14000 | I100: =I35 -> 14500 | J100: =J35 -> 15000 | K100: =K35 -> 15500
C101: Decreases / (Increases) in working capital assets | G101: =F50+F51+F52+F53-G50-G51-G52-G53 -> -385052.13 | H101: =G50+G51+G52+G53-H50-H51-H52-H53 -> -383822.16 | I101: =H50+H51+H52+H53-I50-I51-I52-I53 -> -396782.27 | J101: =I50+I51+I52+I53-J50-J51-J52-J53 -> -409135.3 | K101: =J50+J51+J52+J53-K50-K51-K52-K53 -> -413682.27
C102: Increases / (Decreases) in working capital liabilities | G102: =G66+G67+G68+G71-F66-F67-F68-F71 -> 184850.16 | H102: =H66+H67+H68+H71-G66-G67-G68-G71 -> 184277.96 | I102: =I66+I67+I68+I71-H66-H67-H68-H71 -> 189281 | J102: =J66+J67+J68+J71-I66-I67-I68-I71 -> 195783.96 | K102: =K66+K67+K68+K71-J66-J67-J68-J71 -> 198243.48
C103: Other non current assets | G103: =-G62+F62 -> -965.1 | H103: =-H62+G62 -> -961.883 | I103: =-I62+H62 -> -1003.318 | J103: =-J62+I62 -> -1030.0731 | K103: =-K62+J62 -> -1039.4374
C104: Other non current liabilities | G104: =G79-F79 -> 1089.15 | H104: =H79-G79 -> 1085.5195 | I104: =I79-H79 -> 1132.2803 | J104: =J79-I79 -> 1162.4745 | K104: =K79-J79 -> 1173.0424
C105: Cash from operating activities | G105: =SUM(G98:G104) -> 414485.2 | H105: =SUM(H98:H104) -> 520684.32 | I105: =SUM(I98:I104) -> 644636.26 | J105: =SUM(J98:J104) -> 766465.98 | K105: =SUM(K98:K104) -> 891678.21
C107: Capital expenditures | G107: =-G123 -> -94760 | H107: =-H123 -> -107078.8 | I107: =-I123 -> -119928.26 | J107: =-J123 -> -133120.36 | K107: =-K123 -> -146432.4
C108: Cash from investing activities | G108: =G107 -> -94760 | H108: =H107 -> -107078.8 | I108: =I107 -> -119928.26 | J108: =J107 -> -133120.36 | K108: =K107 -> -146432.4
C110: Long term debt | G110: =-G73 -> -23444 | H110: =-H73 -> -23444 | I110: =-I73 -> -23444 | J110: =-J73 -> -23444 | K110: =-K73 -> -23444
C111: Revolver | G111: 0 | H111: 0 | I111: 0 | J111: 0 | K111: 0
C112: Share repurchases | G112: 0 | H112: 0 | I112: 0 | J112: 0 | K112: 0
...

Sheet Sheet1
C2: ="Financial Statement Model for "&D5 -> Financial Statement Model for StandardAero
C3: $ in thousands except per share
C5: Company name | D5: StandardAero
C6: Ticker | D6: SARO
D7: 1
C8: Latest closing share price | D8: 25.59
C9: Latest closing share price date | D9: 46119
C10: Latest fiscal year end date | D10: 46022
C11: Shares outstanding (millions) | D11: 334321
C13: INCOME STATEMENT
C14: Fiscal year | D14: =E14-1 -> 2023 | E14: =F14-1 -> 2024 | F14: =YEAR(D10) -> 2025 | G14: =F14+1 -> 2026 | H14: =G14+1 -> 2027 | I14: =H14+1 -> 2028 | J14: =I14+1 -> 2029 | K14: =J14+1 -> 2030
C15: Fiscal year end date | D15: =EOMONTH(E15,-12) -> 45291 | E15: =EOMONTH(F15,-12) -> 45657 | F15: =D10 -> 46022 | G15: =EOMONTH(F15,12) -> 46387 | H15: =EOMONTH(G15,12) -> 46752 | I15: =EOMONTH(H15,12) -> 47118 | J15: =EOMONTH(I15,12) -> 47483 | K15: =EOMONTH(J15,12) -> 47848 | M15: Comments
C17: Revenue | D17: 4563284 | E17: 5237161 | F17: 6062513 | G17: =F17*(1+G39) -> 6971889.9 | H17: =G17*(1+H39) -> 7878235.6 | I17: =H17*(1+I39) -> 8823623.9 | J17: =I17*(1+J39) -> 9794222.6 | K17: =J17*(1+K39) -> 10773645
C18: Cost of sales | D18: -3927965 | E18: -4483019 | F18: =-5165060 -> -5165060 | G18: =G19-G17 -> -5912162.7 | H18: =H19-H17 -> -6657109.1 | I18: =I19-I17 -> -7411844.1 | J18: =J19-J17 -> -8197764.3 | K18: =K19-K17 -> -8995993.4
C19: Gross Profit | D19: =SUM(D17:D18) -> 635319 | E19: =SUM(E17:E18) -> 754142 | F19: =SUM(F17:F18) -> 897453 | G19: =G17*G40 -> 1059727.3 | H19: =H17*H40 -> 1221126.5 | I19: =I17*I40 -> 1411779.8 | J19: =J17*J40 -> 1596458.3 | K19: =K17*K40 -> 1777651.4
C20: Amortisation of intangible assets | D20: -93681 | E20: -95457 | F20: -98681 | G20: -121400 | H20: -111100 | I20: -109600 | J20: -106400 | K20: -105400 | M20: Given in 10k
C21: Selling, general & administrative | D21: -202766 | E21: -254092 | F21: -247703 | G21: =-G17*G41 -> -285847.49 | H21: =-H17*H41 -> -315129.43 | I21: =-I17*I41 -> -344121.33 | J21: =-J17*J41 -> -372180.46 | K21: =-K17*K41 -> -398624.86
C22: Acquisition Cost | D22: -1514 | E22: -1374 | F22: 0 | G22: =F22 -> 0 | H22: =G22 -> 0 | I22: =H22 -> 0 | J22: =I22 -> 0 | K22: =J22 -> 0
C23: Operating profit (EBIT) | D23: =SUM(D19:D22) -> 337358 | E23: =SUM(E19:E22) -> 403219 | F23: =SUM(F19:F22) -> 551069 | G23: =SUM(G19:G22) -> 652479.78 | H23: =SUM(H19:H22) -> 794897.1 | I23: =SUM(I19:I22) -> 958058.49 | J23: =SUM(J19:J22) -> 1117877.8 | K23: =SUM(K19:K22) -> 1273626.5
C24: Interest income | D24: 0 | E24: 0 | F24: 0 | G24: 0 | H24: 0 | I24: 0 | J24: 0 | K24: 0 | M24: Reference from interest on cash schedule
C25: Interest expense | D25: -309645 | E25: -282507 | F25: -174217 | M25: Reference from interest expense schedule
C26: Refinancing costs | D26: -19921 | E26: -23700 | F26: 0 | G26: =F26 -> 0 | H26: =G26 -> 0 | I26: =H26 -> 0 | J26: =I26 -> 0 | K26: =J26 -> 0
C27: Loss on debt extinguishment | D27: -6182 | E27: -15255 | F27: 0 | G27: =F27 -> 0 | H27: =G27 -> 0 | I27: =H27 -> 0 | J27: =I27 -> 0 | K27: =J27 -> 0
C28: Other expense, net | D28: 3509 | E28: 0 | F28: 0 | G28: 0 | H28: 0 | I28: 0 | J28: 0 | K28: 0
C29: Pretax profit | D29: =SUM(D23:D28) -> 5119 | E29: =SUM(E23:E28) -> 81757 | F29: =SUM(F23:F28) -> 376852 | G29: =SUM(G23:G28) -> 652479.78 | H29: =SUM(H23:H28) -> 794897.1 | I29: =SUM(I23:I28) -> 958058.49 | J29: =SUM(J23:J28) -> 1117877.8 | K29: =SUM(K23:K28) -> 1273626.5
C30: Taxes | D30: -40180 | E30: =-70783 -> -70783 | F30: -99435 | G30: =-G29*G42 -> -163119.95 | H30: =-H29*H42 -> -198724.27 | I30: =-I29*I42 -> -239514.62 | J30: =-J29*J42 -> -279469.45 | K30: =-K29*K42 -> -318406.63
C31: Net income | D31: =SUM(D29:D30) -> -35061 | E31: =SUM(E29:E30) -> 10974 | F31: =SUM(F29:F30) -> 277417 | G31: =SUM(G29:G30) -> 489359.84 | H31: =SUM(H29:H30) -> 596172.82 | I31: =SUM(I29:I30) -> 718543.87 | J31: =SUM(J29:J30) -> 838408.36 | K31: =SUM(K29:K30) -> 955219.9
C33: Depreciation & amortization | D33: 197104 | E33: 187080 | F33: 193664 | G33: =G132 -> 216229.61 | H33: =H132 -> 214550.49 | I33: =I132 -> 217360.92 | J33: =J132 -> 218471.36 | K33: =K132 -> 217471.36
C34: EBITDA | D34: =D23+D33 -> 534462 | E34: =E23+E33 -> 590299 | F34: =F23+F33 -> 744733 | G34: =G23+G33 -> 868709.4 | H34: =H23+H33 -> 1009447.6 | I34: =I23+I33 -> 1175419.4 | J34: =J23+J33 -> 1336349.2 | K34: =K23+K33 -> 1491097.9
C35: Stock based compensation | D35: -6182 | E35: -15255 | F35: 0 | G35: 0 | H35: 0 | I35: 0 | J35: 0 | K35: 0
C36: Adjusted EBITDA | D36: =D34+D35 -> 528280 | E36: =E34+E35 -> 575044 | F36: =F34+F35 -> 744733 | G36: =G34+G35 -> 868709.4 | H36: =H34+H35 -> 1009447.6 | I36: =I34+I35 -> 1175419.4 | J36: =J34+J35 -> 1336349.2 | K36: =K34+K35 -> 1491097.9
C38: Growth rates & margins
C39: Revenue growth | E39: =(E17-D17)/D17 -> 0.14767369 | F39: =(F17-E17)/E17 -> 0.15759531 | G39: 0.15 | H39: 0.13 | I39: 0.12 | J39: 0.11 | K39: 0.1 | M39: LEAP/CFM56 shop visits ramping; ~80% of revenue under long-term agreements; aging installed base drives MRO demand through 2030; military spending elevated due to geopolitical tensions; business aviation fleet growth
C40: Gross profit margin | D40: =D19/D17 -> 0.13922408 | E40: =E19/E17 -> 0.14399825 | F40: =F19/F17 -> 0.14803317 | G40: 0.152 | H40: 0.155 | I40: 0.16 | J40: 0.163 | K40: 0.165 | M40: LEAP learning curve progressively reduces industrialization costs; mix shift toward higher-margin Component Repair Services; operating leverage on fixed overhead as volumes scale; partially offset by material cost inflation pass-through
C41: SG&A % of sales | D41: =-D21/D17 -> 0.044434228 | E41: =-E21/E17 -> 0.048517126 | F41: =-F21/F17 -> 0.040858139 | G41: 0.041 | H41: 0.04 | I41: 0.039 | J41: 0.038 | K41: 0.037 | M41: SG&A already declined to 4.1% in 2025 (from 4.9% in 2024). Post-IPO one-time costs are behind the company. Further leverage expected as revenue scales against relatively fixed corporate overhead and sales force
C42: Tax rate | D42: =-D30/D29 -> 7.8491893 | E42: =-E30/E29 -> 0.86577296 | F42: =-F30/F29 -> 0.2638569 | G42: 0.25 | H42: 0.25 | I42: 0.25 | J42: 0.25 | K42: 0.25 | M42: 2025 effective rate of 26.4% includes GILTI, state taxes (California heavy), and changes in uncertain tax benefits. OBBBA provisions (signed Jul 4, 2025) restore favorable business tax treatment in 2026–2027 — rate likely drifts toward 24–26% as Canada/foreign mix optimizes and interest carryforwards begin to release
C44: BALANCE SHEET
C45: =C14 -> Fiscal year | E45: =E14 -> 2024 | F45: =F14 -> 2025 | G45: =G14 -> 2026 | H45: =H14 -> 2027 | I45: =I14 -> 2028 | J45: =J14 -> 2029 | K45: =K14 -> 2030
C46: =C15 -> Fiscal year end date | E46: =E15 -> 45657 | F46: =F15 -> 46022 | G46: =G15 -> 46387 | H46: =H15 -> 46752 | I46: =I15 -> 47118 | J46: =J15 -> 47483 | K46: =K15 -> 47848
C47: ASSETS
C48: Current Assets
C49: Cash & equivalents, ST and LT marketable securities | E49: 102581 | F49: 289717 | G49: =F49+G116 -> 100000 | H49: =G49+H116 -> 100000 | I49: =H49+I116 -> 100000 | J49: =I49+J116 -> 100000 | K49: =J49+K116 -> 100000
C50: Accounts receivable | E50: 580668 | F50: 654390 | G50: =F50*(1+G39) -> 752548.5 | H50: =G50*(1+H39) -> 850379.8 | I50: =H50*(1+I39) -> 952425.38 | J50: =I50*(1+J39) -> 1057192.2 | K50: =J50*(1+K39) -> 1162911.4
C51: Contract Assets | E51: 915200 | F51: 1071703 | G51: =F51*(1+G39) -> 1232458.4 | H51: =G51*(1+H39) -> 1392678 | I51: =H51*(1+I39) -> 1559799.4 | J51: =I51*(1+J39) -> 1731377.3 | K51: =J51*(1+K39) -> 1904515.1
C52: Inventories | E52: 847018 | F52: 827691 | G52: =F52*(1+((G18-F18)/F18)) -> 947412.78 | H52: =G52*(1+((H18-G18)/G18)) -> 1066789 | I52: =H52*(1+((I18-H18)/H18)) -> 1187733.9 | J52: =I52*(1+((J18-I18)/I18)) -> 1313676.1 | K52: =J52*(1+((K18-J18)/J18)) -> 1441590.8
C53: Other current assets | E53: 29707 | F53: 42776 | G53: =F53*(1+G39) -> 49192.4 | H53: =G53*(1+H39) -> 55587.412 | I53: =H53*(1+I39) -> 62257.901 | J53: =I53*(1+J39) -> 69106.271 | K53: =J53*(1+K39) -> 76016.898
C54: Income tax receivable | E54: 9960 | F54: 10182 | G54: =F54 -> 10182 | H54: =G54 -> 10182 | I54: =H54 -> 10182 | J54: =I54 -> 10182 | K54: =J54 -> 10182
C55: Total current assets | E55: =SUM(E49:E54) -> 2485134 | F55: =SUM(F49:F54) -> 2896459 | G55: =SUM(G49:G54) -> 3091794.1 | H55: =SUM(H49:H54) -> 3475616.3 | I55: =SUM(I49:I54) -> 3872398.6 | J55: =SUM(J49:J54) -> 4281533.9 | K55: =SUM(K49:K54) -> 4695216.1
C56: Property, plant & equipment | E56: 568607 | F56: 579971 | G56: =G125 -> 595141.39 | H56: =H125 -> 611690.9 | I56: =I125 -> 628929.98 | J56: =J125 -> 646858.62 | K56: =K125 -> 664787.26
C57: Operating lease right of use asset | E57: 172206 | F57: 222151 | G57: =F57 -> 222151 | H57: =G57 -> 222151 | I57: =H57 -> 222151 | J57: =I57 -> 222151 | K57: =J57 -> 222151
C58: Customer relationships | E58: 1004701 | F58: 920432 | G58: =F58+G20*64% -> 842736 | H58: =G58+H20*64% -> 771632 | I58: =H58+I20*64% -> 701488 | J58: =I58+J20*64% -> 633392 | K58: =J58+K20*64% -> 565936
C59: Other intangible assets | E59: 291487 | F59: 244877 | G59: =F59+G20*36% -> 201173 | H59: =G59+H20*36% -> 161177 | I59: =H59+I20*36% -> 121721 | J59: =I59+J20*36% -> 83417 | K59: =J59+K20*36% -> 45473
C60: Goodwill | E60: 1685970 | F60: 1684255 | G60: =F60 -> 1684255 | H60: =G60 -> 1684255 | I60: =H60 -> 1684255 | J60: =I60 -> 1684255 | K60: =J60 -> 1684255
C61: Deferred income tax assets | E61: 1079 | F61: 2832 | G61: =F61 -> 2832 | H61: =G61 -> 2832 | I61: =H61 -> 2832 | J61: =I61 -> 2832 | K61: =J61 -> 2832
C62: Other non current assets | E62: 4417 | F62: 6434 | G62: =F62*(1+G39) -> 7399.1 | H62: =G62*(1+H39) -> 8360.983 | I62: =H62*(1+I39) -> 9364.301 | J62: =I62*(1+J39) -> 10394.374 | K62: =J62*(1+K39) -> 11433.811
C63: Total assets | E63: =SUM(E55:E62) -> 6213601 | F63: =SUM(F55:F62) -> 6557411 | G63: =SUM(G55:G62) -> 6647481.6 | H63: =SUM(H55:H62) -> 6937715.2 | I63: =SUM(I55:I62) -> 7243139.8 | J63: =SUM(J55:J62) -> 7564833.9 | K63: =SUM(K55:K62) -> 7892084.2
C64: LIABILITIES AND STOCKHOLDERS' EQUITY
C65: Current Liabilities
C66: Accounts payable | E66: 645701 | F66: 679772 | G66: =F66*(1+(G18-F18)/F18) -> 778097.96 | H66: =G66*(1+(H18-G18)/G18) -> 876140.14 | I66: =H66*(1+(I18-H18)/H18) -> 975470.58 | J66: =I66*(1+(J18-I18)/I18) -> 1078905.3 | K66: =J66*(1+(K18-J18)/J18) -> 1183960
C67: Accrued expenses and other current liabilities | E67: 99572 | F67: 91499 | G67: =F67*(1+G39) -> 105223.85 | H67: =G67*(1+H39) -> 118902.95 | I67: =H67*(1+I39) -> 133171.3 | J67: =I67*(1+J39) -> 147820.15 | K67: =J67*(1+K39) -> 162602.16
C68: Accrued employ costs | E68: 79134 | F68: 74008 | G68: =F68*(1+G39) -> 85109.2 | H68: =G68*(1+H39) -> 96173.396 | I68: =H68*(1+I39) -> 107714.2 | J68: =I68*(1+J39) -> 119562.77 | K68: =J68*(1+K39) -> 131519.04
C69: Operating lease liabilities, current | E69: 17663 | F69: 22308 | G69: =F69 -> 22308 | H69: =G69 -> 22308 | I69: =H69 -> 22308 | J69: =I69 -> 22308 | K69: =J69 -> 22308
C70: Due to related parties | E70: 1345 | F70: 438 | G70: =F70 -> 438 | H70: =G70 -> 438 | I70: =H70 -> 438 | J70: =I70 -> 438 | K70: =J70 -> 438
C71: Contract liabilities | E71: 400025 | F71: 411321 | G71: =F71*(1+G39) -> 473019.15 | H71: =G71*(1+H39) -> 534511.64 | I71: =H71*(1+I39) -> 598653.04 | J71: =I71*(1+J39) -> 664504.87 | K71: =J71*(1+K39) -> 730955.36
C72: Income taxes payable, current | E72: 6655 | F72: 13547 | G72: =F72 -> 13547 | H72: =G72 -> 13547 | I72: =H72 -> 13547 | J72: =I72 -> 13547 | K72: =J72 -> 13547
C73: Long-term debt, current portion | E73: 23449 | F73: 23444 | G73: =F73 -> 23444 | H73: =G73 -> 23444 | I73: =H73 -> 23444 | J73: =I73 -> 23444 | K73: =J73 -> 23444
C74: Total current liabilities | E74: =SUM(E66:E73) -> 1273544 | F74: =SUM(F66:F73) -> 1316337 | G74: =SUM(G66:G73) -> 1501187.2 | H74: =SUM(H66:H73) -> 1685465.1 | I74: =SUM(I66:I73) -> 1874746.1 | J74: =SUM(J66:J73) -> 2070530.1 | K74: =SUM(K66:K73) -> 2268773.6
C75: Long term debt | E75: 2207977 | F75: 2191161 | G75: =F75-F73 -> 2167717 | H75: =G75-G73 -> 2144273 | I75: =H75-H73 -> 2120829 | J75: =I75-I73 -> 2097385 | K75: =J75-J73 -> 2073941
C76: Operating Lease Liabilities Non Current | E76: 164224 | F76: 212365 | G76: =F76 -> 212365 | H76: =G76 -> 212365 | I76: =H76 -> 212365 | J76: =I76 -> 212365 | K76: =J76 -> 212365
C77: Deferred income tax liabilities | E77: 169824 | F77: 157206 | G77: =F77 -> 157206 | H77: =G77 -> 157206 | I77: =H77 -> 157206 | J77: =I77 -> 157206 | K77: =J77 -> 157206
C78: Income tax payable, non-current | E78: 0 | F78: 5770 | G78: =F78 -> 5770 | H78: =G78 -> 5770 | I78: =H78 -> 5770 | J78: =I78 -> 5770 | K78: =J78 -> 5770
C79: Other non current liabilities | E79: 24628 | F79: 7261 | G79: =F79*(1+G39) -> 8350.15 | H79: =G79*(1+H39) -> 9435.6695 | I79: =H79*(1+I39) -> 10567.95 | J79: =I79*(1+J39) -> 11730.424 | K79: =J79*(1+K39) -> 12903.467
C80: Total liabilities | E80: =SUM(E74:E79) -> 3840197 | F80: =SUM(F74:F79) -> 3890100 | G80: =SUM(G74:G79) -> 4052595.3 | H80: =SUM(H74:H79) -> 4214514.8 | I80: =SUM(I74:I79) -> 4381484.1 | J80: =SUM(J74:J79) -> 4554986.5 | K80: =SUM(K74:K79) -> 4730959
C81: Commitments and contingencies
C82: Stockholders Equity:
C83: Common stock | E83: 3345 | F83: 3345 | G83: =F83 -> 3345 | H83: =G83 -> 3345 | I83: =H83 -> 3345 | J83: =I83 -> 3345 | K83: =J83 -> 3345
C84: Preferred stock | E84: 0 | F84: 0 | G84: 0 | H84: 0 | I84: 0 | J84: 0 | K84: 0
C85: Adittional paid-in capital | E85: 3944802 | F85: 3958039
C86: Accumulated deficit | E86: =-1563321 -> -1563321 | F86: -1285904
C87: Accumulated other comprehensive loss | E87: =-11422 -> -11422 | F87: -8169
C88: Treasury stock | E88: 0 | F88: 0 | G88: 0 | H88: 0 | I88: 0 | J88: 0 | K88: 0
C89: Total equity | E89: =SUM(E83:E88) -> 2373404 | F89: =SUM(F83:F88) -> 2667311
C90: Total liabilities and stockholders' equity | E90: =SUM(E89,E80) -> 6213601 | F90: =SUM(F89,F80) -> 6557411
C92: Balance check | E92: =E63-E90 -> 0 | F92: =F63-F90 -> 0 | G92: =G63-G90 -> 6647481.6 | H92: =H63-H90 -> 6937715.2 | I92: =I63-I90 -> 7243139.8 | J92: =J63-J90 -> 7564833.9 | K92: =K63-K90 -> 7892084.2
C94: CASH FLOW STATEMENT
C95: =C14 -> Fiscal year | G95: =G14 -> 2026 | H95: =H14 -> 2027 | I95: =I14 -> 2028 | J95: =J14 -> 2029 | K95: =K14 -> 2030
C96: =C15 -> Fiscal year end date | G96: =G15 -> 46387 | H96: =H15 -> 46752 | I96: =I15 -> 47118 | J96: =J15 -> 47483 | K96: =K15 -> 47848
C98: Net income | G98: =G31 -> 489359.84 | H98: =H31 -> 596172.82 | I98: =I31 -> 718543.87 | J98: =J31 -> 838408.36 | K98: =K31 -> 955219.9
C99: Depreciation and amortization | G99: =G33 -> 216229.61 | H99: =H33 -> 214550.49 | I99: =I33 -> 217360.92 | J99: =J33 -> 218471.36 | K99: =K33 -> 217471.36 | M99: Reference from the I/S
C100: Stock based compensation | G100: =G35 -> 0 | H100: =H35 -> 0 | I100: =I35 -> 0 | J100: =J35 -> 0 | K100: =K35 -> 0
C101: Decreases / (Increases) in working capital assets | G101: =F50+F51+F52+F53-G50-G51-G52-G53 -> -385052.13 | H101: =G50+G51+G52+G53-H50-H51-H52-H53 -> -383822.16 | I101: =H50+H51+H52+H53-I50-I51-I52-I53 -> -396782.27 | J101: =I50+I51+I52+I53-J50-J51-J52-J53 -> -409135.3 | K101: =J50+J51+J52+J53-K50-K51-K52-K53 -> -413682.27
C102: Increases / (Decreases) in working capital liabilities | G102: =F50+F51+F52+F53-G50-G51-G52-G53 -> -385052.13 | H102: =H66+H67+H68+H71-G66-G67-G68-G71 -> 184277.96 | I102: =I66+I67+I68+I71-H66-H67-H68-H71 -> 189281 | J102: =J66+J67+J68+J71-I66-I67-I68-I71 -> 195783.96 | K102: =K66+K67+K68+K71-J66-J67-J68-J71 -> 198243.48
C103: Other non current assets | G103: =G62 -> 7399.1 | H103: =H62 -> 8360.983 | I103: =I62 -> 9364.301 | J103: =J62 -> 10394.374 | K103: =K62 -> 11433.811 | M103: Reference from schedule NOT the B/S: Only include 'Additions' (as outflow)
C104: Other non current liabilities | G104: =G79 -> 8350.15 | H104: =H79 -> 9435.6695 | I104: =I79 -> 10567.95 | J104: =J79 -> 11730.424 | K104: =K79 -> 12903.467
C105: Cash from operating activities | G105: =SUM(G98:G104) -> -48765.554 | H105: =SUM(H98:H104) -> 628975.77 | I105: =SUM(I98:I104) -> 748335.78 | J105: =SUM(J98:J104) -> 865653.18 | K105: =SUM(K98:K104) -> 981589.74
C107: Capital expenditures | G107: =G123 -> 110000 | H107: =H123 -> 120000 | I107: =I123 -> 125000 | J107: =J123 -> 130000 | K107: =K123 -> 130000 | M107: Reference from PP&E schedule
C108: Cash from investing activities | G108: =G107 -> 110000 | H108: =H107 -> 120000 | I108: =I107 -> 125000 | J108: =J107 -> 130000 | K108: =K107 -> 130000
C110: Long term debt | G110: =F73+F75-G73-G75 -> 23444 | H110: =G73+G75-H73-H75 -> 23444 | I110: =H73+H75-I73-I75 -> 23444 | J110: =I73+I75-J73-J75 -> 23444 | K110: =J73+J75-K73-K75 -> 23444
C111: Revolver | G111: =-G155 -> -274395.45 | H111: =-H155 -> -772419.77 | I111: =-I155 -> -896779.78 | J111: =-J155 -> -1019097.2 | K111: =-K155 -> -1135033.7 | M111: Reference from B/S
C112: Share repurchases | G112: =G144 -> 0 | H112: =H144 -> 0 | I112: =I144 -> 0 | J112: =J144 -> 0 | K112: =K144 -> 0 | M112: Reference from Retained Earnings schedule
...

Sheet v2
B2: X | C2: ="Financial Statement Model for "&D5 -> Financial Statement Model for StandardAero
C3: $ in thousands except per share
C5: Company name | D5: StandardAero
C6: Ticker | D6: SARO
D7: 1
C8: Latest closing share price | D8: 25.59
C9: Latest closing share price date | D9: 46119
C10: Latest fiscal year end date | D10: 46022
C11: Shares outstanding (millions) | D11: 334321
B13: X | C13: INCOME STATEMENT
C14: Fiscal year | D14: =E14-1 -> 2023 | E14: =F14-1 -> 2024 | F14: =YEAR(D10) -> 2025 | G14: =F14+1 -> 2026 | H14: =G14+1 -> 2027 | I14: =H14+1 -> 2028 | J14: =I14+1 -> 2029 | K14: =J14+1 -> 2030
C15: Fiscal year end date | D15: =EOMONTH(E15,-12) -> 45291 | E15: =EOMONTH(F15,-12) -> 45657 | F15: =D10 -> 46022 | G15: =EOMONTH(F15,12) -> 46387 | H15: =EOMONTH(G15,12) -> 46752 | I15: =EOMONTH(H15,12) -> 47118 | J15: =EOMONTH(I15,12) -> 47483 | K15: =EOMONTH(J15,12) -> 47848 | M15: Comments
C17: Revenue | D17: 4563284 | E17: 5237161 | F17: 6062513 | G17: =F17*(1+G39) -> 6971889.9 | H17: =G17*(1+H39) -> 7878235.6 | I17: =H17*(1+I39) -> 8823623.9 | J17: =I17*(1+J39) -> 9794222.6 | K17: =J17*(1+K39) -> 10773645
C18: Cost of sales | D18: -3927965 | E18: -4483019 | F18: -5165060 | G18: =G19-G17 -> -5912162.7 | H18: =H19-H17 -> -6657109.1 | I18: =I19-I17 -> -7411844.1 | J18: =J19-J17 -> -8197764.3 | K18: =K19-K17 -> -8995993.4
C19: Gross Profit | D19: =SUM(D17:D18) -> 635319 | E19: =SUM(E17:E18) -> 754142 | F19: =SUM(F17:F18) -> 897453 | G19: =G17*G40 -> 1059727.3 | H19: =H17*H40 -> 1221126.5 | I19: =I17*I40 -> 1411779.8 | J19: =J17*J40 -> 1596458.3 | K19: =K17*K40 -> 1777651.4
C20: Amortisation of intangible assets | D20: -93681 | E20: -95457 | F20: -98681 | G20: =-121400*0.75 -> -91050 | H20: =0.75*-111100 -> -83325 | I20: =0.75*-109600 -> -82200 | J20: =-106400*0.75 -> -79800 | K20: =0.75*-105400 -> -79050 | M20: Given in 10k
C21: Selling, general & administrative | D21: -202766 | E21: -254092 | F21: -247703 | G21: =-G17*G41 -> -285847.49 | H21: =-H17*H41 -> -315129.43 | I21: =-I17*I41 -> -344121.33 | J21: =-J17*J41 -> -372180.46 | K21: =-K17*K41 -> -398624.86
C22: Acquisition Cost | D22: -1514 | E22: -1374 | F22: 0 | G22: =F22 -> 0 | H22: =G22 -> 0 | I22: =H22 -> 0 | J22: =I22 -> 0 | K22: =J22 -> 0
C23: Operating profit (EBIT) | D23: =SUM(D19:D22) -> 337358 | E23: =SUM(E19:E22) -> 403219 | F23: =SUM(F19:F22) -> 551069 | G23: =SUM(G19:G22) -> 682829.78 | H23: =SUM(H19:H22) -> 822672.1 | I23: =SUM(I19:I22) -> 985458.49 | J23: =SUM(J19:J22) -> 1144477.8 | K23: =SUM(K19:K22) -> 1299976.5
C24: Interest income | D24: 0 | E24: 0 | F24: 0 | G24: =G176 -> 6287.8853 | H24: =H176 -> 10928.078 | I24: =I176 -> 17202.773 | J24: =J176 -> 25229.141 | K24: =K176 -> 35032.364
C25: Interest expense | D25: -309645 | E25: -282507 | F25: -174217 | G25: =G162 -> -149796.04 | H25: =H162 -> -148201.85 | I25: =I162 -> -146607.66 | J25: =J162 -> -145013.47 | K25: =K162 -> -143419.28
C26: Refinancing costs | D26: -19921 | E26: -23700 | F26: 0 | G26: =F26 -> 0 | H26: =G26 -> 0 | I26: =H26 -> 0 | J26: =I26 -> 0 | K26: =J26 -> 0
C27: Loss on debt extinguishment | D27: -6182 | E27: -15255 | F27: 0 | G27: =F27 -> 0 | H27: =G27 -> 0 | I27: =H27 -> 0 | J27: =I27 -> 0 | K27: =J27 -> 0
C28: Other expense, net | D28: 3509 | E28: 0 | F28: 0 | G28: 0 | H28: 0 | I28: 0 | J28: 0 | K28: 0
C29: Pretax profit | D29: =SUM(D23:D28) -> 5119 | E29: =SUM(E23:E28) -> 81757 | F29: =SUM(F23:F28) -> 376852 | G29: =SUM(G23:G28) -> 539321.63 | H29: =SUM(H23:H28) -> 685398.33 | I29: =SUM(I23:I28) -> 856053.61 | J29: =SUM(J23:J28) -> 1024693.5 | K29: =SUM(K23:K28) -> 1191589.6
C30: Taxes | D30: -40180 | E30: -70783 | F30: -99435 | G30: =-G29*G42 -> -134830.41 | H30: =-H29*H42 -> -171349.58 | I30: =-I29*I42 -> -214013.4 | J30: =-J29*J42 -> -256173.37 | K30: =-K29*K42 -> -297897.41
C31: Net income | D31: =SUM(D29:D30) -> -35061 | E31: =SUM(E29:E30) -> 10974 | F31: =SUM(F29:F30) -> 277417 | G31: =SUM(G29:G30) -> 404491.22 | H31: =SUM(H29:H30) -> 514048.74 | I31: =SUM(I29:I30) -> 642040.21 | J31: =SUM(J29:J30) -> 768520.12 | K31: =SUM(K29:K30) -> 893692.22
C33: Depreciation & amortization | D33: 197104 | E33: 188164 | F33: 193664 | G33: =G132 -> 172741.4 | H33: =H132 -> 175636.28 | I33: =I132 -> 185588.64 | J33: =J132 -> 194561.39 | K33: =K132 -> 205287.52
C34: EBITDA | D34: =D23+D33 -> 534462 | E34: =E23+E33 -> 591383 | F34: =F23+F33 -> 744733 | G34: =G23+G33 -> 855571.18 | H34: =H23+H33 -> 998308.38 | I34: =I23+I33 -> 1171047.1 | J34: =J23+J33 -> 1339039.2 | K34: =K23+K33 -> 1505264.1
C35: Stock based compensation | D35: 0 | E35: 0 | F35: 0 | G35: 0 | H35: 0 | I35: 0 | J35: 0 | K35: 0
C36: Adjusted EBITDA | D36: =D34+D35 -> 534462 | E36: =E34+E35 -> 591383 | F36: =F34+F35 -> 744733 | G36: =G34+G35 -> 855571.18 | H36: =H34+H35 -> 998308.38 | I36: =I34+I35 -> 1171047.1 | J36: =J34+J35 -> 1339039.2 | K36: =K34+K35 -> 1505264.1
C38: Growth rates & margins
C39: Revenue growth | E39: =(E17-D17)/D17 -> 0.14767369 | F39: =(F17-E17)/E17 -> 0.15759531 | G39: 0.15 | H39: 0.13 | I39: 0.12 | J39: 0.11 | K39: 0.1 | M39: LEAP/CFM56 shop visits ramping; ~80% of revenue under long-term agreements; aging installed base drives MRO demand through 2030; military spending elevated due to geopolitical tensions; business aviation fleet growth
C40: Gross profit margin | D40: =D19/D17 -> 0.13922408 | E40: =E19/E17 -> 0.14399825 | F40: =F19/F17 -> 0.14803317 | G40: 0.152 | H40: 0.155 | I40: 0.16 | J40: 0.163 | K40: 0.165 | M40: LEAP learning curve progressively reduces industrialization costs; mix shift toward higher-margin Component Repair Services; operating leverage on fixed overhead as volumes scale; partially offset by material cost inflation pass-through
C41: SG&A % of sales | D41: =-D21/D17 -> 0.044434228 | E41: =-E21/E17 -> 0.048517126 | F41: =-F21/F17 -> 0.040858139 | G41: 0.041 | H41: 0.04 | I41: 0.039 | J41: 0.038 | K41: 0.037 | M41: SG&A already declined to 4.1% in 2025 (from 4.9% in 2024). Post-IPO one-time costs are behind the company. Further leverage expected as revenue scales against relatively fixed corporate overhead and sales force
C42: Tax rate | D42: =-D30/D29 -> 7.8491893 | E42: =-E30/E29 -> 0.86577296 | F42: =-F30/F29 -> 0.2638569 | G42: 0.25 | H42: 0.25 | I42: 0.25 | J42: 0.25 | K42: 0.25 | M42: 2025 effective rate of 26.4% includes GILTI, state taxes (California heavy), and changes in uncertain tax benefits. OBBBA provisions (signed Jul 4, 2025) restore favorable business tax treatment in 2026–2027 — rate likely drifts toward 24–26% as Canada/foreign mix optimizes and interest carryforwards begin to release
B44: X | C44: BALANCE SHEET
C45: =C14 -> Fiscal year | D45: =D14 -> 2023 | E45: =E14 -> 2024 | F45: =F14 -> 2025 | G45: =G14 -> 2026 | H45: =H14 -> 2027 | I45: =I14 -> 2028 | J45: =J14 -> 2029 | K45: =K14 -> 2030
C46: =C15 -> Fiscal year end date | D46: =D15 -> 45291 | E46: =E15 -> 45657 | F46: =F15 -> 46022 | G46: =G15 -> 46387 | H46: =H15 -> 46752 | I46: =I15 -> 47118 | J46: =J15 -> 47483 | K46: =K15 -> 47848
C47: ASSETS
C48: Current Assets
C49: Cash & equivalents, ST and LT marketable securities | E49: 102581 | F49: 289717 | G49: =F49+G116 -> 548667.7 | H49: =G49+H116 -> 908409.37 | I49: =H49+I116 -> 1385293.6 | J49: =I49+J116 -> 1978591.8 | K49: =J49+K116 -> 2692390
C50: Accounts receivable | E50: 580668 | F50: 654390 | G50: =F50*(1+G39) -> 752548.5 | H50: =G50*(1+H39) -> 850379.8 | I50: =H50*(1+I39) -> 952425.38 | J50: =I50*(1+J39) -> 1057192.2 | K50: =J50*(1+K39) -> 1162911.4
C51: Contract Assets | E51: 915200 | F51: 1071703 | G51: =F51*(1+G39) -> 1232458.4 | H51: =G51*(1+H39) -> 1392678 | I51: =H51*(1+I39) -> 1559799.4 | J51: =I51*(1+J39) -> 1731377.3 | K51: =J51*(1+K39) -> 1904515.1
C52: Inventories | E52: 847018 | F52: 827691 | G52: =F52*(1+((G18-F18)/F18)) -> 947412.78 | H52: =G52*(1+((H18-G18)/G18)) -> 1066789 | I52: =H52*(1+((I18-H18)/H18)) -> 1187733.9 | J52: =I52*(1+((J18-I18)/I18)) -> 1313676.1 | K52: =J52*(1+((K18-J18)/J18)) -> 1441590.8
C53: Other current assets | E53: 29707 | F53: 42776 | G53: =F53*(1+G39) -> 49192.4 | H53: =G53*(1+H39) -> 55587.412 | I53: =H53*(1+I39) -> 62257.901 | J53: =I53*(1+J39) -> 69106.271 | K53: =J53*(1+K39) -> 76016.898
C54: Income tax receivable | E54: 9960 | F54: 10182 | G54: =F54 -> 10182 | H54: =G54 -> 10182 | I54: =H54 -> 10182 | J54: =I54 -> 10182 | K54: =J54 -> 10182
C55: Total current assets | E55: =SUM(E49:E54) -> 2485134 | F55: =SUM(F49:F54) -> 2896459 | G55: =SUM(G49:G54) -> 3540461.8 | H55: =SUM(H49:H54) -> 4284025.7 | I55: =SUM(I49:I54) -> 5157692.2 | J55: =SUM(J49:J54) -> 6160125.7 | K55: =SUM(K49:K54) -> 7287606.1
C56: Property, plant & equipment | E56: 568607 | F56: 579971 | G56: =G125 -> 593039.6 | H56: =H125 -> 607807.12 | I56: =I125 -> 624346.74 | J56: =J125 -> 642705.72 | K56: =K125 -> 662900.59
C57: Operating lease right of use asset | E57: 172206 | F57: 222151 | G57: =F57 -> 222151 | H57: =G57 -> 222151 | I57: =H57 -> 222151 | J57: =I57 -> 222151 | K57: =J57 -> 222151
C58: Customer relationships | E58: 1004701 | F58: 920432 | G58: =F58+G20*64% -> 862160 | H58: =G58+H20*64% -> 808832 | I58: =H58+I20*64% -> 756224 | J58: =I58+J20*64% -> 705152 | K58: =J58+K20*64% -> 654560
C59: Other intangible assets | E59: 291487 | F59: 244877 | G59: =F59+G20*36% -> 212099 | H59: =G59+H20*36% -> 182102 | I59: =H59+I20*36% -> 152510 | J59: =I59+J20*36% -> 123782 | K59: =J59+K20*36% -> 95324
C60: Goodwill | E60: 1685970 | F60: 1684255 | G60: =F60 -> 1684255 | H60: =G60 -> 1684255 | I60: =H60 -> 1684255 | J60: =I60 -> 1684255 | K60: =J60 -> 1684255
C61: Deferred income tax assets | E61: 1079 | F61: 2832 | G61: =F61 -> 2832 | H61: =G61 -> 2832 | I61: =H61 -> 2832 | J61: =I61 -> 2832 | K61: =J61 -> 2832
C62: Other non current assets | E62: 4417 | F62: 6434 | G62: =F62*(1+G39) -> 7399.1 | H62: =G62*(1+H39) -> 8360.983 | I62: =H62*(1+I39) -> 9364.301 | J62: =I62*(1+J39) -> 10394.374 | K62: =J62*(1+K39) -> 11433.811
C63: Total assets | E63: =SUM(E55:E62) -> 6213601 | F63: =SUM(F55:F62) -> 6557411 | G63: =SUM(G55:G62) -> 7124397.5 | H63: =SUM(H55:H62) -> 7800365.8 | I63: =SUM(I55:I62) -> 8609375.2 | J63: =SUM(J55:J62) -> 9551397.8 | K63: =SUM(K55:K62) -> 10621063
C64: LIABILITIES AND STOCKHOLDERS' EQUITY
C65: Current Liabilities
C66: Accounts payable | E66: 645701 | F66: 679772 | G66: =F66*(1+(G18-F18)/F18) -> 778097.96 | H66: =G66*(1+(H18-G18)/G18) -> 876140.14 | I66: =H66*(1+(I18-H18)/H18) -> 975470.58 | J66: =I66*(1+(J18-I18)/I18) -> 1078905.3 | K66: =J66*(1+(K18-J18)/J18) -> 1183960
C67: Accrued expenses and other current liabilities | E67: 99572 | F67: 91499 | G67: =F67*(1+G39) -> 105223.85 | H67: =G67*(1+H39) -> 118902.95 | I67: =H67*(1+I39) -> 133171.3 | J67: =I67*(1+J39) -> 147820.15 | K67: =J67*(1+K39) -> 162602.16
C68: Accrued employ costs | E68: 79134 | F68: 74008 | G68: =F68*(1+G39) -> 85109.2 | H68: =G68*(1+H39) -> 96173.396 | I68: =H68*(1+I39) -> 107714.2 | J68: =I68*(1+J39) -> 119562.77 | K68: =J68*(1+K39) -> 131519.04
C69: Operating lease liabilities, current | E69: 17663 | F69: 22308 | G69: =F69 -> 22308 | H69: =G69 -> 22308 | I69: =H69 -> 22308 | J69: =I69 -> 22308 | K69: =J69 -> 22308
C70: Due to related parties | E70: 1345 | F70: 438 | G70: =F70 -> 438 | H70: =G70 -> 438 | I70: =H70 -> 438 | J70: =I70 -> 438 | K70: =J70 -> 438
C71: Contract liabilities | E71: 400025 | F71: 411321 | G71: =F71*(1+G39) -> 473019.15 | H71: =G71*(1+H39) -> 534511.64 | I71: =H71*(1+I39) -> 598653.04 | J71: =I71*(1+J39) -> 664504.87 | K71: =J71*(1+K39) -> 730955.36
C72: Income taxes payable, current | E72: 6655 | F72: 13547 | G72: =F72 -> 13547 | H72: =G72 -> 13547 | I72: =H72 -> 13547 | J72: =I72 -> 13547 | K72: =J72 -> 13547
C73: Long-term debt, current portion | E73: 23449 | F73: 23444 | G73: =F73 -> 23444 | H73: =G73 -> 23444 | I73: =H73 -> 23444 | J73: =I73 -> 23444 | K73: =J73 -> 23444
C74: Total current liabilities | E74: =SUM(E66:E73) -> 1273544 | F74: =SUM(F66:F73) -> 1316337 | G74: =SUM(G66:G73) -> 1501187.2 | H74: =SUM(H66:H73) -> 1685465.1 | I74: =SUM(I66:I73) -> 1874746.1 | J74: =SUM(J66:J73) -> 2070530.1 | K74: =SUM(K66:K73) -> 2268773.6
C75: Long term debt | E75: 2207977 | F75: 2191161 | G75: =F75-F73 -> 2167717 | H75: =G75-G73 -> 2144273 | I75: =H75-H73 -> 2120829 | J75: =I75-I73 -> 2097385 | K75: =J75-J73 -> 2073941
C76: Operating Lease Liabilities Non Current | E76: 164224 | F76: 212365 | G76: =F76 -> 212365 | H76: =G76 -> 212365 | I76: =H76 -> 212365 | J76: =I76 -> 212365 | K76: =J76 -> 212365
C77: Deferred income tax liabilities | E77: 169824 | F77: 157206 | G77: =F77 -> 157206 | H77: =G77 -> 157206 | I77: =H77 -> 157206 | J77: =I77 -> 157206 | K77: =J77 -> 157206
C78: Income tax payable, non-current | E78: 0 | F78: 5770 | G78: =F78 -> 5770 | H78: =G78 -> 5770 | I78: =H78 -> 5770 | J78: =I78 -> 5770 | K78: =J78 -> 5770
C79: Other non current liabilities | E79: 24628 | F79: 7261 | G79: =F79*(1+G39) -> 8350.15 | H79: =G79*(1+H39) -> 9435.6695 | I79: =H79*(1+I39) -> 10567.95 | J79: =I79*(1+J39) -> 11730.424 | K79: =J79*(1+K39) -> 12903.467
C80: Total liabilities | E80: =SUM(E74:E79) -> 3840197 | F80: =SUM(F74:F79) -> 3890100 | G80: =SUM(G74:G79) -> 4052595.3 | H80: =SUM(H74:H79) -> 4214514.8 | I80: =SUM(I74:I79) -> 4381484.1 | J80: =SUM(J74:J79) -> 4554986.5 | K80: =SUM(K74:K79) -> 4730959
C81: Commitments and contingencies | E81: 0 | F81: 0 | G81: =G155 -> 0 | H81: =H155 -> 0 | I81: =I155 -> 0 | J81: =J155 -> 0 | K81: =K155 -> 0
C82: Stockholders Equity:
C83: Common stock | E83: 3345 | F83: 3345 | G83: =F83 -> 3345 | H83: =F83 -> 3345 | I83: =F83 -> 3345 | J83: =F83 -> 3345 | K83: =F83 -> 3345
C84: Preferred stock | E84: 0 | F84: 0 | G84: 0 | H84: 0 | I84: 0 | J84: 0 | K84: 0
C85: Adittional paid-in capital | E85: 3944802 | F85: 3958039 | G85: =F85 -> 3958039 | H85: =G85 -> 3958039 | I85: =H85 -> 3958039 | J85: =I85 -> 3958039 | K85: =J85 -> 3958039
C86: Accumulated deficit | E86: -1563321 | F86: -1285904 | G86: =F86+G31 -> -881412.78 | H86: =G86+H31 -> -367364.04 | I86: =H86+I31 -> 274676.17 | J86: =I86+J31 -> 1043196.3 | K86: =J86+K31 -> 1936888.5
